Workbook
Name 清单_付款主体: 选项!$A$2:$A$4
Name 清单_物流商: 供应商列表!$A$4:$A$25
Name 清单_费用归属: 选项!$C$2:$C$14
Name 清单_业务线: 选项!$B$2:$B$11
Name 清单_结算类型: 选项!$E$2:$E$3
Name 清单_状态: 选项!$G$2:$G$7

Sheet 填表说明
A1: 物流费用计提表模板 v2.1 —— 使用说明(重构方案 v2.1 配套样表)
A3: 六张表分工
A4: ① 填表说明 | B4: 本页。物流部只需要看本页+填② 计提明细表。
A5: ② 计提明细表 | B5: 唯一手填。每行一笔费用:选 付款主体/物流商/费用归属/业务线 + 填含税金额(黄格)。税率/未税/税额/全称/摘要 全部自动,请勿改灰格。右侧浅绿5列=做账维度(财务看/改,物流部不用管)。
A6: ③ 做账去向表 | B6: 财务/审批视角:本月费用准备做到 哪个科目×哪个业务线×哪个部门,全公式自动按明细表维度汇总;行=历史账证实证的维度组合。不用填。
A7: ④ 供应商列表 | B7: 物流商身份+渠道+13类费用归属税率矩阵。由财务工具按月签发快照,物流部勿改;缺物流商请联系财务在工具里新增。
A8: ⑤ 物流商费用汇总表 | B8: 全自动汇总:各主体×税率(9/6/13%)+含税合计+五档进度。不用填。
A9: ⑥ 费用归属表(快照) | B9: 财务口径:13类费用归属各自怎么做账。由财务工具维护,此处为只读快照。
A11: 13 类费用归属怎么选(核心,每类科目唯一)
A12: 销售出库费用 | B12: 各业务线销售发货运费;装卸费没单列在账单里时,含在这里,不用拆。
A13: 成品入库费用 / 原料入库费用 | B13: 入库方向按料件分:代工厂成品回仓/电商仓成品入仓=成品;孝感工厂采购到付/小料原料=原料。拿不准问财务。
A14: 成品仓储费用 / 原料仓储费用 | B14: 外仓仓储费按存的是成品还是原料分。
A15: 成品调拨费用 / 原料调拨费用 | B15: 仓与仓之间转运。
A16: 出库/成品入库/原料入库 装卸费用 | B16: 仅当账单把装卸费单独列一行时才用(目前只有天鹰);平时装卸含在销售出库里。
A17: 研发设备采购 | B17: 研发外购、研发中试的运费。
A18: 设备调拨费用 | B18: 设备转移、设备仓租。科目部门由财务录入时按每笔需求定,物流部只管填金额+业务描述(写清什么设备、从哪到哪、给谁用)。
A19: 其它 | B19: 捐赠/报废、原料销售运费等,选它并在备注里写清楚。
A21: 特殊口径
A22: 山姆业务 | B22: 不用单独标山姆:山姆鲜食→业务线选「鲜食」;山姆零售→选「山姆零售」。系统自动挂 TO C。
A23: 海外业务 | B23: 业务线选「海外」,并在「业务描述」写明 到岸前/到岸后、自产/外采——这决定付款主体归属。
A24: kikiherb | B24: 暂选 业务线=零售,业务描述写 kikiherb(口径确认后模板会更新)。
A25: 非月结 | B25: 结算类型选「非月结」并填经办人(货拉拉、临时用车等)。
A27: 颜色图例
A28: 黄底 | B28: 手填·唯一必填数字(含税金额)
A29: 浅黄底 | B29: 手填·下拉选择或选填文字
A30: 灰底 | B30: 公式自动,勿手改(表已锁定保护)
A31: 蓝底 | B31: 财务工具回填(凭证号/定稿金额),勿手改
A32: 橙底 | B32: 税率特例(与该物流商默认档不同,如易风达/极鲜达仓储6%)
A33: 浅绿底 | B33: 做账维度区(明细表右侧5列:借方科目/部门/费用项目/产品分类/产品项目)——按账证实证规则公式预填,财务可直接改格子,工作台以列值为准;物流部不用管
A34: 绿底 | B34: 财务口径快照,物流部不用管
A36: 提交 | B36: 每月底把本文件发给财务核算。文件名请保持「物流费用计提表_2026-MM」。

Sheet 计提明细表
A1: 物流费用计提 · 计提明细表(唯一手填表) 账期 2026-07 [v2.1 样表·13类费用归属闭环]
A2: 填表须知:黄底=手填(含税金额唯一必填数字);浅黄=下拉/选填;灰底=公式自动(已锁定);蓝底=工具回填;浅绿=做账维度(公式按账证实证规则预填,财务可直接改,工具以列值为准)。一行一笔费用=一张凭证;示例行为 2026-05 真数据机翻,正式使用时清空。 | T2: ── 做账维度区(财务看/改,物流部不用管)──
A3: 账期 | B3: 付款主体 | C3: 物流商简称 | D3: 费用归属 | E3: 业务线 | F3: 业务描述 (摘要用/来源·选填) | G3: 结算类型 | H3: 经办人 | I3: 含税金额 | J3: 税率 | K3: 未税 | L3: 税额 | M3: 物流商全称 | N3: 摘要(公式自动) | O3: 计提凭证号 | P3: 对账定稿金额 | Q3: 计提差异 | R3: 差异处理 | S3: 备注 | T3: 借方科目 | U3: 部门 | V3: 费用项目 | W3: 产品分类 (业务线维度) | X3: 产品项目 (TO C等)
A4: 2026-07 | B4: 深圳星期零 | C4: 顺丰冷运 | D4: 销售出库费用 | E4: 豆蛋制品 | G4: 月结 | I4: 270 | J4: =IFERROR(INDEX(供应商列表!$F$4:$R$25,MATCH(C4,供应商列表!$A$4:$A$25,0),MATCH(D4,供应商列表!$F$3:$R$3,0)),"") | K4: =IFERROR(ROUND(I4/(1+J4),2),"") | L4: =IFERROR(I4-K4,"") | M4: =IFERROR(INDEX(供应商列表!$B$4:$B$25,MATCH(C4,供应商列表!$A$4:$A$25,0)),"") | N4: ="计提"&M4&(MID(A4,6,2)*1)&"月"&IFERROR(INDEX(供应商列表!$E$4:$E$25,MATCH(C4,供应商列表!$A$4:$A$25,0)),"线下")&IF(F4<>"",F4,IF(OR(E4="—",E4=""),"",E4))&IFERROR(INDEX('费用归属表（快照）'!$F$4:$F$16,MATCH(D4,'费用归属表（快照）'!$A$4:$A$16,0)),"") | Q4: =IF(P4="","",P4-I4) | T4: =IF(D4="","",IFERROR(INDEX('费用归属表（快照）'!$C$4:$C$16,MATCH(D4,'费用归属表（快照）'!$A$4:$A$16,0)),"")) | U4: =IF(D4="","",IF(AND(D4="销售出库费用",B4="深圳星期九"),"永续供应中心 0010401",IF(AND(D4="原料入库费用",E4="小料"),"茶饮小料部 0030902",IFERROR(INDEX('费用归属表（快照）'!$D$4:$D$16,MATCH(D4,'费用归属表（快照）'!$A$4:$A$16,0)),"")))) | V4: =IF(D4="","",IFERROR(INDEX('费用归属表（快照）'!$B$4:$B$16,MATCH(D4,'费用归属表（快照）'!$A$4:$A$16,0)),"")) | W4: =IF(OR(E4="",AND(LEFT(T4,4)<>"6601",LEFT(T4,4)<>"6401")),"",IFERROR(IF(INDEX(选项!$I$2:$I$11,MATCH(E4,选项!$H$2:$H$11,0))="","",INDEX(选项!$I$2:$I$11,MATCH(E4,选项!$H$2:$H$11,0))),"")) | X4: =IF(OR(E4="",AND(LEFT(T4,4)<>"6601",LEFT(T4,4)<>"6401")),"",IFERROR(IF(INDEX(选项!$J$2:$J$11,MATCH(E4,选项!$H$2:$H$11,0))="","",INDEX(选项!$J$2:$J$11,MATCH(E4,选项!$H$2:$H$11,0))),""))
A5: 2026-07 | B5: 深圳星期零 | C5: 顺丰冷运 | D5: 原料入库费用 | E5: 小料 | F5: 小料 | G5: 月结 | I5: 1125 | J5: =IFERROR(INDEX(供应商列表!$F$4:$R$25,MATCH(C5,供应商列表!$A$4:$A$25,0),MATCH(D5,供应商列表!$F$3:$R$3,0)),"") | K5: =IFERROR(ROUND(I5/(1+J5),2),"") | L5: =IFERROR(I5-K5,"") | M5: =IFERROR(INDEX(供应商列表!$B$4:$B$25,MATCH(C5,供应商列表!$A$4:$A$25,0)),"") | N5: ="计提"&M5&(MID(A5,6,2)*1)&"月"&IFERROR(INDEX(供应商列表!$E$4:$E$25,MATCH(C5,供应商列表!$A$4:$A$25,0)),"线下")&IF(F5<>"",F5,IF(OR(E5="—",E5=""),"",E5))&IFERROR(INDEX('费用归属表（快照）'!$F$4:$F$16,MATCH(D5,'费用归属表（快照）'!$A$4:$A$16,0)),"") | Q5: =IF(P5="","",P5-I5) | T5: =IF(D5="","",IFERROR(INDEX('费用归属表（快照）'!$C$4:$C$16,MATCH(D5,'费用归属表（快照）'!$A$4:$A$16,0)),"")) | U5: =IF(D5="","",IF(AND(D5="销售出库费用",B5="深圳星期九"),"永续供应中心 0010401",IF(AND(D5="原料入库费用",E5="小料"),"茶饮小料部 0030902",IFERROR(INDEX('费用归属表（快照）'!$D$4:$D$16,MATCH(D5,'费用归属表（快照）'!$A$4:$A$16,0)),"")))) | V5: =IF(D5="","",IFERROR(INDEX('费用归属表（快照）'!$B$4:$B$16,MATCH(D5,'费用归属表（快照）'!$A$4:$A$16,0)),"")) | W5: =IF(OR(E5="",AND(LEFT(T5,4)<>"6601",LEFT(T5,4)<>"6401")),"",IFERROR(IF(INDEX(选项!$I$2:$I$11,MATCH(E5,选项!$H$2:$H$11,0))="","",INDEX(选项!$I$2:$I$11,MATCH(E5,选项!$H$2:$H$11,0))),"")) | X5: =IF(OR(E5="",AND(LEFT(T5,4)<>"6601",LEFT(T5,4)<>"6401")),"",IFERROR(IF(INDEX(选项!$J$2:$J$11,MATCH(E5,选项!$H$2:$H$11,0))="","",INDEX(选项!$J$2:$J$11,MATCH(E5,选项!$H$2:$H$11,0))),""))
A6: 2026-07 | B6: 深圳星期零 | C6: 顺丰冷运 | D6: 销售出库费用 | E6: 小料 | G6: 月结 | I6: 2220 | J6: =IFERROR(INDEX(供应商列表!$F$4:$R$25,MATCH(C6,供应商列表!$A$4:$A$25,0),MATCH(D6,供应商列表!$F$3:$R$3,0)),"") | K6: =IFERROR(ROUND(I6/(1+J6),2),"") | L6: =IFERROR(I6-K6,"") | M6: =IFERROR(INDEX(供应商列表!$B$4:$B$25,MATCH(C6,供应商列表!$A$4:$A$25,0)),"") | N6: ="计提"&M6&(MID(A6,6,2)*1)&"月"&IFERROR(INDEX(供应商列表!$E$4:$E$25,MATCH(C6,供应商列表!$A$4:$A$25,0)),"线下")&IF(F6<>"",F6,IF(OR(E6="—",E6=""),"",E6))&IFERROR(INDEX('费用归属表（快照）'!$F$4:$F$16,MATCH(D6,'费用归属表（快照）'!$A$4:$A$16,0)),"") | Q6: =IF(P6="","",P6-I6) | T6: =IF(D6="","",IFERROR(INDEX('费用归属表（快照）'!$C$4:$C$16,MATCH(D6,'费用归属表（快照）'!$A$4:$A$16,0)),"")) | U6: =IF(D6="","",IF(AND(D6="销售出库费用",B6="深圳星期九"),"永续供应中心 0010401",IF(AND(D6="原料入库费用",E6="小料"),"茶饮小料部 0030902",IFERROR(INDEX('费用归属表（快照）'!$D$4:$D$16,MATCH(D6,'费用归属表（快照）'!$A$4:$A$16,0)),"")))) | V6: =IF(D6="","",IFERROR(INDEX('费用归属表（快照）'!$B$4:$B$16,MATCH(D6,'费用归属表（快照）'!$A$4:$A$16,0)),"")) | W6: =IF(OR(E6="",AND(LEFT(T6,4)<>"6601",LEFT(T6,4)<>"6401")),"",IFERROR(IF(INDEX(选项!$I$2:$I$11,MATCH(E6,选项!$H$2:$H$11,0))="","",INDEX(选项!$I$2:$I$11,MATCH(E6,选项!$H$2:$H$11,0))),"")) | X6: =IF(OR(E6="",AND(LEFT(T6,4)<>"6601",LEFT(T6,4)<>"6401")),"",IFERROR(IF(INDEX(选项!$J$2:$J$11,MATCH(E6,选项!$H$2:$H$11,0))="","",INDEX(选项!$J$2:$J$11,MATCH(E6,选项!$H$2:$H$11,0))),""))
A7: 2026-07 | B7: 深圳星期零 | C7: 顺丰速运 | D7: 销售出库费用 | E7: 植物肉 | G7: 月结 | I7: 384 | J7: =IFERROR(INDEX(供应商列表!$F$4:$R$25,MATCH(C7,供应商列表!$A$4:$A$25,0),MATCH(D7,供应商列表!$F$3:$R$3,0)),"") | K7: =IFERROR(ROUND(I7/(1+J7),2),"") | L7: =IFERROR(I7-K7,"") | M7: =IFERROR(INDEX(供应商列表!$B$4:$B$25,MATCH(C7,供应商列表!$A$4:$A$25,0)),"") | N7: ="计提"&M7&(MID(A7,6,2)*1)&"月"&IFERROR(INDEX(供应商列表!$E$4:$E$25,MATCH(C7,供应商列表!$A$4:$A$25,0)),"线下")&IF(F7<>"",F7,IF(OR(E7="—",E7=""),"",E7))&IFERROR(INDEX('费用归属表（快照）'!$F$4:$F$16,MATCH(D7,'费用归属表（快照）'!$A$4:$A$16,0)),"") | Q7: =IF(P7="","",P7-I7) | T7: =IF(D7="","",IFERROR(INDEX('费用归属表（快照）'!$C$4:$C$16,MATCH(D7,'费用归属表（快照）'!$A$4:$A$16,0)),"")) | U7: =IF(D7="","",IF(AND(D7="销售出库费用",B7="深圳星期九"),"永续供应中心 0010401",IF(AND(D7="原料入库费用",E7="小料"),"茶饮小料部 0030902",IFERROR(INDEX('费用归属表（快照）'!$D$4:$D$16,MATCH(D7,'费用归属表（快照）'!$A$4:$A$16,0)),"")))) | V7: =IF(D7="","",IFERROR(INDEX('费用归属表（快照）'!$B$4:$B$16,MATCH(D7,'费用归属表（快照）'!$A$4:$A$16,0)),"")) | W7: =IF(OR(E7="",AND(LEFT(T7,4)<>"6601",LEFT(T7,4)<>"6401")),"",IFERROR(IF(INDEX(选项!$I$2:$I$11,MATCH(E7,选项!$H$2:$H$11,0))="","",INDEX(选项!$I$2:$I$11,MATCH(E7,选项!$H$2:$H$11,0))),"")) | X7: =IF(OR(E7="",AND(LEFT(T7,4)<>"6601",LEFT(T7,4)<>"6401")),"",IFERROR(IF(INDEX(选项!$J$2:$J$11,MATCH(E7,选项!$H$2:$H$11,0))="","",INDEX(选项!$J$2:$J$11,MATCH(E7,选项!$H$2:$H$11,0))),""))
A8: 2026-07 | B8: 深圳星期零 | C8: 顺丰速运 | D8: 销售出库费用 | E8: 鲜食 | G8: 月结 | I8: 66 | J8: =IFERROR(INDEX(供应商列表!$F$4:$R$25,MATCH(C8,供应商列表!$A$4:$A$25,0),MATCH(D8,供应商列表!$F$3:$R$3,0)),"") | K8: =IFERROR(ROUND(I8/(1+J8),2),"") | L8: =IFERROR(I8-K8,"") | M8: =IFERROR(INDEX(供应商列表!$B$4:$B$25,MATCH(C8,供应商列表!$A$4:$A$25,0)),"") | N8: ="计提"&M8&(MID(A8,6,2)*1)&"月"&IFERROR(INDEX(供应商列表!$E$4:$E$25,MATCH(C8,供应商列表!$A$4:$A$25,0)),"线下")&IF(F8<>"",F8,IF(OR(E8="—",E8=""),"",E8))&IFERROR(INDEX('费用归属表（快照）'!$F$4:$F$16,MATCH(D8,'费用归属表（快照）'!$A$4:$A$16,0)),"") | Q8: =IF(P8="","",P8-I8) | T8: =IF(D8="","",IFERROR(INDEX('费用归属表（快照）'!$C$4:$C$16,MATCH(D8,'费用归属表（快照）'!$A$4:$A$16,0)),"")) | U8: =IF(D8="","",IF(AND(D8="销售出库费用",B8="深圳星期九"),"永续供应中心 0010401",IF(AND(D8="原料入库费用",E8="小料"),"茶饮小料部 0030902",IFERROR(INDEX('费用归属表（快照）'!$D$4:$D$16,MATCH(D8,'费用归属表（快照）'!$A$4:$A$16,0)),"")))) | V8: =IF(D8="","",IFERROR(INDEX('费用归属表（快照）'!$B$4:$B$16,MATCH(D8,'费用归属表（快照）'!$A$4:$A$16,0)),"")) | W8: =IF(OR(E8="",AND(LEFT(T8,4)<>"6601",LEFT(T8,4)<>"6401")),"",IFERROR(IF(INDEX(选项!$I$2:$I$11,MATCH(E8,选项!$H$2:$H$11,0))="","",INDEX(选项!$I$2:$I$11,MATCH(E8,选项!$H$2:$H$11,0))),"")) | X8: =IF(OR(E8="",AND(LEFT(T8,4)<>"6601",LEFT(T8,4)<>"6401")),"",IFERROR(IF(INDEX(选项!$J$2:$J$11,MATCH(E8,选项!$H$2:$H$11,0))="","",INDEX(选项!$J$2:$J$11,MATCH(E8,选项!$H$2:$H$11,0))),""))
A9: 2026-07 | B9: 深圳星期零 | C9: 顺丰速运 | D9: 销售出库费用 | E9: 豆蛋制品 | G9: 月结 | I9: 268 | J9: =IFERROR(INDEX(供应商列表!$F$4:$R$25,MATCH(C9,供应商列表!$A$4:$A$25,0),MATCH(D9,供应商列表!$F$3:$R$3,0)),"") | K9: =IFERROR(ROUND(I9/(1+J9),2),"") | L9: =IFERROR(I9-K9,"") | M9: =IFERROR(INDEX(供应商列表!$B$4:$B$25,MATCH(C9,供应商列表!$A$4:$A$25,0)),"") | N9: ="计提"&M9&(MID(A9,6,2)*1)&"月"&IFERROR(INDEX(供应商列表!$E$4:$E$25,MATCH(C9,供应商列表!$A$4:$A$25,0)),"线下")&IF(F9<>"",F9,IF(OR(E9="—",E9=""),"",E9))&IFERROR(INDEX('费用归属表（快照）'!$F$4:$F$16,MATCH(D9,'费用归属表（快照）'!$A$4:$A$16,0)),"") | Q9: =IF(P9="","",P9-I9) | T9: =IF(D9="","",IFERROR(INDEX('费用归属表（快照）'!$C$4:$C$16,MATCH(D9,'费用归属表（快照）'!$A$4:$A$16,0)),"")) | U9: =IF(D9="","",IF(AND(D9="销售出库费用",B9="深圳星期九"),"永续供应中心 0010401",IF(AND(D9="原料入库费用",E9="小料"),"茶饮小料部 0030902",IFERROR(INDEX('费用归属表（快照）'!$D$4:$D$16,MATCH(D9,'费用归属表（快照）'!$A$4:$A$16,0)),"")))) | V9: =IF(D9="","",IFERROR(INDEX('费用归属表（快照）'!$B$4:$B$16,MATCH(D9,'费用归属表（快照）'!$A$4:$A$16,0)),"")) | W9: =IF(OR(E9="",AND(LEFT(T9,4)<>"6601",LEFT(T9,4)<>"6401")),"",IFERROR(IF(INDEX(选项!$I$2:$I$11,MATCH(E9,选项!$H$2:$H$11,0))="","",INDEX(选项!$I$2:$I$11,MATCH(E9,选项!$H$2:$H$11,0))),"")) | X9: =IF(OR(E9="",AND(LEFT(T9,4)<>"6601",LEFT(T9,4)<>"6401")),"",IFERROR(IF(INDEX(选项!$J$2:$J$11,MATCH(E9,选项!$H$2:$H$11,0))="","",INDEX(选项!$J$2:$J$11,MATCH(E9,选项!$H$2:$H$11,0))),""))
A10: 2026-07 | B10: 深圳星期零 | C10: 顺丰速运 | D10: 销售出库费用 | E10: 零售 | G10: 月结 | I10: 175 | J10: =IFERROR(INDEX(供应商列表!$F$4:$R$25,MATCH(C10,供应商列表!$A$4:$A$25,0),MATCH(D10,供应商列表!$F$3:$R$3,0)),"") | K10: =IFERROR(ROUND(I10/(1+J10),2),"") | L10: =IFERROR(I10-K10,"") | M10: =IFERROR(INDEX(供应商列表!$B$4:$B$25,MATCH(C10,供应商列表!$A$4:$A$25,0)),"") | N10: ="计提"&M10&(MID(A10,6,2)*1)&"月"&IFERROR(INDEX(供应商列表!$E$4:$E$25,MATCH(C10,供应商列表!$A$4:$A$25,0)),"线下")&IF(F10<>"",F10,IF(OR(E10="—",E10=""),"",E10))&IFERROR(INDEX('费用归属表（快照）'!$F$4:$F$16,MATCH(D10,'费用归属表（快照）'!$A$4:$A$16,0)),"") | Q10: =IF(P10="","",P10-I10) | T10: =IF(D10="","",IFERROR(INDEX('费用归属表（快照）'!$C$4:$C$16,MATCH(D10,'费用归属表（快照）'!$A$4:$A$16,0)),"")) | U10: =IF(D10="","",IF(AND(D10="销售出库费用",B10="深圳星期九"),"永续供应中心 0010401",IF(AND(D10="原料入库费用",E10="小料"),"茶饮小料部 0030902",IFERROR(INDEX('费用归属表（快照）'!$D$4:$D$16,MATCH(D10,'费用归属表（快照）'!$A$4:$A$16,0)),"")))) | V10: =IF(D10="","",IFERROR(INDEX('费用归属表（快照）'!$B$4:$B$16,MATCH(D10,'费用归属表（快照）'!$A$4:$A$16,0)),"")) | W10: =IF(OR(E10="",AND(LEFT(T10,4)<>"6601",LEFT(T10,4)<>"6401")),"",IFERROR(IF(INDEX(选项!$I$2:$I$11,MATCH(E10,选项!$H$2:$H$11,0))="","",INDEX(选项!$I$2:$I$11,MATCH(E10,选项!$H$2:$H$11,0))),"")) | X10: =IF(OR(E10="",AND(LEFT(T10,4)<>"6601",LEFT(T10,4)<>"6401")),"",IFERROR(IF(INDEX(选项!$J$2:$J$11,MATCH(E10,选项!$H$2:$H$11,0))="","",INDEX(选项!$J$2:$J$11,MATCH(E10,选项!$H$2:$H$11,0))),""))
A11: 2026-07 | B11: 深圳星期零 | C11: 顺丰速运 | D11: 销售出库费用 | E11: 小料 | G11: 月结 | I11: 612 | J11: =IFERROR(INDEX(供应商列表!$F$4:$R$25,MATCH(C11,供应商列表!$A$4:$A$25,0),MATCH(D11,供应商列表!$F$3:$R$3,0)),"") | K11: =IFERROR(ROUND(I11/(1+J11),2),"") | L11: =IFERROR(I11-K11,"") | M11: =IFERROR(INDEX(供应商列表!$B$4:$B$25,MATCH(C11,供应商列表!$A$4:$A$25,0)),"") | N11: ="计提"&M11&(MID(A11,6,2)*1)&"月"&IFERROR(INDEX(供应商列表!$E$4:$E$25,MATCH(C11,供应商列表!$A$4:$A$25,0)),"线下")&IF(F11<>"",F11,IF(OR(E11="—",E11=""),"",E11))&IFERROR(INDEX('费用归属表（快照）'!$F$4:$F$16,MATCH(D11,'费用归属表（快照）'!$A$4:$A$16,0)),"") | Q11: =IF(P11="","",P11-I11) | T11: =IF(D11="","",IFERROR(INDEX('费用归属表（快照）'!$C$4:$C$16,MATCH(D11,'费用归属表（快照）'!$A$4:$A$16,0)),"")) | U11: =IF(D11="","",IF(AND(D11="销售出库费用",B11="深圳星期九"),"永续供应中心 0010401",IF(AND(D11="原料入库费用",E11="小料"),"茶饮小料部 0030902",IFERROR(INDEX('费用归属表（快照）'!$D$4:$D$16,MATCH(D11,'费用归属表（快照）'!$A$4:$A$16,0)),"")))) | V11: =IF(D11="","",IFERROR(INDEX('费用归属表（快照）'!$B$4:$B$16,MATCH(D11,'费用归属表（快照）'!$A$4:$A$16,0)),"")) | W11: =IF(OR(E11="",AND(LEFT(T11,4)<>"6601",LEFT(T11,4)<>"6401")),"",IFERROR(IF(INDEX(选项!$I$2:$I$11,MATCH(E11,选项!$H$2:$H$11,0))="","",INDEX(选项!$I$2:$I$11,MATCH(E11,选项!$H$2:$H$11,0))),"")) | X11: =IF(OR(E11="",AND(LEFT(T11,4)<>"6601",LEFT(T11,4)<>"6401")),"",IFERROR(IF(INDEX(选项!$J$2:$J$11,MATCH(E11,选项!$H$2:$H$11,0))="","",INDEX(选项!$J$2:$J$11,MATCH(E11,选项!$H$2:$H$11,0))),""))
A12: 2026-07 | B12: 深圳星期零 | C12: 跨越物流 | D12: 销售出库费用 | E12: 植物肉 | G12: 月结 | I12: 1199.55 | J12: =IFERROR(INDEX(供应商列表!$F$4:$R$25,MATCH(C12,供应商列表!$A$4:$A$25,0),MATCH(D12,供应商列表!$F$3:$R$3,0)),"") | K12: =IFERROR(ROUND(I12/(1+J12),2),"") | L12: =IFERROR(I12-K12,"") | M12: =IFERROR(INDEX(供应商列表!$B$4:$B$25,MATCH(C12,供应商列表!$A$4:$A$25,0)),"") | N12: ="计提"&M12&(MID(A12,6,2)*1)&"月"&IFERROR(INDEX(供应商列表!$E$4:$E$25,MATCH(C12,供应商列表!$A$4:$A$25,0)),"线下")&IF(F12<>"",F12,IF(OR(E12="—",E12=""),"",E12))&IFERROR(INDEX('费用归属表（快照）'!$F$4:$F$16,MATCH(D12,'费用归属表（快照）'!$A$4:$A$16,0)),"") | Q12: =IF(P12="","",P12-I12) | T12: =IF(D12="","",IFERROR(INDEX('费用归属表（快照）'!$C$4:$C$16,MATCH(D12,'费用归属表（快照）'!$A$4:$A$16,0)),"")) | U12: =IF(D12="","",IF(AND(D12="销售出库费用",B12="深圳星期九"),"永续供应中心 0010401",IF(AND(D12="原料入库费用",E12="小料"),"茶饮小料部 0030902",IFERROR(INDEX('费用归属表（快照）'!$D$4:$D$16,MATCH(D12,'费用归属表（快照）'!$A$4:$A$16,0)),"")))) | V12: =IF(D12="","",IFERROR(INDEX('费用归属表（快照）'!$B$4:$B$16,MATCH(D12,'费用归属表（快照）'!$A$4:$A$16,0)),"")) | W12: =IF(OR(E12="",AND(LEFT(T12,4)<>"6601",LEFT(T12,4)<>"6401")),"",IFERROR(IF(INDEX(选项!$I$2:$I$11,MATCH(E12,选项!$H$2:$H$11,0))="","",INDEX(选项!$I$2:$I$11,MATCH(E12,选项!$H$2:$H$11,0))),"")) | X12: =IF(OR(E12="",AND(LEFT(T12,4)<>"6601",LEFT(T12,4)<>"6401")),"",IFERROR(IF(INDEX(选项!$J$2:$J$11,MATCH(E12,选项!$H$2:$H$11,0))="","",INDEX(选项!$J$2:$J$11,MATCH(E12,选项!$H$2:$H$11,0))),""))
A13: 2026-07 | B13: 深圳星期零 | C13: 跨越物流 | D13: 销售出库费用 | E13: 零售 | G13: 月结 | I13: 195.55 | J13: =IFERROR(INDEX(供应商列表!$F$4:$R$25,MATCH(C13,供应商列表!$A$4:$A$25,0),MATCH(D13,供应商列表!$F$3:$R$3,0)),"") | K13: =IFERROR(ROUND(I13/(1+J13),2),"") | L13: =IFERROR(I13-K13,"") | M13: =IFERROR(INDEX(供应商列表!$B$4:$B$25,MATCH(C13,供应商列表!$A$4:$A$25,0)),"") | N13: ="计提"&M13&(MID(A13,6,2)*1)&"月"&IFERROR(INDEX(供应商列表!$E$4:$E$25,MATCH(C13,供应商列表!$A$4:$A$25,0)),"线下")&IF(F13<>"",F13,IF(OR(E13="—",E13=""),"",E13))&IFERROR(INDEX('费用归属表（快照）'!$F$4:$F$16,MATCH(D13,'费用归属表（快照）'!$A$4:$A$16,0)),"") | Q13: =IF(P13="","",P13-I13) | T13: =IF(D13="","",IFERROR(INDEX('费用归属表（快照）'!$C$4:$C$16,MATCH(D13,'费用归属表（快照）'!$A$4:$A$16,0)),"")) | U13: =IF(D13="","",IF(AND(D13="销售出库费用",B13="深圳星期九"),"永续供应中心 0010401",IF(AND(D13="原料入库费用",E13="小料"),"茶饮小料部 0030902",IFERROR(INDEX('费用归属表（快照）'!$D$4:$D$16,MATCH(D13,'费用归属表（快照）'!$A$4:$A$16,0)),"")))) | V13: =IF(D13="","",IFERROR(INDEX('费用归属表（快照）'!$B$4:$B$16,MATCH(D13,'费用归属表（快照）'!$A$4:$A$16,0)),"")) | W13: =IF(OR(E13="",AND(LEFT(T13,4)<>"6601",LEFT(T13,4)<>"6401")),"",IFERROR(IF(INDEX(选项!$I$2:$I$11,MATCH(E13,选项!$H$2:$H$11,0))="","",INDEX(选项!$I$2:$I$11,MATCH(E13,选项!$H$2:$H$11,0))),"")) | X13: =IF(OR(E13="",AND(LEFT(T13,4)<>"6601",LEFT(T13,4)<>"6401")),"",IFERROR(IF(INDEX(选项!$J$2:$J$11,MATCH(E13,选项!$H$2:$H$11,0))="","",INDEX(选项!$J$2:$J$11,MATCH(E13,选项!$H$2:$H$11,0))),""))
A14: 2026-07 | B14: 深圳星期零 | C14: 跨越物流 | D14: 销售出库费用 | E14: 小料 | G14: 月结 | I14: 421.56 | J14: =IFERROR(INDEX(供应商列表!$F$4:$R$25,MATCH(C14,供应商列表!$A$4:$A$25,0),MATCH(D14,供应商列表!$F$3:$R$3,0)),"") | K14: =IFERROR(ROUND(I14/(1+J14),2),"") | L14: =IFERROR(I14-K14,"") | M14: =IFERROR(INDEX(供应商列表!$B$4:$B$25,MATCH(C14,供应商列表!$A$4:$A$25,0)),"") | N14: ="计提"&M14&(MID(A14,6,2)*1)&"月"&IFERROR(INDEX(供应商列表!$E$4:$E$25,MATCH(C14,供应商列表!$A$4:$A$25,0)),"线下")&IF(F14<>"",F14,IF(OR(E14="—",E14=""),"",E14))&IFERROR(INDEX('费用归属表（快照）'!$F$4:$F$16,MATCH(D14,'费用归属表（快照）'!$A$4:$A$16,0)),"") | Q14: =IF(P14="","",P14-I14) | T14: =IF(D14="","",IFERROR(INDEX('费用归属表（快照）'!$C$4:$C$16,MATCH(D14,'费用归属表（快照）'!$A$4:$A$16,0)),"")) | U14: =IF(D14="","",IF(AND(D14="销售出库费用",B14="深圳星期九"),"永续供应中心 0010401",IF(AND(D14="原料入库费用",E14="小料"),"茶饮小料部 0030902",IFERROR(INDEX('费用归属表（快照）'!$D$4:$D$16,MATCH(D14,'费用归属表（快照）'!$A$4:$A$16,0)),"")))) | V14: =IF(D14="","",IFERROR(INDEX('费用归属表（快照）'!$B$4:$B$16,MATCH(D14,'费用归属表（快照）'!$A$4:$A$16,0)),"")) | W14: =IF(OR(E14="",AND(LEFT(T14,4)<>"6601",LEFT(T14,4)<>"6401")),"",IFERROR(IF(INDEX(选项!$I$2:$I$11,MATCH(E14,选项!$H$2:$H$11,0))="","",INDEX(选项!$I$2:$I$11,MATCH(E14,选项!$H$2:$H$11,0))),"")) | X14: =IF(OR(E14="",AND(LEFT(T14,4)<>"6601",LEFT(T14,4)<>"6401")),"",IFERROR(IF(INDEX(选项!$J$2:$J$11,MATCH(E14,选项!$H$2:$H$11,0))="","",INDEX(选项!$J$2:$J$11,MATCH(E14,选项!$H$2:$H$11,0))),""))
A15: 2026-07 | B15: 深圳星期零 | C15: 跨越物流 | D15: 研发设备采购 | E15: — | G15: 月结 | I15: 329.4 | J15: =IFERROR(INDEX(供应商列表!$F$4:$R$25,MATCH(C15,供应商列表!$A$4:$A$25,0),MATCH(D15,供应商列表!$F$3:$R$3,0)),"") | K15: =IFERROR(ROUND(I15/(1+J15),2),"") | L15: =IFERROR(I15-K15,"") | M15: =IFERROR(INDEX(供应商列表!$B$4:$B$25,MATCH(C15,供应商列表!$A$4:$A$25,0)),"") | N15: ="计提"&M15&(MID(A15,6,2)*1)&"月"&IFERROR(INDEX(供应商列表!$E$4:$E$25,MATCH(C15,供应商列表!$A$4:$A$25,0)),"线下")&IF(F15<>"",F15,IF(OR(E15="—",E15=""),"",E15))&IFERROR(INDEX('费用归属表（快照）'!$F$4:$F$16,MATCH(D15,'费用归属表（快照）'!$A$4:$A$16,0)),"") | Q15: =IF(P15="","",P15-I15) | T15: =IF(D15="","",IFERROR(INDEX('费用归属表（快照）'!$C$4:$C$16,MATCH(D15,'费用归属表（快照）'!$A$4:$A$16,0)),"")) | U15: =IF(D15="","",IF(AND(D15="销售出库费用",B15="深圳星期九"),"永续供应中心 0010401",IF(AND(D15="原料入库费用",E15="小料"),"茶饮小料部 0030902",IFERROR(INDEX('费用归属表（快照）'!$D$4:$D$16,MATCH(D15,'费用归属表（快照）'!$A$4:$A$16,0)),"")))) | V15: =IF(D15="","",IFERROR(INDEX('费用归属表（快照）'!$B$4:$B$16,MATCH(D15,'费用归属表（快照）'!$A$4:$A$16,0)),"")) | W15: =IF(OR(E15="",AND(LEFT(T15,4)<>"6601",LEFT(T15,4)<>"6401")),"",IFERROR(IF(INDEX(选项!$I$2:$I$11,MATCH(E15,选项!$H$2:$H$11,0))="","",INDEX(选项!$I$2:$I$11,MATCH(E15,选项!$H$2:$H$11,0))),"")) | X15: =IF(OR(E15="",AND(LEFT(T15,4)<>"6601",LEFT(T15,4)<>"6401")),"",IFERROR(IF(INDEX(选项!$J$2:$J$11,MATCH(E15,选项!$H$2:$H$11,0))="","",INDEX(选项!$J$2:$J$11,MATCH(E15,选项!$H$2:$H$11,0))),""))
A16: 2026-07 | B16: 深圳星期零 | C16: 跨越物流 | D16: 原料入库费用 | E16: — | F16: 孝感工厂 | G16: 月结 | I16: 991.84 | J16: =IFERROR(INDEX(供应商列表!$F$4:$R$25,MATCH(C16,供应商列表!$A$4:$A$25,0),MATCH(D16,供应商列表!$F$3:$R$3,0)),"") | K16: =IFERROR(ROUND(I16/(1+J16),2),"") | L16: =IFERROR(I16-K16,"") | M16: =IFERROR(INDEX(供应商列表!$B$4:$B$25,MATCH(C16,供应商列表!$A$4:$A$25,0)),"") | N16: ="计提"&M16&(MID(A16,6,2)*1)&"月"&IFERROR(INDEX(供应商列表!$E$4:$E$25,MATCH(C16,供应商列表!$A$4:$A$25,0)),"线下")&IF(F16<>"",F16,IF(OR(E16="—",E16=""),"",E16))&IFERROR(INDEX('费用归属表（快照）'!$F$4:$F$16,MATCH(D16,'费用归属表（快照）'!$A$4:$A$16,0)),"") | Q16: =IF(P16="","",P16-I16) | T16: =IF(D16="","",IFERROR(INDEX('费用归属表（快照）'!$C$4:$C$16,MATCH(D16,'费用归属表（快照）'!$A$4:$A$16,0)),"")) | U16: =IF(D16="","",IF(AND(D16="销售出库费用",B16="深圳星期九"),"永续供应中心 0010401",IF(AND(D16="原料入库费用",E16="小料"),"茶饮小料部 0030902",IFERROR(INDEX('费用归属表（快照）'!$D$4:$D$16,MATCH(D16,'费用归属表（快照）'!$A$4:$A$16,0)),"")))) | V16: =IF(D16="","",IFERROR(INDEX('费用归属表（快照）'!$B$4:$B$16,MATCH(D16,'费用归属表（快照）'!$A$4:$A$16,0)),"")) | W16: =IF(OR(E16="",AND(LEFT(T16,4)<>"6601",LEFT(T16,4)<>"6401")),"",IFERROR(IF(INDEX(选项!$I$2:$I$11,MATCH(E16,选项!$H$2:$H$11,0))="","",INDEX(选项!$I$2:$I$11,MATCH(E16,选项!$H$2:$H$11,0))),"")) | X16: =IF(OR(E16="",AND(LEFT(T16,4)<>"6601",LEFT(T16,4)<>"6401")),"",IFERROR(IF(INDEX(选项!$J$2:$J$11,MATCH(E16,选项!$H$2:$H$11,0))="","",INDEX(选项!$J$2:$J$11,MATCH(E16,选项!$H$2:$H$11,0))),""))
A17: 2026-07 | B17: 深圳星期零 | C17: 跨越物流 | D17: 设备调拨费用 | E17: — | G17: 月结 | I17: 1509.53 | J17: =IFERROR(INDEX(供应商列表!$F$4:$R$25,MATCH(C17,供应商列表!$A$4:$A$25,0),MATCH(D17,供应商列表!$F$3:$R$3,0)),"") | K17: =IFERROR(ROUND(I17/(1+J17),2),"") | L17: =IFERROR(I17-K17,"") | M17: =IFERROR(INDEX(供应商列表!$B$4:$B$25,MATCH(C17,供应商列表!$A$4:$A$25,0)),"") | N17: ="计提"&M17&(MID(A17,6,2)*1)&"月"&IFERROR(INDEX(供应商列表!$E$4:$E$25,MATCH(C17,供应商列表!$A$4:$A$25,0)),"线下")&IF(F17<>"",F17,IF(OR(E17="—",E17=""),"",E17))&IFERROR(INDEX('费用归属表（快照）'!$F$4:$F$16,MATCH(D17,'费用归属表（快照）'!$A$4:$A$16,0)),"") | Q17: =IF(P17="","",P17-I17) | T17: =IF(D17="","",IFERROR(INDEX('费用归属表（快照）'!$C$4:$C$16,MATCH(D17,'费用归属表（快照）'!$A$4:$A$16,0)),"")) | U17: =IF(D17="","",IF(AND(D17="销售出库费用",B17="深圳星期九"),"永续供应中心 0010401",IF(AND(D17="原料入库费用",E17="小料"),"茶饮小料部 0030902",IFERROR(INDEX('费用归属表（快照）'!$D$4:$D$16,MATCH(D17,'费用归属表（快照）'!$A$4:$A$16,0)),"")))) | V17: =IF(D17="","",IFERROR(INDEX('费用归属表（快照）'!$B$4:$B$16,MATCH(D17,'费用归属表（快照）'!$A$4:$A$16,0)),"")) | W17: =IF(OR(E17="",AND(LEFT(T17,4)<>"6601",LEFT(T17,4)<>"6401")),"",IFERROR(IF(INDEX(选项!$I$2:$I$11,MATCH(E17,选项!$H$2:$H$11,0))="","",INDEX(选项!$I$2:$I$11,MATCH(E17,选项!$H$2:$H$11,0))),"")) | X17: =IF(OR(E17="",AND(LEFT(T17,4)<>"6601",LEFT(T17,4)<>"6401")),"",IFERROR(IF(INDEX(选项!$J$2:$J$11,MATCH(E17,选项!$H$2:$H$11,0))="","",INDEX(选项!$J$2:$J$11,MATCH(E17,选项!$H$2:$H$11,0))),""))
A18: 2026-07 | B18: 深圳星期零 | C18: 跨越物流 | D18: 销售出库费用 | E18: 小料 | G18: 月结 | I18: 486.8 | J18: =IFERROR(INDEX(供应商列表!$F$4:$R$25,MATCH(C18,供应商列表!$A$4:$A$25,0),MATCH(D18,供应商列表!$F$3:$R$3,0)),"") | K18: =IFERROR(ROUND(I18/(1+J18),2),"") | L18: =IFERROR(I18-K18,"") | M18: =IFERROR(INDEX(供应商列表!$B$4:$B$25,MATCH(C18,供应商列表!$A$4:$A$25,0)),"") | N18: ="计提"&M18&(MID(A18,6,2)*1)&"月"&IFERROR(INDEX(供应商列表!$E$4:$E$25,MATCH(C18,供应商列表!$A$4:$A$25,0)),"线下")&IF(F18<>"",F18,IF(OR(E18="—",E18=""),"",E18))&IFERROR(INDEX('费用归属表（快照）'!$F$4:$F$16,MATCH(D18,'费用归属表（快照）'!$A$4:$A$16,0)),"") | Q18: =IF(P18="","",P18-I18) | T18: =IF(D18="","",IFERROR(INDEX('费用归属表（快照）'!$C$4:$C$16,MATCH(D18,'费用归属表（快照）'!$A$4:$A$16,0)),"")) | U18: =IF(D18="","",IF(AND(D18="销售出库费用",B18="深圳星期九"),"永续供应中心 0010401",IF(AND(D18="原料入库费用",E18="小料"),"茶饮小料部 0030902",IFERROR(INDEX('费用归属表（快照）'!$D$4:$D$16,MATCH(D18,'费用归属表（快照）'!$A$4:$A$16,0)),"")))) | V18: =IF(D18="","",IFERROR(INDEX('费用归属表（快照）'!$B$4:$B$16,MATCH(D18,'费用归属表（快照）'!$A$4:$A$16,0)),"")) | W18: =IF(OR(E18="",AND(LEFT(T18,4)<>"6601",LEFT(T18,4)<>"6401")),"",IFERROR(IF(INDEX(选项!$I$2:$I$11,MATCH(E18,选项!$H$2:$H$11,0))="","",INDEX(选项!$I$2:$I$11,MATCH(E18,选项!$H$2:$H$11,0))),"")) | X18: =IF(OR(E18="",AND(LEFT(T18,4)<>"6601",LEFT(T18,4)<>"6401")),"",IFERROR(IF(INDEX(选项!$J$2:$J$11,MATCH(E18,选项!$H$2:$H$11,0))="","",INDEX(选项!$J$2:$J$11,MATCH(E18,选项!$H$2:$H$11,0))),""))
A19: 2026-07 | B19: 深圳星期零 | C19: 易风达 | D19: 销售出库费用 | E19: 小料 | G19: 月结 | I19: 400 | J19: =IFERROR(INDEX(供应商列表!$F$4:$R$25,MATCH(C19,供应商列表!$A$4:$A$25,0),MATCH(D19,供应商列表!$F$3:$R$3,0)),"") | K19: =IFERROR(ROUND(I19/(1+J19),2),"") | L19: =IFERROR(I19-K19,"") | M19: =IFERROR(INDEX(供应商列表!$B$4:$B$25,MATCH(C19,供应商列表!$A$4:$A$25,0)),"") | N19: ="计提"&M19&(MID(A19,6,2)*1)&"月"&IFERROR(INDEX(供应商列表!$E$4:$E$25,MATCH(C19,供应商列表!$A$4:$A$25,0)),"线下")&IF(F19<>"",F19,IF(OR(E19="—",E19=""),"",E19))&IFERROR(INDEX('费用归属表（快照）'!$F$4:$F$16,MATCH(D19,'费用归属表（快照）'!$A$4:$A$16,0)),"") | Q19: =IF(P19="","",P19-I19) | T19: =IF(D19="","",IFERROR(INDEX('费用归属表（快照）'!$C$4:$C$16,MATCH(D19,'费用归属表（快照）'!$A$4:$A$16,0)),"")) | U19: =IF(D19="","",IF(AND(D19="销售出库费用",B19="深圳星期九"),"永续供应中心 0010401",IF(AND(D19="原料入库费用",E19="小料"),"茶饮小料部 0030902",IFERROR(INDEX('费用归属表（快照）'!$D$4:$D$16,MATCH(D19,'费用归属表（快照）'!$A$4:$A$16,0)),"")))) | V19: =IF(D19="","",IFERROR(INDEX('费用归属表（快照）'!$B$4:$B$16,MATCH(D19,'费用归属表（快照）'!$A$4:$A$16,0)),"")) | W19: =IF(OR(E19="",AND(LEFT(T19,4)<>"6601",LEFT(T19,4)<>"6401")),"",IFERROR(IF(INDEX(选项!$I$2:$I$11,MATCH(E19,选项!$H$2:$H$11,0))="","",INDEX(选项!$I$2:$I$11,MATCH(E19,选项!$H$2:$H$11,0))),"")) | X19: =IF(OR(E19="",AND(LEFT(T19,4)<>"6601",LEFT(T19,4)<>"6401")),"",IFERROR(IF(INDEX(选项!$J$2:$J$11,MATCH(E19,选项!$H$2:$H$11,0))="","",INDEX(选项!$J$2:$J$11,MATCH(E19,选项!$H$2:$H$11,0))),""))
A20: 2026-07 | B20: 深圳星期零 | C20: 易风达 | D20: 原料入库费用 | E20: 小料 | F20: 小料 | G20: 月结 | I20: 6000 | J20: =IFERROR(INDEX(供应商列表!$F$4:$R$25,MATCH(C20,供应商列表!$A$4:$A$25,0),MATCH(D20,供应商列表!$F$3:$R$3,0)),"") | K20: =IFERROR(ROUND(I20/(1+J20),2),"") | L20: =IFERROR(I20-K20,"") | M20: =IFERROR(INDEX(供应商列表!$B$4:$B$25,MATCH(C20,供应商列表!$A$4:$A$25,0)),"") | N20: ="计提"&M20&(MID(A20,6,2)*1)&"月"&IFERROR(INDEX(供应商列表!$E$4:$E$25,MATCH(C20,供应商列表!$A$4:$A$25,0)),"线下")&IF(F20<>"",F20,IF(OR(E20="—",E20=""),"",E20))&IFERROR(INDEX('费用归属表（快照）'!$F$4:$F$16,MATCH(D20,'费用归属表（快照）'!$A$4:$A$16,0)),"") | Q20: =IF(P20="","",P20-I20) | T20: =IF(D20="","",IFERROR(INDEX('费用归属表（快照）'!$C$4:$C$16,MATCH(D20,'费用归属表（快照）'!$A$4:$A$16,0)),"")) | U20: =IF(D20="","",IF(AND(D20="销售出库费用",B20="深圳星期九"),"永续供应中心 0010401",IF(AND(D20="原料入库费用",E20="小料"),"茶饮小料部 0030902",IFERROR(INDEX('费用归属表（快照）'!$D$4:$D$16,MATCH(D20,'费用归属表（快照）'!$A$4:$A$16,0)),"")))) | V20: =IF(D20="","",IFERROR(INDEX('费用归属表（快照）'!$B$4:$B$16,MATCH(D20,'费用归属表（快照）'!$A$4:$A$16,0)),"")) | W20: =IF(OR(E20="",AND(LEFT(T20,4)<>"6601",LEFT(T20,4)<>"6401")),"",IFERROR(IF(INDEX(选项!$I$2:$I$11,MATCH(E20,选项!$H$2:$H$11,0))="","",INDEX(选项!$I$2:$I$11,MATCH(E20,选项!$H$2:$H$11,0))),"")) | X20: =IF(OR(E20="",AND(LEFT(T20,4)<>"6601",LEFT(T20,4)<>"6401")),"",IFERROR(IF(INDEX(选项!$J$2:$J$11,MATCH(E20,选项!$H$2:$H$11,0))="","",INDEX(选项!$J$2:$J$11,MATCH(E20,选项!$H$2:$H$11,0))),""))
A21: 2026-07 | B21: 深圳星期零 | C21: 易风达 | D21: 成品仓储费用 | E21: — | G21: 月结 | I21: 45281.9 | J21: =IFERROR(INDEX(供应商列表!$F$4:$R$25,MATCH(C21,供应商列表!$A$4:$A$25,0),MATCH(D21,供应商列表!$F$3:$R$3,0)),"") | K21: =IFERROR(ROUND(I21/(1+J21),2),"") | L21: =IFERROR(I21-K21,"") | M21: =IFERROR(INDEX(供应商列表!$B$4:$B$25,MATCH(C21,供应商列表!$A$4:$A$25,0)),"") | N21: ="计提"&M21&(MID(A21,6,2)*1)&"月"&IFERROR(INDEX(供应商列表!$E$4:$E$25,MATCH(C21,供应商列表!$A$4:$A$25,0)),"线下")&IF(F21<>"",F21,IF(OR(E21="—",E21=""),"",E21))&IFERROR(INDEX('费用归属表（快照）'!$F$4:$F$16,MATCH(D21,'费用归属表（快照）'!$A$4:$A$16,0)),"") | Q21: =IF(P21="","",P21-I21) | T21: =IF(D21="","",IFERROR(INDEX('费用归属表（快照）'!$C$4:$C$16,MATCH(D21,'费用归属表（快照）'!$A$4:$A$16,0)),"")) | U21: =IF(D21="","",IF(AND(D21="销售出库费用",B21="深圳星期九"),"永续供应中心 0010401",IF(AND(D21="原料入库费用",E21="小料"),"茶饮小料部 0030902",IFERROR(INDEX('费用归属表（快照）'!$D$4:$D$16,MATCH(D21,'费用归属表（快照）'!$A$4:$A$16,0)),"")))) | V21: =IF(D21="","",IFERROR(INDEX('费用归属表（快照）'!$B$4:$B$16,MATCH(D21,'费用归属表（快照）'!$A$4:$A$16,0)),"")) | W21: =IF(OR(E21="",AND(LEFT(T21,4)<>"6601",LEFT(T21,4)<>"6401")),"",IFERROR(IF(INDEX(选项!$I$2:$I$11,MATCH(E21,选项!$H$2:$H$11,0))="","",INDEX(选项!$I$2:$I$11,MATCH(E21,选项!$H$2:$H$11,0))),"")) | X21: =IF(OR(E21="",AND(LEFT(T21,4)<>"6601",LEFT(T21,4)<>"6401")),"",IFERROR(IF(INDEX(选项!$J$2:$J$11,MATCH(E21,选项!$H$2:$H$11,0))="","",INDEX(选项!$J$2:$J$11,MATCH(E21,选项!$H$2:$H$11,0))),""))
A22: 2026-07 | B22: 深圳星期零 | C22: 诚煜物流 | D22: 销售出库费用 | E22: 鲜食 | G22: 月结 | I22: 183204.47 | J22: =IFERROR(INDEX(供应商列表!$F$4:$R$25,MATCH(C22,供应商列表!$A$4:$A$25,0),MATCH(D22,供应商列表!$F$3:$R$3,0)),"") | K22: =IFERROR(ROUND(I22/(1+J22),2),"") | L22: =IFERROR(I22-K22,"") | M22: =IFERROR(INDEX(供应商列表!$B$4:$B$25,MATCH(C22,供应商列表!$A$4:$A$25,0)),"") | N22: ="计提"&M22&(MID(A22,6,2)*1)&"月"&IFERROR(INDEX(供应商列表!$E$4:$E$25,MATCH(C22,供应商列表!$A$4:$A$25,0)),"线下")&IF(F22<>"",F22,IF(OR(E22="—",E22=""),"",E22))&IFERROR(INDEX('费用归属表（快照）'!$F$4:$F$16,MATCH(D22,'费用归属表（快照）'!$A$4:$A$16,0)),"") | Q22: =IF(P22="","",P22-I22) | T22: =IF(D22="","",IFERROR(INDEX('费用归属表（快照）'!$C$4:$C$16,MATCH(D22,'费用归属表（快照）'!$A$4:$A$16,0)),"")) | U22: =IF(D22="","",IF(AND(D22="销售出库费用",B22="深圳星期九"),"永续供应中心 0010401",IF(AND(D22="原料入库费用",E22="小料"),"茶饮小料部 0030902",IFERROR(INDEX('费用归属表（快照）'!$D$4:$D$16,MATCH(D22,'费用归属表（快照）'!$A$4:$A$16,0)),"")))) | V22: =IF(D22="","",IFERROR(INDEX('费用归属表（快照）'!$B$4:$B$16,MATCH(D22,'费用归属表（快照）'!$A$4:$A$16,0)),"")) | W22: =IF(OR(E22="",AND(LEFT(T22,4)<>"6601",LEFT(T22,4)<>"6401")),"",IFERROR(IF(INDEX(选项!$I$2:$I$11,MATCH(E22,选项!$H$2:$H$11,0))="","",INDEX(选项!$I$2:$I$11,MATCH(E22,选项!$H$2:$H$11,0))),"")) | X22: =IF(OR(E22="",AND(LEFT(T22,4)<>"6601",LEFT(T22,4)<>"6401")),"",IFERROR(IF(INDEX(选项!$J$2:$J$11,MATCH(E22,选项!$H$2:$H$11,0))="","",INDEX(选项!$J$2:$J$11,MATCH(E22,选项!$H$2:$H$11,0))),""))
A23: 2026-07 | B23: 深圳星期零 | C23: 链盟 | D23: 销售出库费用 | E23: 植物肉 | G23: 月结 | I23: 5827.5 | J23: =IFERROR(INDEX(供应商列表!$F$4:$R$25,MATCH(C23,供应商列表!$A$4:$A$25,0),MATCH(D23,供应商列表!$F$3:$R$3,0)),"") | K23: =IFERROR(ROUND(I23/(1+J23),2),"") | L23: =IFERROR(I23-K23,"") | M23: =IFERROR(INDEX(供应商列表!$B$4:$B$25,MATCH(C23,供应商列表!$A$4:$A$25,0)),"") | N23: ="计提"&M23&(MID(A23,6,2)*1)&"月"&IFERROR(INDEX(供应商列表!$E$4:$E$25,MATCH(C23,供应商列表!$A$4:$A$25,0)),"线下")&IF(F23<>"",F23,IF(OR(E23="—",E23=""),"",E23))&IFERROR(INDEX('费用归属表（快照）'!$F$4:$F$16,MATCH(D23,'费用归属表（快照）'!$A$4:$A$16,0)),"") | Q23: =IF(P23="","",P23-I23) | T23: =IF(D23="","",IFERROR(INDEX('费用归属表（快照）'!$C$4:$C$16,MATCH(D23,'费用归属表（快照）'!$A$4:$A$16,0)),"")) | U23: =IF(D23="","",IF(AND(D23="销售出库费用",B23="深圳星期九"),"永续供应中心 0010401",IF(AND(D23="原料入库费用",E23="小料"),"茶饮小料部 0030902",IFERROR(INDEX('费用归属表（快照）'!$D$4:$D$16,MATCH(D23,'费用归属表（快照）'!$A$4:$A$16,0)),"")))) | V23: =IF(D23="","",IFERROR(INDEX('费用归属表（快照）'!$B$4:$B$16,MATCH(D23,'费用归属表（快照）'!$A$4:$A$16,0)),"")) | W23: =IF(OR(E23="",AND(LEFT(T23,4)<>"6601",LEFT(T23,4)<>"6401")),"",IFERROR(IF(INDEX(选项!$I$2:$I$11,MATCH(E23,选项!$H$2:$H$11,0))="","",INDEX(选项!$I$2:$I$11,MATCH(E23,选项!$H$2:$H$11,0))),"")) | X23: =IF(OR(E23="",AND(LEFT(T23,4)<>"6601",LEFT(T23,4)<>"6401")),"",IFERROR(IF(INDEX(选项!$J$2:$J$11,MATCH(E23,选项!$H$2:$H$11,0))="","",INDEX(选项!$J$2:$J$11,MATCH(E23,选项!$H$2:$H$11,0))),""))
A24: 2026-07 | B24: 深圳星期零 | C24: 链盟 | D24: 销售出库费用 | E24: 鲜食 | G24: 月结 | I24: 1500 | J24: =IFERROR(INDEX(供应商列表!$F$4:$R$25,MATCH(C24,供应商列表!$A$4:$A$25,0),MATCH(D24,供应商列表!$F$3:$R$3,0)),"") | K24: =IFERROR(ROUND(I24/(1+J24),2),"") | L24: =IFERROR(I24-K24,"") | M24: =IFERROR(INDEX(供应商列表!$B$4:$B$25,MATCH(C24,供应商列表!$A$4:$A$25,0)),"") | N24: ="计提"&M24&(MID(A24,6,2)*1)&"月"&IFERROR(INDEX(供应商列表!$E$4:$E$25,MATCH(C24,供应商列表!$A$4:$A$25,0)),"线下")&IF(F24<>"",F24,IF(OR(E24="—",E24=""),"",E24))&IFERROR(INDEX('费用归属表（快照）'!$F$4:$F$16,MATCH(D24,'费用归属表（快照）'!$A$4:$A$16,0)),"") | Q24: =IF(P24="","",P24-I24) | T24: =IF(D24="","",IFERROR(INDEX('费用归属表（快照）'!$C$4:$C$16,MATCH(D24,'费用归属表（快照）'!$A$4:$A$16,0)),"")) | U24: =IF(D24="","",IF(AND(D24="销售出库费用",B24="深圳星期九"),"永续供应中心 0010401",IF(AND(D24="原料入库费用",E24="小料"),"茶饮小料部 0030902",IFERROR(INDEX('费用归属表（快照）'!$D$4:$D$16,MATCH(D24,'费用归属表（快照）'!$A$4:$A$16,0)),"")))) | V24: =IF(D24="","",IFERROR(INDEX('费用归属表（快照）'!$B$4:$B$16,MATCH(D24,'费用归属表（快照）'!$A$4:$A$16,0)),"")) | W24: =IF(OR(E24="",AND(LEFT(T24,4)<>"6601",LEFT(T24,4)<>"6401")),"",IFERROR(IF(INDEX(选项!$I$2:$I$11,MATCH(E24,选项!$H$2:$H$11,0))="","",INDEX(选项!$I$2:$I$11,MATCH(E24,选项!$H$2:$H$11,0))),"")) | X24: =IF(OR(E24="",AND(LEFT(T24,4)<>"6601",LEFT(T24,4)<>"6401")),"",IFERROR(IF(INDEX(选项!$J$2:$J$11,MATCH(E24,选项!$H$2:$H$11,0))="","",INDEX(选项!$J$2:$J$11,MATCH(E24,选项!$H$2:$H$11,0))),""))
A25: 2026-07 | B25: 深圳星期零 | C25: 链盟 | D25: 销售出库费用 | E25: 山姆零售 | G25: 月结 | I25: 880 | J25: =IFERROR(INDEX(供应商列表!$F$4:$R$25,MATCH(C25,供应商列表!$A$4:$A$25,0),MATCH(D25,供应商列表!$F$3:$R$3,0)),"") | K25: =IFERROR(ROUND(I25/(1+J25),2),"") | L25: =IFERROR(I25-K25,"") | M25: =IFERROR(INDEX(供应商列表!$B$4:$B$25,MATCH(C25,供应商列表!$A$4:$A$25,0)),"") | N25: ="计提"&M25&(MID(A25,6,2)*1)&"月"&IFERROR(INDEX(供应商列表!$E$4:$E$25,MATCH(C25,供应商列表!$A$4:$A$25,0)),"线下")&IF(F25<>"",F25,IF(OR(E25="—",E25=""),"",E25))&IFERROR(INDEX('费用归属表（快照）'!$F$4:$F$16,MATCH(D25,'费用归属表（快照）'!$A$4:$A$16,0)),"") | Q25: =IF(P25="","",P25-I25) | T25: =IF(D25="","",IFERROR(INDEX('费用归属表（快照）'!$C$4:$C$16,MATCH(D25,'费用归属表（快照）'!$A$4:$A$16,0)),"")) | U25: =IF(D25="","",IF(AND(D25="销售出库费用",B25="深圳星期九"),"永续供应中心 0010401",IF(AND(D25="原料入库费用",E25="小料"),"茶饮小料部 0030902",IFERROR(INDEX('费用归属表（快照）'!$D$4:$D$16,MATCH(D25,'费用归属表（快照）'!$A$4:$A$16,0)),"")))) | V25: =IF(D25="","",IFERROR(INDEX('费用归属表（快照）'!$B$4:$B$16,MATCH(D25,'费用归属表（快照）'!$A$4:$A$16,0)),"")) | W25: =IF(OR(E25="",AND(LEFT(T25,4)<>"6601",LEFT(T25,4)<>"6401")),"",IFERROR(IF(INDEX(选项!$I$2:$I$11,MATCH(E25,选项!$H$2:$H$11,0))="","",INDEX(选项!$I$2:$I$11,MATCH(E25,选项!$H$2:$H$11,0))),"")) | X25: =IF(OR(E25="",AND(LEFT(T25,4)<>"6601",LEFT(T25,4)<>"6401")),"",IFERROR(IF(INDEX(选项!$J$2:$J$11,MATCH(E25,选项!$H$2:$H$11,0))="","",INDEX(选项!$J$2:$J$11,MATCH(E25,选项!$H$2:$H$11,0))),""))
A26: 2026-07 | B26: 深圳星期零 | C26: 链盟 | D26: 销售出库费用 | E26: 零售 | G26: 月结 | I26: 3350 | J26: =IFERROR(INDEX(供应商列表!$F$4:$R$25,MATCH(C26,供应商列表!$A$4:$A$25,0),MATCH(D26,供应商列表!$F$3:$R$3,0)),"") | K26: =IFERROR(ROUND(I26/(1+J26),2),"") | L26: =IFERROR(I26-K26,"") | M26: =IFERROR(INDEX(供应商列表!$B$4:$B$25,MATCH(C26,供应商列表!$A$4:$A$25,0)),"") | N26: ="计提"&M26&(MID(A26,6,2)*1)&"月"&IFERROR(INDEX(供应商列表!$E$4:$E$25,MATCH(C26,供应商列表!$A$4:$A$25,0)),"线下")&IF(F26<>"",F26,IF(OR(E26="—",E26=""),"",E26))&IFERROR(INDEX('费用归属表（快照）'!$F$4:$F$16,MATCH(D26,'费用归属表（快照）'!$A$4:$A$16,0)),"") | Q26: =IF(P26="","",P26-I26) | T26: =IF(D26="","",IFERROR(INDEX('费用归属表（快照）'!$C$4:$C$16,MATCH(D26,'费用归属表（快照）'!$A$4:$A$16,0)),"")) | U26: =IF(D26="","",IF(AND(D26="销售出库费用",B26="深圳星期九"),"永续供应中心 0010401",IF(AND(D26="原料入库费用",E26="小料"),"茶饮小料部 0030902",IFERROR(INDEX('费用归属表（快照）'!$D$4:$D$16,MATCH(D26,'费用归属表（快照）'!$A$4:$A$16,0)),"")))) | V26: =IF(D26="","",IFERROR(INDEX('费用归属表（快照）'!$B$4:$B$16,MATCH(D26,'费用归属表（快照）'!$A$4:$A$16,0)),"")) | W26: =IF(OR(E26="",AND(LEFT(T26,4)<>"6601",LEFT(T26,4)<>"6401")),"",IFERROR(IF(INDEX(选项!$I$2:$I$11,MATCH(E26,选项!$H$2:$H$11,0))="","",INDEX(选项!$I$2:$I$11,MATCH(E26,选项!$H$2:$H$11,0))),"")) | X26: =IF(OR(E26="",AND(LEFT(T26,4)<>"6601",LEFT(T26,4)<>"6401")),"",IFERROR(IF(INDEX(选项!$J$2:$J$11,MATCH(E26,选项!$H$2:$H$11,0))="","",INDEX(选项!$J$2:$J$11,MATCH(E26,选项!$H$2:$H$11,0))),""))
A27: 2026-07 | B27: 深圳星期零 | C27: 链盟 | D27: 销售出库费用 | E27: 小料 | G27: 月结 | I27: 15760 | J27: =IFERROR(INDEX(供应商列表!$F$4:$R$25,MATCH(C27,供应商列表!$A$4:$A$25,0),MATCH(D27,供应商列表!$F$3:$R$3,0)),"") | K27: =IFERROR(ROUND(I27/(1+J27),2),"") | L27: =IFERROR(I27-K27,"") | M27: =IFERROR(INDEX(供应商列表!$B$4:$B$25,MATCH(C27,供应商列表!$A$4:$A$25,0)),"") | N27: ="计提"&M27&(MID(A27,6,2)*1)&"月"&IFERROR(INDEX(供应商列表!$E$4:$E$25,MATCH(C27,供应商列表!$A$4:$A$25,0)),"线下")&IF(F27<>"",F27,IF(OR(E27="—",E27=""),"",E27))&IFERROR(INDEX('费用归属表（快照）'!$F$4:$F$16,MATCH(D27,'费用归属表（快照）'!$A$4:$A$16,0)),"") | Q27: =IF(P27="","",P27-I27) | T27: =IF(D27="","",IFERROR(INDEX('费用归属表（快照）'!$C$4:$C$16,MATCH(D27,'费用归属表（快照）'!$A$4:$A$16,0)),"")) | U27: =IF(D27="","",IF(AND(D27="销售出库费用",B27="深圳星期九"),"永续供应中心 0010401",IF(AND(D27="原料入库费用",E27="小料"),"茶饮小料部 0030902",IFERROR(INDEX('费用归属表（快照）'!$D$4:$D$16,MATCH(D27,'费用归属表（快照）'!$A$4:$A$16,0)),"")))) | V27: =IF(D27="","",IFERROR(INDEX('费用归属表（快照）'!$B$4:$B$16,MATCH(D27,'费用归属表（快照）'!$A$4:$A$16,0)),"")) | W27: =IF(OR(E27="",AND(LEFT(T27,4)<>"6601",LEFT(T27,4)<>"6401")),"",IFERROR(IF(INDEX(选项!$I$2:$I$11,MATCH(E27,选项!$H$2:$H$11,0))="","",INDEX(选项!$I$2:$I$11,MATCH(E27,选项!$H$2:$H$11,0))),"")) | X27: =IF(OR(E27="",AND(LEFT(T27,4)<>"6601",LEFT(T27,4)<>"6401")),"",IFERROR(IF(INDEX(选项!$J$2:$J$11,MATCH(E27,选项!$H$2:$H$11,0))="","",INDEX(选项!$J$2:$J$11,MATCH(E27,选项!$H$2:$H$11,0))),""))
A28: 2026-07 | B28: 深圳星期零 | C28: 链盟 | D28: 原料入库费用 | E28: — | F28: 孝感工厂 | G28: 月结 | I28: 760 | J28: =IFERROR(INDEX(供应商列表!$F$4:$R$25,MATCH(C28,供应商列表!$A$4:$A$25,0),MATCH(D28,供应商列表!$F$3:$R$3,0)),"") | K28: =IFERROR(ROUND(I28/(1+J28),2),"") | L28: =IFERROR(I28-K28,"") | M28: =IFERROR(INDEX(供应商列表!$B$4:$B$25,MATCH(C28,供应商列表!$A$4:$A$25,0)),"") | N28: ="计提"&M28&(MID(A28,6,2)*1)&"月"&IFERROR(INDEX(供应商列表!$E$4:$E$25,MATCH(C28,供应商列表!$A$4:$A$25,0)),"线下")&IF(F28<>"",F28,IF(OR(E28="—",E28=""),"",E28))&IFERROR(INDEX('费用归属表（快照）'!$F$4:$F$16,MATCH(D28,'费用归属表（快照）'!$A$4:$A$16,0)),"") | Q28: =IF(P28="","",P28-I28) | T28: =IF(D28="","",IFERROR(INDEX('费用归属表（快照）'!$C$4:$C$16,MATCH(D28,'费用归属表（快照）'!$A$4:$A$16,0)),"")) | U28: =IF(D28="","",IF(AND(D28="销售出库费用",B28="深圳星期九"),"永续供应中心 0010401",IF(AND(D28="原料入库费用",E28="小料"),"茶饮小料部 0030902",IFERROR(INDEX('费用归属表（快照）'!$D$4:$D$16,MATCH(D28,'费用归属表（快照）'!$A$4:$A$16,0)),"")))) | V28: =IF(D28="","",IFERROR(INDEX('费用归属表（快照）'!$B$4:$B$16,MATCH(D28,'费用归属表（快照）'!$A$4:$A$16,0)),"")) | W28: =IF(OR(E28="",AND(LEFT(T28,4)<>"6601",LEFT(T28,4)<>"6401")),"",IFERROR(IF(INDEX(选项!$I$2:$I$11,MATCH(E28,选项!$H$2:$H$11,0))="","",INDEX(选项!$I$2:$I$11,MATCH(E28,选项!$H$2:$H$11,0))),"")) | X28: =IF(OR(E28="",AND(LEFT(T28,4)<>"6601",LEFT(T28,4)<>"6401")),"",IFERROR(IF(INDEX(选项!$J$2:$J$11,MATCH(E28,选项!$H$2:$H$11,0))="","",INDEX(选项!$J$2:$J$11,MATCH(E28,选项!$H$2:$H$11,0))),""))
A29: 2026-07 | B29: 深圳星期零 | C29: 链盟 | D29: 原料入库费用 | E29: 小料 | F29: 小料 | G29: 月结 | I29: 24600 | J29: =IFERROR(INDEX(供应商列表!$F$4:$R$25,MATCH(C29,供应商列表!$A$4:$A$25,0),MATCH(D29,供应商列表!$F$3:$R$3,0)),"") | K29: =IFERROR(ROUND(I29/(1+J29),2),"") | L29: =IFERROR(I29-K29,"") | M29: =IFERROR(INDEX(供应商列表!$B$4:$B$25,MATCH(C29,供应商列表!$A$4:$A$25,0)),"") | N29: ="计提"&M29&(MID(A29,6,2)*1)&"月"&IFERROR(INDEX(供应商列表!$E$4:$E$25,MATCH(C29,供应商列表!$A$4:$A$25,0)),"线下")&IF(F29<>"",F29,IF(OR(E29="—",E29=""),"",E29))&IFERROR(INDEX('费用归属表（快照）'!$F$4:$F$16,MATCH(D29,'费用归属表（快照）'!$A$4:$A$16,0)),"") | Q29: =IF(P29="","",P29-I29) | T29: =IF(D29="","",IFERROR(INDEX('费用归属表（快照）'!$C$4:$C$16,MATCH(D29,'费用归属表（快照）'!$A$4:$A$16,0)),"")) | U29: =IF(D29="","",IF(AND(D29="销售出库费用",B29="深圳星期九"),"永续供应中心 0010401",IF(AND(D29="原料入库费用",E29="小料"),"茶饮小料部 0030902",IFERROR(INDEX('费用归属表（快照）'!$D$4:$D$16,MATCH(D29,'费用归属表（快照）'!$A$4:$A$16,0)),"")))) | V29: =IF(D29="","",IFERROR(INDEX('费用归属表（快照）'!$B$4:$B$16,MATCH(D29,'费用归属表（快照）'!$A$4:$A$16,0)),"")) | W29: =IF(OR(E29="",AND(LEFT(T29,4)<>"6601",LEFT(T29,4)<>"6401")),"",IFERROR(IF(INDEX(选项!$I$2:$I$11,MATCH(E29,选项!$H$2:$H$11,0))="","",INDEX(选项!$I$2:$I$11,MATCH(E29,选项!$H$2:$H$11,0))),"")) | X29: =IF(OR(E29="",AND(LEFT(T29,4)<>"6601",LEFT(T29,4)<>"6401")),"",IFERROR(IF(INDEX(选项!$J$2:$J$11,MATCH(E29,选项!$H$2:$H$11,0))="","",INDEX(选项!$J$2:$J$11,MATCH(E29,选项!$H$2:$H$11,0))),""))
A30: 2026-07 | B30: 深圳星期零 | C30: 链盟 | D30: 销售出库费用 | E30: 小料 | G30: 月结 | I30: 1407.5 | J30: =IFERROR(INDEX(供应商列表!$F$4:$R$25,MATCH(C30,供应商列表!$A$4:$A$25,0),MATCH(D30,供应商列表!$F$3:$R$3,0)),"") | K30: =IFERROR(ROUND(I30/(1+J30),2),"") | L30: =IFERROR(I30-K30,"") | M30: =IFERROR(INDEX(供应商列表!$B$4:$B$25,MATCH(C30,供应商列表!$A$4:$A$25,0)),"") | N30: ="计提"&M30&(MID(A30,6,2)*1)&"月"&IFERROR(INDEX(供应商列表!$E$4:$E$25,MATCH(C30,供应商列表!$A$4:$A$25,0)),"线下")&IF(F30<>"",F30,IF(OR(E30="—",E30=""),"",E30))&IFERROR(INDEX('费用归属表（快照）'!$F$4:$F$16,MATCH(D30,'费用归属表（快照）'!$A$4:$A$16,0)),"") | Q30: =IF(P30="","",P30-I30) | T30: =IF(D30="","",IFERROR(INDEX('费用归属表（快照）'!$C$4:$C$16,MATCH(D30,'费用归属表（快照）'!$A$4:$A$16,0)),"")) | U30: =IF(D30="","",IF(AND(D30="销售出库费用",B30="深圳星期九"),"永续供应中心 0010401",IF(AND(D30="原料入库费用",E30="小料"),"茶饮小料部 0030902",IFERROR(INDEX('费用归属表（快照）'!$D$4:$D$16,MATCH(D30,'费用归属表（快照）'!$A$4:$A$16,0)),"")))) | V30: =IF(D30="","",IFERROR(INDEX('费用归属表（快照）'!$B$4:$B$16,MATCH(D30,'费用归属表（快照）'!$A$4:$A$16,0)),"")) | W30: =IF(OR(E30="",AND(LEFT(T30,4)<>"6601",LEFT(T30,4)<>"6401")),"",IFERROR(IF(INDEX(选项!$I$2:$I$11,MATCH(E30,选项!$H$2:$H$11,0))="","",INDEX(选项!$I$2:$I$11,MATCH(E30,选项!$H$2:$H$11,0))),"")) | X30: =IF(OR(E30="",AND(LEFT(T30,4)<>"6601",LEFT(T30,4)<>"6401")),"",IFERROR(IF(INDEX(选项!$J$2:$J$11,MATCH(E30,选项!$H$2:$H$11,0))="","",INDEX(选项!$J$2:$J$11,MATCH(E30,选项!$H$2:$H$11,0))),""))
A31: 2026-07 | B31: 深圳星期零 | C31: 路凯（13%） | D31: 销售出库费用 | E31: 山姆零售 | G31: 月结 | I31: 3265.31 | J31: =IFERROR(INDEX(供应商列表!$F$4:$R$25,MATCH(C31,供应商列表!$A$4:$A$25,0),MATCH(D31,供应商列表!$F$3:$R$3,0)),"") | K31: =IFERROR(ROUND(I31/(1+J31),2),"") | L31: =IFERROR(I31-K31,"") | M31: =IFERROR(INDEX(供应商列表!$B$4:$B$25,MATCH(C31,供应商列表!$A$4:$A$25,0)),"") | N31: ="计提"&M31&(MID(A31,6,2)*1)&"月"&IFERROR(INDEX(供应商列表!$E$4:$E$25,MATCH(C31,供应商列表!$A$4:$A$25,0)),"线下")&IF(F31<>"",F31,IF(OR(E31="—",E31=""),"",E31))&IFERROR(INDEX('费用归属表（快照）'!$F$4:$F$16,MATCH(D31,'费用归属表（快照）'!$A$4:$A$16,0)),"") | Q31: =IF(P31="","",P31-I31) | T31: =IF(D31="","",IFERROR(INDEX('费用归属表（快照）'!$C$4:$C$16,MATCH(D31,'费用归属表（快照）'!$A$4:$A$16,0)),"")) | U31: =IF(D31="","",IF(AND(D31="销售出库费用",B31="深圳星期九"),"永续供应中心 0010401",IF(AND(D31="原料入库费用",E31="小料"),"茶饮小料部 0030902",IFERROR(INDEX('费用归属表（快照）'!$D$4:$D$16,MATCH(D31,'费用归属表（快照）'!$A$4:$A$16,0)),"")))) | V31: =IF(D31="","",IFERROR(INDEX('费用归属表（快照）'!$B$4:$B$16,MATCH(D31,'费用归属表（快照）'!$A$4:$A$16,0)),"")) | W31: =IF(OR(E31="",AND(LEFT(T31,4)<>"6601",LEFT(T31,4)<>"6401")),"",IFERROR(IF(INDEX(选项!$I$2:$I$11,MATCH(E31,选项!$H$2:$H$11,0))="","",INDEX(选项!$I$2:$I$11,MATCH(E31,选项!$H$2:$H$11,0))),"")) | X31: =IF(OR(E31="",AND(LEFT(T31,4)<>"6601",LEFT(T31,4)<>"6401")),"",IFERROR(IF(INDEX(选项!$J$2:$J$11,MATCH(E31,选项!$H$2:$H$11,0))="","",INDEX(选项!$J$2:$J$11,MATCH(E31,选项!$H$2:$H$11,0))),""))
A32: 2026-07 | B32: 深圳星期零 | C32: 中通快运 | D32: 销售出库费用 | E32: 植物肉 | G32: 月结 | I32: 208.6 | J32: =IFERROR(INDEX(供应商列表!$F$4:$R$25,MATCH(C32,供应商列表!$A$4:$A$25,0),MATCH(D32,供应商列表!$F$3:$R$3,0)),"") | K32: =IFERROR(ROUND(I32/(1+J32),2),"") | L32: =IFERROR(I32-K32,"") | M32: =IFERROR(INDEX(供应商列表!$B$4:$B$25,MATCH(C32,供应商列表!$A$4:$A$25,0)),"") | N32: ="计提"&M32&(MID(A32,6,2)*1)&"月"&IFERROR(INDEX(供应商列表!$E$4:$E$25,MATCH(C32,供应商列表!$A$4:$A$25,0)),"线下")&IF(F32<>"",F32,IF(OR(E32="—",E32=""),"",E32))&IFERROR(INDEX('费用归属表（快照）'!$F$4:$F$16,MATCH(D32,'费用归属表（快照）'!$A$4:$A$16,0)),"") | Q32: =IF(P32="","",P32-I32) | T32: =IF(D32="","",IFERROR(INDEX('费用归属表（快照）'!$C$4:$C$16,MATCH(D32,'费用归属表（快照）'!$A$4:$A$16,0)),"")) | U32: =IF(D32="","",IF(AND(D32="销售出库费用",B32="深圳星期九"),"永续供应中心 0010401",IF(AND(D32="原料入库费用",E32="小料"),"茶饮小料部 0030902",IFERROR(INDEX('费用归属表（快照）'!$D$4:$D$16,MATCH(D32,'费用归属表（快照）'!$A$4:$A$16,0)),"")))) | V32: =IF(D32="","",IFERROR(INDEX('费用归属表（快照）'!$B$4:$B$16,MATCH(D32,'费用归属表（快照）'!$A$4:$A$16,0)),"")) | W32: =IF(OR(E32="",AND(LEFT(T32,4)<>"6601",LEFT(T32,4)<>"6401")),"",IFERROR(IF(INDEX(选项!$I$2:$I$11,MATCH(E32,选项!$H$2:$H$11,0))="","",INDEX(选项!$I$2:$I$11,MATCH(E32,选项!$H$2:$H$11,0))),"")) | X32: =IF(OR(E32="",AND(LEFT(T32,4)<>"6601",LEFT(T32,4)<>"6401")),"",IFERROR(IF(INDEX(选项!$J$2:$J$11,MATCH(E32,选项!$H$2:$H$11,0))="","",INDEX(选项!$J$2:$J$11,MATCH(E32,选项!$H$2:$H$11,0))),""))
A33: 2026-07 | B33: 深圳星期零 | C33: 中通快运 | D33: 销售出库费用 | E33: 山姆零售 | G33: 月结 | I33: 26.25 | J33: =IFERROR(INDEX(供应商列表!$F$4:$R$25,MATCH(C33,供应商列表!$A$4:$A$25,0),MATCH(D33,供应商列表!$F$3:$R$3,0)),"") | K33: =IFERROR(ROUND(I33/(1+J33),2),"") | L33: =IFERROR(I33-K33,"") | M33: =IFERROR(INDEX(供应商列表!$B$4:$B$25,MATCH(C33,供应商列表!$A$4:$A$25,0)),"") | N33: ="计提"&M33&(MID(A33,6,2)*1)&"月"&IFERROR(INDEX(供应商列表!$E$4:$E$25,MATCH(C33,供应商列表!$A$4:$A$25,0)),"线下")&IF(F33<>"",F33,IF(OR(E33="—",E33=""),"",E33))&IFERROR(INDEX('费用归属表（快照）'!$F$4:$F$16,MATCH(D33,'费用归属表（快照）'!$A$4:$A$16,0)),"") | Q33: =IF(P33="","",P33-I33) | T33: =IF(D33="","",IFERROR(INDEX('费用归属表（快照）'!$C$4:$C$16,MATCH(D33,'费用归属表（快照）'!$A$4:$A$16,0)),"")) | U33: =IF(D33="","",IF(AND(D33="销售出库费用",B33="深圳星期九"),"永续供应中心 0010401",IF(AND(D33="原料入库费用",E33="小料"),"茶饮小料部 0030902",IFERROR(INDEX('费用归属表（快照）'!$D$4:$D$16,MATCH(D33,'费用归属表（快照）'!$A$4:$A$16,0)),"")))) | V33: =IF(D33="","",IFERROR(INDEX('费用归属表（快照）'!$B$4:$B$16,MATCH(D33,'费用归属表（快照）'!$A$4:$A$16,0)),"")) | W33: =IF(OR(E33="",AND(LEFT(T33,4)<>"6601",LEFT(T33,4)<>"6401")),"",IFERROR(IF(INDEX(选项!$I$2:$I$11,MATCH(E33,选项!$H$2:$H$11,0))="","",INDEX(选项!$I$2:$I$11,MATCH(E33,选项!$H$2:$H$11,0))),"")) | X33: =IF(OR(E33="",AND(LEFT(T33,4)<>"6601",LEFT(T33,4)<>"6401")),"",IFERROR(IF(INDEX(选项!$J$2:$J$11,MATCH(E33,选项!$H$2:$H$11,0))="","",INDEX(选项!$J$2:$J$11,MATCH(E33,选项!$H$2:$H$11,0))),""))
A34: 2026-07 | B34: 深圳星期零 | C34: 中通快运 | D34: 销售出库费用 | E34: 零售 | G34: 月结 | I34: 21 | J34: =IFERROR(INDEX(供应商列表!$F$4:$R$25,MATCH(C34,供应商列表!$A$4:$A$25,0),MATCH(D34,供应商列表!$F$3:$R$3,0)),"") | K34: =IFERROR(ROUND(I34/(1+J34),2),"") | L34: =IFERROR(I34-K34,"") | M34: =IFERROR(INDEX(供应商列表!$B$4:$B$25,MATCH(C34,供应商列表!$A$4:$A$25,0)),"") | N34: ="计提"&M34&(MID(A34,6,2)*1)&"月"&IFERROR(INDEX(供应商列表!$E$4:$E$25,MATCH(C34,供应商列表!$A$4:$A$25,0)),"线下")&IF(F34<>"",F34,IF(OR(E34="—",E34=""),"",E34))&IFERROR(INDEX('费用归属表（快照）'!$F$4:$F$16,MATCH(D34,'费用归属表（快照）'!$A$4:$A$16,0)),"") | Q34: =IF(P34="","",P34-I34) | T34: =IF(D34="","",IFERROR(INDEX('费用归属表（快照）'!$C$4:$C$16,MATCH(D34,'费用归属表（快照）'!$A$4:$A$16,0)),"")) | U34: =IF(D34="","",IF(AND(D34="销售出库费用",B34="深圳星期九"),"永续供应中心 0010401",IF(AND(D34="原料入库费用",E34="小料"),"茶饮小料部 0030902",IFERROR(INDEX('费用归属表（快照）'!$D$4:$D$16,MATCH(D34,'费用归属表（快照）'!$A$4:$A$16,0)),"")))) | V34: =IF(D34="","",IFERROR(INDEX('费用归属表（快照）'!$B$4:$B$16,MATCH(D34,'费用归属表（快照）'!$A$4:$A$16,0)),"")) | W34: =IF(OR(E34="",AND(LEFT(T34,4)<>"6601",LEFT(T34,4)<>"6401")),"",IFERROR(IF(INDEX(选项!$I$2:$I$11,MATCH(E34,选项!$H$2:$H$11,0))="","",INDEX(选项!$I$2:$I$11,MATCH(E34,选项!$H$2:$H$11,0))),"")) | X34: =IF(OR(E34="",AND(LEFT(T34,4)<>"6601",LEFT(T34,4)<>"6401")),"",IFERROR(IF(INDEX(选项!$J$2:$J$11,MATCH(E34,选项!$H$2:$H$11,0))="","",INDEX(选项!$J$2:$J$11,MATCH(E34,选项!$H$2:$H$11,0))),""))
A35: 2026-07 | B35: 深圳星期零 | C35: 中通快运 | D35: 研发设备采购 | E35: — | G35: 月结 | I35: 207.1 | J35: =IFERROR(INDEX(供应商列表!$F$4:$R$25,MATCH(C35,供应商列表!$A$4:$A$25,0),MATCH(D35,供应商列表!$F$3:$R$3,0)),"") | K35: =IFERROR(ROUND(I35/(1+J35),2),"") | L35: =IFERROR(I35-K35,"") | M35: =IFERROR(INDEX(供应商列表!$B$4:$B$25,MATCH(C35,供应商列表!$A$4:$A$25,0)),"") | N35: ="计提"&M35&(MID(A35,6,2)*1)&"月"&IFERROR(INDEX(供应商列表!$E$4:$E$25,MATCH(C35,供应商列表!$A$4:$A$25,0)),"线下")&IF(F35<>"",F35,IF(OR(E35="—",E35=""),"",E35))&IFERROR(INDEX('费用归属表（快照）'!$F$4:$F$16,MATCH(D35,'费用归属表（快照）'!$A$4:$A$16,0)),"") | Q35: =IF(P35="","",P35-I35) | T35: =IF(D35="","",IFERROR(INDEX('费用归属表（快照）'!$C$4:$C$16,MATCH(D35,'费用归属表（快照）'!$A$4:$A$16,0)),"")) | U35: =IF(D35="","",IF(AND(D35="销售出库费用",B35="深圳星期九"),"永续供应中心 0010401",IF(AND(D35="原料入库费用",E35="小料"),"茶饮小料部 0030902",IFERROR(INDEX('费用归属表（快照）'!$D$4:$D$16,MATCH(D35,'费用归属表（快照）'!$A$4:$A$16,0)),"")))) | V35: =IF(D35="","",IFERROR(INDEX('费用归属表（快照）'!$B$4:$B$16,MATCH(D35,'费用归属表（快照）'!$A$4:$A$16,0)),"")) | W35: =IF(OR(E35="",AND(LEFT(T35,4)<>"6601",LEFT(T35,4)<>"6401")),"",IFERROR(IF(INDEX(选项!$I$2:$I$11,MATCH(E35,选项!$H$2:$H$11,0))="","",INDEX(选项!$I$2:$I$11,MATCH(E35,选项!$H$2:$H$11,0))),"")) | X35: =IF(OR(E35="",AND(LEFT(T35,4)<>"6601",LEFT(T35,4)<>"6401")),"",IFERROR(IF(INDEX(选项!$J$2:$J$11,MATCH(E35,选项!$H$2:$H$11,0))="","",INDEX(选项!$J$2:$J$11,MATCH(E35,选项!$H$2:$H$11,0))),""))
A36: 2026-07 | B36: 深圳星期零 | C36: 极鲜达 | D36: 销售出库费用 | E36: 植物肉 | G36: 月结 | I36: 13607.96 | J36: =IFERROR(INDEX(供应商列表!$F$4:$R$25,MATCH(C36,供应商列表!$A$4:$A$25,0),MATCH(D36,供应商列表!$F$3:$R$3,0)),"") | K36: =IFERROR(ROUND(I36/(1+J36),2),"") | L36: =IFERROR(I36-K36,"") | M36: =IFERROR(INDEX(供应商列表!$B$4:$B$25,MATCH(C36,供应商列表!$A$4:$A$25,0)),"") | N36: ="计提"&M36&(MID(A36,6,2)*1)&"月"&IFERROR(INDEX(供应商列表!$E$4:$E$25,MATCH(C36,供应商列表!$A$4:$A$25,0)),"线下")&IF(F36<>"",F36,IF(OR(E36="—",E36=""),"",E36))&IFERROR(INDEX('费用归属表（快照）'!$F$4:$F$16,MATCH(D36,'费用归属表（快照）'!$A$4:$A$16,0)),"") | Q36: =IF(P36="","",P36-I36) | T36: =IF(D36="","",IFERROR(INDEX('费用归属表（快照）'!$C$4:$C$16,MATCH(D36,'费用归属表（快照）'!$A$4:$A$16,0)),"")) | U36: =IF(D36="","",IF(AND(D36="销售出库费用",B36="深圳星期九"),"永续供应中心 0010401",IF(AND(D36="原料入库费用",E36="小料"),"茶饮小料部 0030902",IFERROR(INDEX('费用归属表（快照）'!$D$4:$D$16,MATCH(D36,'费用归属表（快照）'!$A$4:$A$16,0)),"")))) | V36: =IF(D36="","",IFERROR(INDEX('费用归属表（快照）'!$B$4:$B$16,MATCH(D36,'费用归属表（快照）'!$A$4:$A$16,0)),"")) | W36: =IF(OR(E36="",AND(LEFT(T36,4)<>"6601",LEFT(T36,4)<>"6401")),"",IFERROR(IF(INDEX(选项!$I$2:$I$11,MATCH(E36,选项!$H$2:$H$11,0))="","",INDEX(选项!$I$2:$I$11,MATCH(E36,选项!$H$2:$H$11,0))),"")) | X36: =IF(OR(E36="",AND(LEFT(T36,4)<>"6601",LEFT(T36,4)<>"6401")),"",IFERROR(IF(INDEX(选项!$J$2:$J$11,MATCH(E36,选项!$H$2:$H$11,0))="","",INDEX(选项!$J$2:$J$11,MATCH(E36,选项!$H$2:$H$11,0))),""))
A37: 2026-07 | B37: 深圳星期零 | C37: 极鲜达 | D37: 销售出库费用 | E37: 山姆零售 | G37: 月结 | I37: 118762.7 | J37: =IFERROR(INDEX(供应商列表!$F$4:$R$25,MATCH(C37,供应商列表!$A$4:$A$25,0),MATCH(D37,供应商列表!$F$3:$R$3,0)),"") | K37: =IFERROR(ROUND(I37/(1+J37),2),"") | L37: =IFERROR(I37-K37,"") | M37: =IFERROR(INDEX(供应商列表!$B$4:$B$25,MATCH(C37,供应商列表!$A$4:$A$25,0)),"") | N37: ="计提"&M37&(MID(A37,6,2)*1)&"月"&IFERROR(INDEX(供应商列表!$E$4:$E$25,MATCH(C37,供应商列表!$A$4:$A$25,0)),"线下")&IF(F37<>"",F37,IF(OR(E37="—",E37=""),"",E37))&IFERROR(INDEX('费用归属表（快照）'!$F$4:$F$16,MATCH(D37,'费用归属表（快照）'!$A$4:$A$16,0)),"") | Q37: =IF(P37="","",P37-I37) | T37: =IF(D37="","",IFERROR(INDEX('费用归属表（快照）'!$C$4:$C$16,MATCH(D37,'费用归属表（快照）'!$A$4:$A$16,0)),"")) | U37: =IF(D37="","",IF(AND(D37="销售出库费用",B37="深圳星期九"),"永续供应中心 0010401",IF(AND(D37="原料入库费用",E37="小料"),"茶饮小料部 0030902",IFERROR(INDEX('费用归属表（快照）'!$D$4:$D$16,MATCH(D37,'费用归属表（快照）'!$A$4:$A$16,0)),"")))) | V37: =IF(D37="","",IFERROR(INDEX('费用归属表（快照）'!$B$4:$B$16,MATCH(D37,'费用归属表（快照）'!$A$4:$A$16,0)),"")) | W37: =IF(OR(E37="",AND(LEFT(T37,4)<>"6601",LEFT(T37,4)<>"6401")),"",IFERROR(IF(INDEX(选项!$I$2:$I$11,MATCH(E37,选项!$H$2:$H$11,0))="","",INDEX(选项!$I$2:$I$11,MATCH(E37,选项!$H$2:$H$11,0))),"")) | X37: =IF(OR(E37="",AND(LEFT(T37,4)<>"6601",LEFT(T37,4)<>"6401")),"",IFERROR(IF(INDEX(选项!$J$2:$J$11,MATCH(E37,选项!$H$2:$H$11,0))="","",INDEX(选项!$J$2:$J$11,MATCH(E37,选项!$H$2:$H$11,0))),""))
A38: 2026-07 | B38: 深圳星期零 | C38: 极鲜达 | D38: 销售出库费用 | E38: 豆蛋制品 | G38: 月结 | I38: 12814.27 | J38: =IFERROR(INDEX(供应商列表!$F$4:$R$25,MATCH(C38,供应商列表!$A$4:$A$25,0),MATCH(D38,供应商列表!$F$3:$R$3,0)),"") | K38: =IFERROR(ROUND(I38/(1+J38),2),"") | L38: =IFERROR(I38-K38,"") | M38: =IFERROR(INDEX(供应商列表!$B$4:$B$25,MATCH(C38,供应商列表!$A$4:$A$25,0)),"") | N38: ="计提"&M38&(MID(A38,6,2)*1)&"月"&IFERROR(INDEX(供应商列表!$E$4:$E$25,MATCH(C38,供应商列表!$A$4:$A$25,0)),"线下")&IF(F38<>"",F38,IF(OR(E38="—",E38=""),"",E38))&IFERROR(INDEX('费用归属表（快照）'!$F$4:$F$16,MATCH(D38,'费用归属表（快照）'!$A$4:$A$16,0)),"") | Q38: =IF(P38="","",P38-I38) | T38: =IF(D38="","",IFERROR(INDEX('费用归属表（快照）'!$C$4:$C$16,MATCH(D38,'费用归属表（快照）'!$A$4:$A$16,0)),"")) | U38: =IF(D38="","",IF(AND(D38="销售出库费用",B38="深圳星期九"),"永续供应中心 0010401",IF(AND(D38="原料入库费用",E38="小料"),"茶饮小料部 0030902",IFERROR(INDEX('费用归属表（快照）'!$D$4:$D$16,MATCH(D38,'费用归属表（快照）'!$A$4:$A$16,0)),"")))) | V38: =IF(D38="","",IFERROR(INDEX('费用归属表（快照）'!$B$4:$B$16,MATCH(D38,'费用归属表（快照）'!$A$4:$A$16,0)),"")) | W38: =IF(OR(E38="",AND(LEFT(T38,4)<>"6601",LEFT(T38,4)<>"6401")),"",IFERROR(IF(INDEX(选项!$I$2:$I$11,MATCH(E38,选项!$H$2:$H$11,0))="","",INDEX(选项!$I$2:$I$11,MATCH(E38,选项!$H$2:$H$11,0))),"")) | X38: =IF(OR(E38="",AND(LEFT(T38,4)<>"6601",LEFT(T38,4)<>"6401")),"",IFERROR(IF(INDEX(选项!$J$2:$J$11,MATCH(E38,选项!$H$2:$H$11,0))="","",INDEX(选项!$J$2:$J$11,MATCH(E38,选项!$H$2:$H$11,0))),""))
A39: 2026-07 | B39: 深圳星期零 | C39: 极鲜达 | D39: 销售出库费用 | E39: 零售 | G39: 月结 | I39: 12088.75 | J39: =IFERROR(INDEX(供应商列表!$F$4:$R$25,MATCH(C39,供应商列表!$A$4:$A$25,0),MATCH(D39,供应商列表!$F$3:$R$3,0)),"") | K39: =IFERROR(ROUND(I39/(1+J39),2),"") | L39: =IFERROR(I39-K39,"") | M39: =IFERROR(INDEX(供应商列表!$B$4:$B$25,MATCH(C39,供应商列表!$A$4:$A$25,0)),"") | N39: ="计提"&M39&(MID(A39,6,2)*1)&"月"&IFERROR(INDEX(供应商列表!$E$4:$E$25,MATCH(C39,供应商列表!$A$4:$A$25,0)),"线下")&IF(F39<>"",F39,IF(OR(E39="—",E39=""),"",E39))&IFERROR(INDEX('费用归属表（快照）'!$F$4:$F$16,MATCH(D39,'费用归属表（快照）'!$A$4:$A$16,0)),"") | Q39: =IF(P39="","",P39-I39) | T39: =IF(D39="","",IFERROR(INDEX('费用归属表（快照）'!$C$4:$C$16,MATCH(D39,'费用归属表（快照）'!$A$4:$A$16,0)),"")) | U39: =IF(D39="","",IF(AND(D39="销售出库费用",B39="深圳星期九"),"永续供应中心 0010401",IF(AND(D39="原料入库费用",E39="小料"),"茶饮小料部 0030902",IFERROR(INDEX('费用归属表（快照）'!$D$4:$D$16,MATCH(D39,'费用归属表（快照）'!$A$4:$A$16,0)),"")))) | V39: =IF(D39="","",IFERROR(INDEX('费用归属表（快照）'!$B$4:$B$16,MATCH(D39,'费用归属表（快照）'!$A$4:$A$16,0)),"")) | W39: =IF(OR(E39="",AND(LEFT(T39,4)<>"6601",LEFT(T39,4)<>"6401")),"",IFERROR(IF(INDEX(选项!$I$2:$I$11,MATCH(E39,选项!$H$2:$H$11,0))="","",INDEX(选项!$I$2:$I$11,MATCH(E39,选项!$H$2:$H$11,0))),"")) | X39: =IF(OR(E39="",AND(LEFT(T39,4)<>"6601",LEFT(T39,4)<>"6401")),"",IFERROR(IF(INDEX(选项!$J$2:$J$11,MATCH(E39,选项!$H$2:$H$11,0))="","",INDEX(选项!$J$2:$J$11,MATCH(E39,选项!$H$2:$H$11,0))),""))
A40: 2026-07 | B40: 深圳星期零 | C40: 极鲜达 | D40: 销售出库费用 | E40: 小料 | G40: 月结 | I40: 18086.67 | J40: =IFERROR(INDEX(供应商列表!$F$4:$R$25,MATCH(C40,供应商列表!$A$4:$A$25,0),MATCH(D40,供应商列表!$F$3:$R$3,0)),"") | K40: =IFERROR(ROUND(I40/(1+J40),2),"") | L40: =IFERROR(I40-K40,"") | M40: =IFERROR(INDEX(供应商列表!$B$4:$B$25,MATCH(C40,供应商列表!$A$4:$A$25,0)),"") | N40: ="计提"&M40&(MID(A40,6,2)*1)&"月"&IFERROR(INDEX(供应商列表!$E$4:$E$25,MATCH(C40,供应商列表!$A$4:$A$25,0)),"线下")&IF(F40<>"",F40,IF(OR(E40="—",E40=""),"",E40))&IFERROR(INDEX('费用归属表（快照）'!$F$4:$F$16,MATCH(D40,'费用归属表（快照）'!$A$4:$A$16,0)),"") | Q40: =IF(P40="","",P40-I40) | T40: =IF(D40="","",IFERROR(INDEX('费用归属表（快照）'!$C$4:$C$16,MATCH(D40,'费用归属表（快照）'!$A$4:$A$16,0)),"")) | U40: =IF(D40="","",IF(AND(D40="销售出库费用",B40="深圳星期九"),"永续供应中心 0010401",IF(AND(D40="原料入库费用",E40="小料"),"茶饮小料部 0030902",IFERROR(INDEX('费用归属表（快照）'!$D$4:$D$16,MATCH(D40,'费用归属表（快照）'!$A$4:$A$16,0)),"")))) | V40: =IF(D40="","",IFERROR(INDEX('费用归属表（快照）'!$B$4:$B$16,MATCH(D40,'费用归属表（快照）'!$A$4:$A$16,0)),"")) | W40: =IF(OR(E40="",AND(LEFT(T40,4)<>"6601",LEFT(T40,4)<>"6401")),"",IFERROR(IF(INDEX(选项!$I$2:$I$11,MATCH(E40,选项!$H$2:$H$11,0))="","",INDEX(选项!$I$2:$I$11,MATCH(E40,选项!$H$2:$H$11,0))),"")) | X40: =IF(OR(E40="",AND(LEFT(T40,4)<>"6601",LEFT(T40,4)<>"6401")),"",IFERROR(IF(INDEX(选项!$J$2:$J$11,MATCH(E40,选项!$H$2:$H$11,0))="","",INDEX(选项!$J$2:$J$11,MATCH(E40,选项!$H$2:$H$11,0))),""))
A41: 2026-07 | B41: 深圳星期零 | C41: 极鲜达 | D41: 研发设备采购 | E41: — | G41: 月结 | I41: 595 | J41: =IFERROR(INDEX(供应商列表!$F$4:$R$25,MATCH(C41,供应商列表!$A$4:$A$25,0),MATCH(D41,供应商列表!$F$3:$R$3,0)),"") | K41: =IFERROR(ROUND(I41/(1+J41),2),"") | L41: =IFERROR(I41-K41,"") | M41: =IFERROR(INDEX(供应商列表!$B$4:$B$25,MATCH(C41,供应商列表!$A$4:$A$25,0)),"") | N41: ="计提"&M41&(MID(A41,6,2)*1)&"月"&IFERROR(INDEX(供应商列表!$E$4:$E$25,MATCH(C41,供应商列表!$A$4:$A$25,0)),"线下")&IF(F41<>"",F41,IF(OR(E41="—",E41=""),"",E41))&IFERROR(INDEX('费用归属表（快照）'!$F$4:$F$16,MATCH(D41,'费用归属表（快照）'!$A$4:$A$16,0)),"") | Q41: =IF(P41="","",P41-I41) | T41: =IF(D41="","",IFERROR(INDEX('费用归属表（快照）'!$C$4:$C$16,MATCH(D41,'费用归属表（快照）'!$A$4:$A$16,0)),"")) | U41: =IF(D41="","",IF(AND(D41="销售出库费用",B41="深圳星期九"),"永续供应中心 0010401",IF(AND(D41="原料入库费用",E41="小料"),"茶饮小料部 0030902",IFERROR(INDEX('费用归属表（快照）'!$D$4:$D$16,MATCH(D41,'费用归属表（快照）'!$A$4:$A$16,0)),"")))) | V41: =IF(D41="","",IFERROR(INDEX('费用归属表（快照）'!$B$4:$B$16,MATCH(D41,'费用归属表（快照）'!$A$4:$A$16,0)),"")) | W41: =IF(OR(E41="",AND(LEFT(T41,4)<>"6601",LEFT(T41,4)<>"6401")),"",IFERROR(IF(INDEX(选项!$I$2:$I$11,MATCH(E41,选项!$H$2:$H$11,0))="","",INDEX(选项!$I$2:$I$11,MATCH(E41,选项!$H$2:$H$11,0))),"")) | X41: =IF(OR(E41="",AND(LEFT(T41,4)<>"6601",LEFT(T41,4)<>"6401")),"",IFERROR(IF(INDEX(选项!$J$2:$J$11,MATCH(E41,选项!$H$2:$H$11,0))="","",INDEX(选项!$J$2:$J$11,MATCH(E41,选项!$H$2:$H$11,0))),""))
A42: 2026-07 | B42: 深圳星期零 | C42: 极鲜达 | D42: 成品入库费用 | E42: — | F42: 代工厂 | G42: 月结 | I42: 1526.51 | J42: =IFERROR(INDEX(供应商列表!$F$4:$R$25,MATCH(C42,供应商列表!$A$4:$A$25,0),MATCH(D42,供应商列表!$F$3:$R$3,0)),"") | K42: =IFERROR(ROUND(I42/(1+J42),2),"") | L42: =IFERROR(I42-K42,"") | M42: =IFERROR(INDEX(供应商列表!$B$4:$B$25,MATCH(C42,供应商列表!$A$4:$A$25,0)),"") | N42: ="计提"&M42&(MID(A42,6,2)*1)&"月"&IFERROR(INDEX(供应商列表!$E$4:$E$25,MATCH(C42,供应商列表!$A$4:$A$25,0)),"线下")&IF(F42<>"",F42,IF(OR(E42="—",E42=""),"",E42))&IFERROR(INDEX('费用归属表（快照）'!$F$4:$F$16,MATCH(D42,'费用归属表（快照）'!$A$4:$A$16,0)),"") | Q42: =IF(P42="","",P42-I42) | T42: =IF(D42="","",IFERROR(INDEX('费用归属表（快照）'!$C$4:$C$16,MATCH(D42,'费用归属表（快照）'!$A$4:$A$16,0)),"")) | U42: =IF(D42="","",IF(AND(D42="销售出库费用",B42="深圳星期九"),"永续供应中心 0010401",IF(AND(D42="原料入库费用",E42="小料"),"茶饮小料部 0030902",IFERROR(INDEX('费用归属表（快照）'!$D$4:$D$16,MATCH(D42,'费用归属表（快照）'!$A$4:$A$16,0)),"")))) | V42: =IF(D42="","",IFERROR(INDEX('费用归属表（快照）'!$B$4:$B$16,MATCH(D42,'费用归属表（快照）'!$A$4:$A$16,0)),"")) | W42: =IF(OR(E42="",AND(LEFT(T42,4)<>"6601",LEFT(T42,4)<>"6401")),"",IFERROR(IF(INDEX(选项!$I$2:$I$11,MATCH(E42,选项!$H$2:$H$11,0))="","",INDEX(选项!$I$2:$I$11,MATCH(E42,选项!$H$2:$H$11,0))),"")) | X42: =IF(OR(E42="",AND(LEFT(T42,4)<>"6601",LEFT(T42,4)<>"6401")),"",IFERROR(IF(INDEX(选项!$J$2:$J$11,MATCH(E42,选项!$H$2:$H$11,0))="","",INDEX(选项!$J$2:$J$11,MATCH(E42,选项!$H$2:$H$11,0))),""))
A43: 2026-07 | B43: 深圳星期零 | C43: 极鲜达 | D43: 原料入库费用 | E43: — | F43: 孝感工厂 | G43: 月结 | I43: 4860 | J43: =IFERROR(INDEX(供应商列表!$F$4:$R$25,MATCH(C43,供应商列表!$A$4:$A$25,0),MATCH(D43,供应商列表!$F$3:$R$3,0)),"") | K43: =IFERROR(ROUND(I43/(1+J43),2),"") | L43: =IFERROR(I43-K43,"") | M43: =IFERROR(INDEX(供应商列表!$B$4:$B$25,MATCH(C43,供应商列表!$A$4:$A$25,0)),"") | N43: ="计提"&M43&(MID(A43,6,2)*1)&"月"&IFERROR(INDEX(供应商列表!$E$4:$E$25,MATCH(C43,供应商列表!$A$4:$A$25,0)),"线下")&IF(F43<>"",F43,IF(OR(E43="—",E43=""),"",E43))&IFERROR(INDEX('费用归属表（快照）'!$F$4:$F$16,MATCH(D43,'费用归属表（快照）'!$A$4:$A$16,0)),"") | Q43: =IF(P43="","",P43-I43) | T43: =IF(D43="","",IFERROR(INDEX('费用归属表（快照）'!$C$4:$C$16,MATCH(D43,'费用归属表（快照）'!$A$4:$A$16,0)),"")) | U43: =IF(D43="","",IF(AND(D43="销售出库费用",B43="深圳星期九"),"永续供应中心 0010401",IF(AND(D43="原料入库费用",E43="小料"),"茶饮小料部 0030902",IFERROR(INDEX('费用归属表（快照）'!$D$4:$D$16,MATCH(D43,'费用归属表（快照）'!$A$4:$A$16,0)),"")))) | V43: =IF(D43="","",IFERROR(INDEX('费用归属表（快照）'!$B$4:$B$16,MATCH(D43,'费用归属表（快照）'!$A$4:$A$16,0)),"")) | W43: =IF(OR(E43="",AND(LEFT(T43,4)<>"6601",LEFT(T43,4)<>"6401")),"",IFERROR(IF(INDEX(选项!$I$2:$I$11,MATCH(E43,选项!$H$2:$H$11,0))="","",INDEX(选项!$I$2:$I$11,MATCH(E43,选项!$H$2:$H$11,0))),"")) | X43: =IF(OR(E43="",AND(LEFT(T43,4)<>"6601",LEFT(T43,4)<>"6401")),"",IFERROR(IF(INDEX(选项!$J$2:$J$11,MATCH(E43,选项!$H$2:$H$11,0))="","",INDEX(选项!$J$2:$J$11,MATCH(E43,选项!$H$2:$H$11,0))),""))
A44: 2026-07 | B44: 深圳星期零 | C44: 极鲜达 | D44: 原料入库费用 | E44: 小料 | F44: 小料 | G44: 月结 | I44: 1750 | J44: =IFERROR(INDEX(供应商列表!$F$4:$R$25,MATCH(C44,供应商列表!$A$4:$A$25,0),MATCH(D44,供应商列表!$F$3:$R$3,0)),"") | K44: =IFERROR(ROUND(I44/(1+J44),2),"") | L44: =IFERROR(I44-K44,"") | M44: =IFERROR(INDEX(供应商列表!$B$4:$B$25,MATCH(C44,供应商列表!$A$4:$A$25,0)),"") | N44: ="计提"&M44&(MID(A44,6,2)*1)&"月"&IFERROR(INDEX(供应商列表!$E$4:$E$25,MATCH(C44,供应商列表!$A$4:$A$25,0)),"线下")&IF(F44<>"",F44,IF(OR(E44="—",E44=""),"",E44))&IFERROR(INDEX('费用归属表（快照）'!$F$4:$F$16,MATCH(D44,'费用归属表（快照）'!$A$4:$A$16,0)),"") | Q44: =IF(P44="","",P44-I44) | T44: =IF(D44="","",IFERROR(INDEX('费用归属表（快照）'!$C$4:$C$16,MATCH(D44,'费用归属表（快照）'!$A$4:$A$16,0)),"")) | U44: =IF(D44="","",IF(AND(D44="销售出库费用",B44="深圳星期九"),"永续供应中心 0010401",IF(AND(D44="原料入库费用",E44="小料"),"茶饮小料部 0030902",IFERROR(INDEX('费用归属表（快照）'!$D$4:$D$16,MATCH(D44,'费用归属表（快照）'!$A$4:$A$16,0)),"")))) | V44: =IF(D44="","",IFERROR(INDEX('费用归属表（快照）'!$B$4:$B$16,MATCH(D44,'费用归属表（快照）'!$A$4:$A$16,0)),"")) | W44: =IF(OR(E44="",AND(LEFT(T44,4)<>"6601",LEFT(T44,4)<>"6401")),"",IFERROR(IF(INDEX(选项!$I$2:$I$11,MATCH(E44,选项!$H$2:$H$11,0))="","",INDEX(选项!$I$2:$I$11,MATCH(E44,选项!$H$2:$H$11,0))),"")) | X44: =IF(OR(E44="",AND(LEFT(T44,4)<>"6601",LEFT(T44,4)<>"6401")),"",IFERROR(IF(INDEX(选项!$J$2:$J$11,MATCH(E44,选项!$H$2:$H$11,0))="","",INDEX(选项!$J$2:$J$11,MATCH(E44,选项!$H$2:$H$11,0))),""))
A45: 2026-07 | B45: 深圳星期零 | C45: 极鲜达 | D45: 成品仓储费用 | E45: — | G45: 月结 | I45: 16670 | J45: =IFERROR(INDEX(供应商列表!$F$4:$R$25,MATCH(C45,供应商列表!$A$4:$A$25,0),MATCH(D45,供应商列表!$F$3:$R$3,0)),"") | K45: =IFERROR(ROUND(I45/(1+J45),2),"") | L45: =IFERROR(I45-K45,"") | M45: =IFERROR(INDEX(供应商列表!$B$4:$B$25,MATCH(C45,供应商列表!$A$4:$A$25,0)),"") | N45: ="计提"&M45&(MID(A45,6,2)*1)&"月"&IFERROR(INDEX(供应商列表!$E$4:$E$25,MATCH(C45,供应商列表!$A$4:$A$25,0)),"线下")&IF(F45<>"",F45,IF(OR(E45="—",E45=""),"",E45))&IFERROR(INDEX('费用归属表（快照）'!$F$4:$F$16,MATCH(D45,'费用归属表（快照）'!$A$4:$A$16,0)),"") | Q45: =IF(P45="","",P45-I45) | T45: =IF(D45="","",IFERROR(INDEX('费用归属表（快照）'!$C$4:$C$16,MATCH(D45,'费用归属表（快照）'!$A$4:$A$16,0)),"")) | U45: =IF(D45="","",IF(AND(D45="销售出库费用",B45="深圳星期九"),"永续供应中心 0010401",IF(AND(D45="原料入库费用",E45="小料"),"茶饮小料部 0030902",IFERROR(INDEX('费用归属表（快照）'!$D$4:$D$16,MATCH(D45,'费用归属表（快照）'!$A$4:$A$16,0)),"")))) | V45: =IF(D45="","",IFERROR(INDEX('费用归属表（快照）'!$B$4:$B$16,MATCH(D45,'费用归属表（快照）'!$A$4:$A$16,0)),"")) | W45: =IF(OR(E45="",AND(LEFT(T45,4)<>"6601",LEFT(T45,4)<>"6401")),"",IFERROR(IF(INDEX(选项!$I$2:$I$11,MATCH(E45,选项!$H$2:$H$11,0))="","",INDEX(选项!$I$2:$I$11,MATCH(E45,选项!$H$2:$H$11,0))),"")) | X45: =IF(OR(E45="",AND(LEFT(T45,4)<>"6601",LEFT(T45,4)<>"6401")),"",IFERROR(IF(INDEX(选项!$J$2:$J$11,MATCH(E45,选项!$H$2:$H$11,0))="","",INDEX(选项!$J$2:$J$11,MATCH(E45,选项!$H$2:$H$11,0))),""))
A46: 2026-07 | B46: 深圳星期零 | C46: 极鲜达 | D46: 销售出库费用 | E46: 小料 | G46: 月结 | I46: 1933.55 | J46: =IFERROR(INDEX(供应商列表!$F$4:$R$25,MATCH(C46,供应商列表!$A$4:$A$25,0),MATCH(D46,供应商列表!$F$3:$R$3,0)),"") | K46: =IFERROR(ROUND(I46/(1+J46),2),"") | L46: =IFERROR(I46-K46,"") | M46: =IFERROR(INDEX(供应商列表!$B$4:$B$25,MATCH(C46,供应商列表!$A$4:$A$25,0)),"") | N46: ="计提"&M46&(MID(A46,6,2)*1)&"月"&IFERROR(INDEX(供应商列表!$E$4:$E$25,MATCH(C46,供应商列表!$A$4:$A$25,0)),"线下")&IF(F46<>"",F46,IF(OR(E46="—",E46=""),"",E46))&IFERROR(INDEX('费用归属表（快照）'!$F$4:$F$16,MATCH(D46,'费用归属表（快照）'!$A$4:$A$16,0)),"") | Q46: =IF(P46="","",P46-I46) | T46: =IF(D46="","",IFERROR(INDEX('费用归属表（快照）'!$C$4:$C$16,MATCH(D46,'费用归属表（快照）'!$A$4:$A$16,0)),"")) | U46: =IF(D46="","",IF(AND(D46="销售出库费用",B46="深圳星期九"),"永续供应中心 0010401",IF(AND(D46="原料入库费用",E46="小料"),"茶饮小料部 0030902",IFERROR(INDEX('费用归属表（快照）'!$D$4:$D$16,MATCH(D46,'费用归属表（快照）'!$A$4:$A$16,0)),"")))) | V46: =IF(D46="","",IFERROR(INDEX('费用归属表（快照）'!$B$4:$B$16,MATCH(D46,'费用归属表（快照）'!$A$4:$A$16,0)),"")) | W46: =IF(OR(E46="",AND(LEFT(T46,4)<>"6601",LEFT(T46,4)<>"6401")),"",IFERROR(IF(INDEX(选项!$I$2:$I$11,MATCH(E46,选项!$H$2:$H$11,0))="","",INDEX(选项!$I$2:$I$11,MATCH(E46,选项!$H$2:$H$11,0))),"")) | X46: =IF(OR(E46="",AND(LEFT(T46,4)<>"6601",LEFT(T46,4)<>"6401")),"",IFERROR(IF(INDEX(选项!$J$2:$J$11,MATCH(E46,选项!$H$2:$H$11,0))="","",INDEX(选项!$J$2:$J$11,MATCH(E46,选项!$H$2:$H$11,0))),""))
A47: 2026-07 | B47: 深圳星期零 | C47: 丰源 | D47: 销售出库费用 | E47: 零售 | G47: 月结 | I47: 1826.74 | J47: =IFERROR(INDEX(供应商列表!$F$4:$R$25,MATCH(C47,供应商列表!$A$4:$A$25,0),MATCH(D47,供应商列表!$F$3:$R$3,0)),"") | K47: =IFERROR(ROUND(I47/(1+J47),2),"") | L47: =IFERROR(I47-K47,"") | M47: =IFERROR(INDEX(供应商列表!$B$4:$B$25,MATCH(C47,供应商列表!$A$4:$A$25,0)),"") | N47: ="计提"&M47&(MID(A47,6,2)*1)&"月"&IFERROR(INDEX(供应商列表!$E$4:$E$25,MATCH(C47,供应商列表!$A$4:$A$25,0)),"线下")&IF(F47<>"",F47,IF(OR(E47="—",E47=""),"",E47))&IFERROR(INDEX('费用归属表（快照）'!$F$4:$F$16,MATCH(D47,'费用归属表（快照）'!$A$4:$A$16,0)),"") | Q47: =IF(P47="","",P47-I47) | T47: =IF(D47="","",IFERROR(INDEX('费用归属表（快照）'!$C$4:$C$16,MATCH(D47,'费用归属表（快照）'!$A$4:$A$16,0)),"")) | U47: =IF(D47="","",IF(AND(D47="销售出库费用",B47="深圳星期九"),"永续供应中心 0010401",IF(AND(D47="原料入库费用",E47="小料"),"茶饮小料部 0030902",IFERROR(INDEX('费用归属表（快照）'!$D$4:$D$16,MATCH(D47,'费用归属表（快照）'!$A$4:$A$16,0)),"")))) | V47: =IF(D47="","",IFERROR(INDEX('费用归属表（快照）'!$B$4:$B$16,MATCH(D47,'费用归属表（快照）'!$A$4:$A$16,0)),"")) | W47: =IF(OR(E47="",AND(LEFT(T47,4)<>"6601",LEFT(T47,4)<>"6401")),"",IFERROR(IF(INDEX(选项!$I$2:$I$11,MATCH(E47,选项!$H$2:$H$11,0))="","",INDEX(选项!$I$2:$I$11,MATCH(E47,选项!$H$2:$H$11,0))),"")) | X47: =IF(OR(E47="",AND(LEFT(T47,4)<>"6601",LEFT(T47,4)<>"6401")),"",IFERROR(IF(INDEX(选项!$J$2:$J$11,MATCH(E47,选项!$H$2:$H$11,0))="","",INDEX(选项!$J$2:$J$11,MATCH(E47,选项!$H$2:$H$11,0))),""))
A48: 2026-07 | B48: 深圳星期零 | C48: 丰源 | D48: 原料入库费用 | E48: 小料 | F48: 小料 | G48: 月结 | I48: 100 | J48: =IFERROR(INDEX(供应商列表!$F$4:$R$25,MATCH(C48,供应商列表!$A$4:$A$25,0),MATCH(D48,供应商列表!$F$3:$R$3,0)),"") | K48: =IFERROR(ROUND(I48/(1+J48),2),"") | L48: =IFERROR(I48-K48,"") | M48: =IFERROR(INDEX(供应商列表!$B$4:$B$25,MATCH(C48,供应商列表!$A$4:$A$25,0)),"") | N48: ="计提"&M48&(MID(A48,6,2)*1)&"月"&IFERROR(INDEX(供应商列表!$E$4:$E$25,MATCH(C48,供应商列表!$A$4:$A$25,0)),"线下")&IF(F48<>"",F48,IF(OR(E48="—",E48=""),"",E48))&IFERROR(INDEX('费用归属表（快照）'!$F$4:$F$16,MATCH(D48,'费用归属表（快照）'!$A$4:$A$16,0)),"") | Q48: =IF(P48="","",P48-I48) | T48: =IF(D48="","",IFERROR(INDEX('费用归属表（快照）'!$C$4:$C$16,MATCH(D48,'费用归属表（快照）'!$A$4:$A$16,0)),"")) | U48: =IF(D48="","",IF(AND(D48="销售出库费用",B48="深圳星期九"),"永续供应中心 0010401",IF(AND(D48="原料入库费用",E48="小料"),"茶饮小料部 0030902",IFERROR(INDEX('费用归属表（快照）'!$D$4:$D$16,MATCH(D48,'费用归属表（快照）'!$A$4:$A$16,0)),"")))) | V48: =IF(D48="","",IFERROR(INDEX('费用归属表（快照）'!$B$4:$B$16,MATCH(D48,'费用归属表（快照）'!$A$4:$A$16,0)),"")) | W48: =IF(OR(E48="",AND(LEFT(T48,4)<>"6601",LEFT(T48,4)<>"6401")),"",IFERROR(IF(INDEX(选项!$I$2:$I$11,MATCH(E48,选项!$H$2:$H$11,0))="","",INDEX(选项!$I$2:$I$11,MATCH(E48,选项!$H$2:$H$11,0))),"")) | X48: =IF(OR(E48="",AND(LEFT(T48,4)<>"6601",LEFT(T48,4)<>"6401")),"",IFERROR(IF(INDEX(选项!$J$2:$J$11,MATCH(E48,选项!$H$2:$H$11,0))="","",INDEX(选项!$J$2:$J$11,MATCH(E48,选项!$H$2:$H$11,0))),""))
A49: 2026-07 | B49: 深圳星期零 | C49: 天鹰物流 | D49: 销售出库费用 | E49: 植物肉 | G49: 月结 | I49: 277.87 | J49: =IFERROR(INDEX(供应商列表!$F$4:$R$25,MATCH(C49,供应商列表!$A$4:$A$25,0),MATCH(D49,供应商列表!$F$3:$R$3,0)),"") | K49: =IFERROR(ROUND(I49/(1+J49),2),"") | L49: =IFERROR(I49-K49,"") | M49: =IFERROR(INDEX(供应商列表!$B$4:$B$25,MATCH(C49,供应商列表!$A$4:$A$25,0)),"") | N49: ="计提"&M49&(MID(A49,6,2)*1)&"月"&IFERROR(INDEX(供应商列表!$E$4:$E$25,MATCH(C49,供应商列表!$A$4:$A$25,0)),"线下")&IF(F49<>"",F49,IF(OR(E49="—",E49=""),"",E49))&IFERROR(INDEX('费用归属表（快照）'!$F$4:$F$16,MATCH(D49,'费用归属表（快照）'!$A$4:$A$16,0)),"") | Q49: =IF(P49="","",P49-I49) | T49: =IF(D49="","",IFERROR(INDEX('费用归属表（快照）'!$C$4:$C$16,MATCH(D49,'费用归属表（快照）'!$A$4:$A$16,0)),"")) | U49: =IF(D49="","",IF(AND(D49="销售出库费用",B49="深圳星期九"),"永续供应中心 0010401",IF(AND(D49="原料入库费用",E49="小料"),"茶饮小料部 0030902",IFERROR(INDEX('费用归属表（快照）'!$D$4:$D$16,MATCH(D49,'费用归属表（快照）'!$A$4:$A$16,0)),"")))) | V49: =IF(D49="","",IFERROR(INDEX('费用归属表（快照）'!$B$4:$B$16,MATCH(D49,'费用归属表（快照）'!$A$4:$A$16,0)),"")) | W49: =IF(OR(E49="",AND(LEFT(T49,4)<>"6601",LEFT(T49,4)<>"6401")),"",IFERROR(IF(INDEX(选项!$I$2:$I$11,MATCH(E49,选项!$H$2:$H$11,0))="","",INDEX(选项!$I$2:$I$11,MATCH(E49,选项!$H$2:$H$11,0))),"")) | X49: =IF(OR(E49="",AND(LEFT(T49,4)<>"6601",LEFT(T49,4)<>"6401")),"",IFERROR(IF(INDEX(选项!$J$2:$J$11,MATCH(E49,选项!$H$2:$H$11,0))="","",INDEX(选项!$J$2:$J$11,MATCH(E49,选项!$H$2:$H$11,0))),""))
A50: 2026-07 | B50: 深圳星期零 | C50: 天鹰物流 | D50: 销售出库费用 | E50: 山姆零售 | G50: 月结 | I50: 167.43 | J50: =IFERROR(INDEX(供应商列表!$F$4:$R$25,MATCH(C50,供应商列表!$A$4:$A$25,0),MATCH(D50,供应商列表!$F$3:$R$3,0)),"") | K50: =IFERROR(ROUND(I50/(1+J50),2),"") | L50: =IFERROR(I50-K50,"") | M50: =IFERROR(INDEX(供应商列表!$B$4:$B$25,MATCH(C50,供应商列表!$A$4:$A$25,0)),"") | N50: ="计提"&M50&(MID(A50,6,2)*1)&"月"&IFERROR(INDEX(供应商列表!$E$4:$E$25,MATCH(C50,供应商列表!$A$4:$A$25,0)),"线下")&IF(F50<>"",F50,IF(OR(E50="—",E50=""),"",E50))&IFERROR(INDEX('费用归属表（快照）'!$F$4:$F$16,MATCH(D50,'费用归属表（快照）'!$A$4:$A$16,0)),"") | Q50: =IF(P50="","",P50-I50) | T50: =IF(D50="","",IFERROR(INDEX('费用归属表（快照）'!$C$4:$C$16,MATCH(D50,'费用归属表（快照）'!$A$4:$A$16,0)),"")) | U50: =IF(D50="","",IF(AND(D50="销售出库费用",B50="深圳星期九"),"永续供应中心 0010401",IF(AND(D50="原料入库费用",E50="小料"),"茶饮小料部 0030902",IFERROR(INDEX('费用归属表（快照）'!$D$4:$D$16,MATCH(D50,'费用归属表（快照）'!$A$4:$A$16,0)),"")))) | V50: =IF(D50="","",IFERROR(INDEX('费用归属表（快照）'!$B$4:$B$16,MATCH(D50,'费用归属表（快照）'!$A$4:$A$16,0)),"")) | W50: =IF(OR(E50="",AND(LEFT(T50,4)<>"6601",LEFT(T50,4)<>"6401")),"",IFERROR(IF(INDEX(选项!$I$2:$I$11,MATCH(E50,选项!$H$2:$H$11,0))="","",INDEX(选项!$I$2:$I$11,MATCH(E50,选项!$H$2:$H$11,0))),"")) | X50: =IF(OR(E50="",AND(LEFT(T50,4)<>"6601",LEFT(T50,4)<>"6401")),"",IFERROR(IF(INDEX(选项!$J$2:$J$11,MATCH(E50,选项!$H$2:$H$11,0))="","",INDEX(选项!$J$2:$J$11,MATCH(E50,选项!$H$2:$H$11,0))),""))
A51: 2026-07 | B51: 深圳星期零 | C51: 天鹰物流 | D51: 销售出库费用 | E51: 豆蛋制品 | G51: 月结 | I51: 234.21 | J51: =IFERROR(INDEX(供应商列表!$F$4:$R$25,MATCH(C51,供应商列表!$A$4:$A$25,0),MATCH(D51,供应商列表!$F$3:$R$3,0)),"") | K51: =IFERROR(ROUND(I51/(1+J51),2),"") | L51: =IFERROR(I51-K51,"") | M51: =IFERROR(INDEX(供应商列表!$B$4:$B$25,MATCH(C51,供应商列表!$A$4:$A$25,0)),"") | N51: ="计提"&M51&(MID(A51,6,2)*1)&"月"&IFERROR(INDEX(供应商列表!$E$4:$E$25,MATCH(C51,供应商列表!$A$4:$A$25,0)),"线下")&IF(F51<>"",F51,IF(OR(E51="—",E51=""),"",E51))&IFERROR(INDEX('费用归属表（快照）'!$F$4:$F$16,MATCH(D51,'费用归属表（快照）'!$A$4:$A$16,0)),"") | Q51: =IF(P51="","",P51-I51) | T51: =IF(D51="","",IFERROR(INDEX('费用归属表（快照）'!$C$4:$C$16,MATCH(D51,'费用归属表（快照）'!$A$4:$A$16,0)),"")) | U51: =IF(D51="","",IF(AND(D51="销售出库费用",B51="深圳星期九"),"永续供应中心 0010401",IF(AND(D51="原料入库费用",E51="小料"),"茶饮小料部 0030902",IFERROR(INDEX('费用归属表（快照）'!$D$4:$D$16,MATCH(D51,'费用归属表（快照）'!$A$4:$A$16,0)),"")))) | V51: =IF(D51="","",IFERROR(INDEX('费用归属表（快照）'!$B$4:$B$16,MATCH(D51,'费用归属表（快照）'!$A$4:$A$16,0)),"")) | W51: =IF(OR(E51="",AND(LEFT(T51,4)<>"6601",LEFT(T51,4)<>"6401")),"",IFERROR(IF(INDEX(选项!$I$2:$I$11,MATCH(E51,选项!$H$2:$H$11,0))="","",INDEX(选项!$I$2:$I$11,MATCH(E51,选项!$H$2:$H$11,0))),"")) | X51: =IF(OR(E51="",AND(LEFT(T51,4)<>"6601",LEFT(T51,4)<>"6401")),"",IFERROR(IF(INDEX(选项!$J$2:$J$11,MATCH(E51,选项!$H$2:$H$11,0))="","",INDEX(选项!$J$2:$J$11,MATCH(E51,选项!$H$2:$H$11,0))),""))
A52: 2026-07 | B52: 深圳星期零 | C52: 天鹰物流 | D52: 销售出库费用 | E52: 零售 | G52: 月结 | I52: 89.91 | J52: =IFERROR(INDEX(供应商列表!$F$4:$R$25,MATCH(C52,供应商列表!$A$4:$A$25,0),MATCH(D52,供应商列表!$F$3:$R$3,0)),"") | K52: =IFERROR(ROUND(I52/(1+J52),2),"") | L52: =IFERROR(I52-K52,"") | M52: =IFERROR(INDEX(供应商列表!$B$4:$B$25,MATCH(C52,供应商列表!$A$4:$A$25,0)),"") | N52: ="计提"&M52&(MID(A52,6,2)*1)&"月"&IFERROR(INDEX(供应商列表!$E$4:$E$25,MATCH(C52,供应商列表!$A$4:$A$25,0)),"线下")&IF(F52<>"",F52,IF(OR(E52="—",E52=""),"",E52))&IFERROR(INDEX('费用归属表（快照）'!$F$4:$F$16,MATCH(D52,'费用归属表（快照）'!$A$4:$A$16,0)),"") | Q52: =IF(P52="","",P52-I52) | T52: =IF(D52="","",IFERROR(INDEX('费用归属表（快照）'!$C$4:$C$16,MATCH(D52,'费用归属表（快照）'!$A$4:$A$16,0)),"")) | U52: =IF(D52="","",IF(AND(D52="销售出库费用",B52="深圳星期九"),"永续供应中心 0010401",IF(AND(D52="原料入库费用",E52="小料"),"茶饮小料部 0030902",IFERROR(INDEX('费用归属表（快照）'!$D$4:$D$16,MATCH(D52,'费用归属表（快照）'!$A$4:$A$16,0)),"")))) | V52: =IF(D52="","",IFERROR(INDEX('费用归属表（快照）'!$B$4:$B$16,MATCH(D52,'费用归属表（快照）'!$A$4:$A$16,0)),"")) | W52: =IF(OR(E52="",AND(LEFT(T52,4)<>"6601",LEFT(T52,4)<>"6401")),"",IFERROR(IF(INDEX(选项!$I$2:$I$11,MATCH(E52,选项!$H$2:$H$11,0))="","",INDEX(选项!$I$2:$I$11,MATCH(E52,选项!$H$2:$H$11,0))),"")) | X52: =IF(OR(E52="",AND(LEFT(T52,4)<>"6601",LEFT(T52,4)<>"6401")),"",IFERROR(IF(INDEX(选项!$J$2:$J$11,MATCH(E52,选项!$H$2:$H$11,0))="","",INDEX(选项!$J$2:$J$11,MATCH(E52,选项!$H$2:$H$11,0))),""))
A53: 2026-07 | B53: 深圳星期零 | C53: 天鹰物流 | D53: 原料入库费用 | E53: — | F53: 孝感工厂 | G53: 月结 | I53: 585.04 | J53: =IFERROR(INDEX(供应商列表!$F$4:$R$25,MATCH(C53,供应商列表!$A$4:$A$25,0),MATCH(D53,供应商列表!$F$3:$R$3,0)),"") | K53: =IFERROR(ROUND(I53/(1+J53),2),"") | L53: =IFERROR(I53-K53,"") | M53: =IFERROR(INDEX(供应商列表!$B$4:$B$25,MATCH(C53,供应商列表!$A$4:$A$25,0)),"") | N53: ="计提"&M53&(MID(A53,6,2)*1)&"月"&IFERROR(INDEX(供应商列表!$E$4:$E$25,MATCH(C53,供应商列表!$A$4:$A$25,0)),"线下")&IF(F53<>"",F53,IF(OR(E53="—",E53=""),"",E53))&IFERROR(INDEX('费用归属表（快照）'!$F$4:$F$16,MATCH(D53,'费用归属表（快照）'!$A$4:$A$16,0)),"") | Q53: =IF(P53="","",P53-I53) | T53: =IF(D53="","",IFERROR(INDEX('费用归属表（快照）'!$C$4:$C$16,MATCH(D53,'费用归属表（快照）'!$A$4:$A$16,0)),"")) | U53: =IF(D53="","",IF(AND(D53="销售出库费用",B53="深圳星期九"),"永续供应中心 0010401",IF(AND(D53="原料入库费用",E53="小料"),"茶饮小料部 0030902",IFERROR(INDEX('费用归属表（快照）'!$D$4:$D$16,MATCH(D53,'费用归属表（快照）'!$A$4:$A$16,0)),"")))) | V53: =IF(D53="","",IFERROR(INDEX('费用归属表（快照）'!$B$4:$B$16,MATCH(D53,'费用归属表（快照）'!$A$4:$A$16,0)),"")) | W53: =IF(OR(E53="",AND(LEFT(T53,4)<>"6601",LEFT(T53,4)<>"6401")),"",IFERROR(IF(INDEX(选项!$I$2:$I$11,MATCH(E53,选项!$H$2:$H$11,0))="","",INDEX(选项!$I$2:$I$11,MATCH(E53,选项!$H$2:$H$11,0))),"")) | X53: =IF(OR(E53="",AND(LEFT(T53,4)<>"6601",LEFT(T53,4)<>"6401")),"",IFERROR(IF(INDEX(选项!$J$2:$J$11,MATCH(E53,选项!$H$2:$H$11,0))="","",INDEX(选项!$J$2:$J$11,MATCH(E53,选项!$H$2:$H$11,0))),""))
A54: 2026-07 | B54: 深圳星期零 | C54: 天鹰物流 | D54: 原料入库费用 | E54: 小料 | F54: 小料 | G54: 月结 | I54: 6108.46 | J54: =IFERROR(INDEX(供应商列表!$F$4:$R$25,MATCH(C54,供应商列表!$A$4:$A$25,0),MATCH(D54,供应商列表!$F$3:$R$3,0)),"") | K54: =IFERROR(ROUND(I54/(1+J54),2),"") | L54: =IFERROR(I54-K54,"") | M54: =IFERROR(INDEX(供应商列表!$B$4:$B$25,MATCH(C54,供应商列表!$A$4:$A$25,0)),"") | N54: ="计提"&M54&(MID(A54,6,2)*1)&"月"&IFERROR(INDEX(供应商列表!$E$4:$E$25,MATCH(C54,供应商列表!$A$4:$A$25,0)),"线下")&IF(F54<>"",F54,IF(OR(E54="—",E54=""),"",E54))&IFERROR(INDEX('费用归属表（快照）'!$F$4:$F$16,MATCH(D54,'费用归属表（快照）'!$A$4:$A$16,0)),"") | Q54: =IF(P54="","",P54-I54) | T54: =IF(D54="","",IFERROR(INDEX('费用归属表（快照）'!$C$4:$C$16,MATCH(D54,'费用归属表（快照）'!$A$4:$A$16,0)),"")) | U54: =IF(D54="","",IF(AND(D54="销售出库费用",B54="深圳星期九"),"永续供应中心 0010401",IF(AND(D54="原料入库费用",E54="小料"),"茶饮小料部 0030902",IFERROR(INDEX('费用归属表（快照）'!$D$4:$D$16,MATCH(D54,'费用归属表（快照）'!$A$4:$A$16,0)),"")))) | V54: =IF(D54="","",IFERROR(INDEX('费用归属表（快照）'!$B$4:$B$16,MATCH(D54,'费用归属表（快照）'!$A$4:$A$16,0)),"")) | W54: =IF(OR(E54="",AND(LEFT(T54,4)<>"6601",LEFT(T54,4)<>"6401")),"",IFERROR(IF(INDEX(选项!$I$2:$I$11,MATCH(E54,选项!$H$2:$H$11,0))="","",INDEX(选项!$I$2:$I$11,MATCH(E54,选项!$H$2:$H$11,0))),"")) | X54: =IF(OR(E54="",AND(LEFT(T54,4)<>"6601",LEFT(T54,4)<>"6401")),"",IFERROR(IF(INDEX(选项!$J$2:$J$11,MATCH(E54,选项!$H$2:$H$11,0))="","",INDEX(选项!$J$2:$J$11,MATCH(E54,选项!$H$2:$H$11,0))),""))
A55: 2026-07 | B55: 深圳星期零 | C55: 天鹰物流 | D55: 销售出库费用 | E55: 小料 | G55: 月结 | I55: 5653.97 | J55: =IFERROR(INDEX(供应商列表!$F$4:$R$25,MATCH(C55,供应商列表!$A$4:$A$25,0),MATCH(D55,供应商列表!$F$3:$R$3,0)),"") | K55: =IFERROR(ROUND(I55/(1+J55),2),"") | L55: =IFERROR(I55-K55,"") | M55: =IFERROR(INDEX(供应商列表!$B$4:$B$25,MATCH(C55,供应商列表!$A$4:$A$25,0)),"") | N55: ="计提"&M55&(MID(A55,6,2)*1)&"月"&IFERROR(INDEX(供应商列表!$E$4:$E$25,MATCH(C55,供应商列表!$A$4:$A$25,0)),"线下")&IF(F55<>"",F55,IF(OR(E55="—",E55=""),"",E55))&IFERROR(INDEX('费用归属表（快照）'!$F$4:$F$16,MATCH(D55,'费用归属表（快照）'!$A$4:$A$16,0)),"") | Q55: =IF(P55="","",P55-I55) | T55: =IF(D55="","",IFERROR(INDEX('费用归属表（快照）'!$C$4:$C$16,MATCH(D55,'费用归属表（快照）'!$A$4:$A$16,0)),"")) | U55: =IF(D55="","",IF(AND(D55="销售出库费用",B55="深圳星期九"),"永续供应中心 0010401",IF(AND(D55="原料入库费用",E55="小料"),"茶饮小料部 0030902",IFERROR(INDEX('费用归属表（快照）'!$D$4:$D$16,MATCH(D55,'费用归属表（快照）'!$A$4:$A$16,0)),"")))) | V55: =IF(D55="","",IFERROR(INDEX('费用归属表（快照）'!$B$4:$B$16,MATCH(D55,'费用归属表（快照）'!$A$4:$A$16,0)),"")) | W55: =IF(OR(E55="",AND(LEFT(T55,4)<>"6601",LEFT(T55,4)<>"6401")),"",IFERROR(IF(INDEX(选项!$I$2:$I$11,MATCH(E55,选项!$H$2:$H$11,0))="","",INDEX(选项!$I$2:$I$11,MATCH(E55,选项!$H$2:$H$11,0))),"")) | X55: =IF(OR(E55="",AND(LEFT(T55,4)<>"6601",LEFT(T55,4)<>"6401")),"",IFERROR(IF(INDEX(选项!$J$2:$J$11,MATCH(E55,选项!$H$2:$H$11,0))="","",INDEX(选项!$J$2:$J$11,MATCH(E55,选项!$H$2:$H$11,0))),""))
A56: 2026-07 | B56: 深圳星期零 | C56: 顺鸽电商仓 | D56: 成品入库费用 | E56: 鲜食 | F56: 鲜食 | G56: 月结 | I56: 901 | J56: =IFERROR(INDEX(供应商列表!$F$4:$R$25,MATCH(C56,供应商列表!$A$4:$A$25,0),MATCH(D56,供应商列表!$F$3:$R$3,0)),"") | K56: =IFERROR(ROUND(I56/(1+J56),2),"") | L56: =IFERROR(I56-K56,"") | M56: =IFERROR(INDEX(供应商列表!$B$4:$B$25,MATCH(C56,供应商列表!$A$4:$A$25,0)),"") | N56: ="计提"&M56&(MID(A56,6,2)*1)&"月"&IFERROR(INDEX(供应商列表!$E$4:$E$25,MATCH(C56,供应商列表!$A$4:$A$25,0)),"线下")&IF(F56<>"",F56,IF(OR(E56="—",E56=""),"",E56))&IFERROR(INDEX('费用归属表（快照）'!$F$4:$F$16,MATCH(D56,'费用归属表（快照）'!$A$4:$A$16,0)),"") | Q56: =IF(P56="","",P56-I56) | T56: =IF(D56="","",IFERROR(INDEX('费用归属表（快照）'!$C$4:$C$16,MATCH(D56,'费用归属表（快照）'!$A$4:$A$16,0)),"")) | U56: =IF(D56="","",IF(AND(D56="销售出库费用",B56="深圳星期九"),"永续供应中心 0010401",IF(AND(D56="原料入库费用",E56="小料"),"茶饮小料部 0030902",IFERROR(INDEX('费用归属表（快照）'!$D$4:$D$16,MATCH(D56,'费用归属表（快照）'!$A$4:$A$16,0)),"")))) | V56: =IF(D56="","",IFERROR(INDEX('费用归属表（快照）'!$B$4:$B$16,MATCH(D56,'费用归属表（快照）'!$A$4:$A$16,0)),"")) | W56: =IF(OR(E56="",AND(LEFT(T56,4)<>"6601",LEFT(T56,4)<>"6401")),"",IFERROR(IF(INDEX(选项!$I$2:$I$11,MATCH(E56,选项!$H$2:$H$11,0))="","",INDEX(选项!$I$2:$I$11,MATCH(E56,选项!$H$2:$H$11,0))),"")) | X56: =IF(OR(E56="",AND(LEFT(T56,4)<>"6601",LEFT(T56,4)<>"6401")),"",IFERROR(IF(INDEX(选项!$J$2:$J$11,MATCH(E56,选项!$H$2:$H$11,0))="","",INDEX(选项!$J$2:$J$11,MATCH(E56,选项!$H$2:$H$11,0))),""))
A57: 2026-07 | B57: 深圳星期零 | C57: 大润发 | D57: 销售出库费用 | E57: 零售 | G57: 月结 | I57: 53.56 | J57: =IFERROR(INDEX(供应商列表!$F$4:$R$25,MATCH(C57,供应商列表!$A$4:$A$25,0),MATCH(D57,供应商列表!$F$3:$R$3,0)),"") | K57: =IFERROR(ROUND(I57/(1+J57),2),"") | L57: =IFERROR(I57-K57,"") | M57: =IFERROR(INDEX(供应商列表!$B$4:$B$25,MATCH(C57,供应商列表!$A$4:$A$25,0)),"") | N57: ="计提"&M57&(MID(A57,6,2)*1)&"月"&IFERROR(INDEX(供应商列表!$E$4:$E$25,MATCH(C57,供应商列表!$A$4:$A$25,0)),"线下")&IF(F57<>"",F57,IF(OR(E57="—",E57=""),"",E57))&IFERROR(INDEX('费用归属表（快照）'!$F$4:$F$16,MATCH(D57,'费用归属表（快照）'!$A$4:$A$16,0)),"") | Q57: =IF(P57="","",P57-I57) | T57: =IF(D57="","",IFERROR(INDEX('费用归属表（快照）'!$C$4:$C$16,MATCH(D57,'费用归属表（快照）'!$A$4:$A$16,0)),"")) | U57: =IF(D57="","",IF(AND(D57="销售出库费用",B57="深圳星期九"),"永续供应中心 0010401",IF(AND(D57="原料入库费用",E57="小料"),"茶饮小料部 0030902",IFERROR(INDEX('费用归属表（快照）'!$D$4:$D$16,MATCH(D57,'费用归属表（快照）'!$A$4:$A$16,0)),"")))) | V57: =IF(D57="","",IFERROR(INDEX('费用归属表（快照）'!$B$4:$B$16,MATCH(D57,'费用归属表（快照）'!$A$4:$A$16,0)),"")) | W57: =IF(OR(E57="",AND(LEFT(T57,4)<>"6601",LEFT(T57,4)<>"6401")),"",IFERROR(IF(INDEX(选项!$I$2:$I$11,MATCH(E57,选项!$H$2:$H$11,0))="","",INDEX(选项!$I$2:$I$11,MATCH(E57,选项!$H$2:$H$11,0))),"")) | X57: =IF(OR(E57="",AND(LEFT(T57,4)<>"6601",LEFT(T57,4)<>"6401")),"",IFERROR(IF(INDEX(选项!$J$2:$J$11,MATCH(E57,选项!$H$2:$H$11,0))="","",INDEX(选项!$J$2:$J$11,MATCH(E57,选项!$H$2:$H$11,0))),""))
A58: 2026-07 | B58: 深圳星期零 | C58: 货拉拉 | D58: 销售出库费用 | E58: — | F58: 样品 | G58: 非月结 | H58: 张三 | I58: 860 | J58: =IFERROR(INDEX(供应商列表!$F$4:$R$25,MATCH(C58,供应商列表!$A$4:$A$25,0),MATCH(D58,供应商列表!$F$3:$R$3,0)),"") | K58: =IFERROR(ROUND(I58/(1+J58),2),"") | L58: =IFERROR(I58-K58,"") | M58: =IFERROR(INDEX(供应商列表!$B$4:$B$25,MATCH(C58,供应商列表!$A$4:$A$25,0)),"") | N58: ="计提"&M58&(MID(A58,6,2)*1)&"月"&IFERROR(INDEX(供应商列表!$E$4:$E$25,MATCH(C58,供应商列表!$A$4:$A$25,0)),"线下")&IF(F58<>"",F58,IF(OR(E58="—",E58=""),"",E58))&IFERROR(INDEX('费用归属表（快照）'!$F$4:$F$16,MATCH(D58,'费用归属表（快照）'!$A$4:$A$16,0)),"") | Q58: =IF(P58="","",P58-I58) | T58: =IF(D58="","",IFERROR(INDEX('费用归属表（快照）'!$C$4:$C$16,MATCH(D58,'费用归属表（快照）'!$A$4:$A$16,0)),"")) | U58: =IF(D58="","",IF(AND(D58="销售出库费用",B58="深圳星期九"),"永续供应中心 0010401",IF(AND(D58="原料入库费用",E58="小料"),"茶饮小料部 0030902",IFERROR(INDEX('费用归属表（快照）'!$D$4:$D$16,MATCH(D58,'费用归属表（快照）'!$A$4:$A$16,0)),"")))) | V58: =IF(D58="","",IFERROR(INDEX('费用归属表（快照）'!$B$4:$B$16,MATCH(D58,'费用归属表（快照）'!$A$4:$A$16,0)),"")) | W58: =IF(OR(E58="",AND(LEFT(T58,4)<>"6601",LEFT(T58,4)<>"6401")),"",IFERROR(IF(INDEX(选项!$I$2:$I$11,MATCH(E58,选项!$H$2:$H$11,0))="","",INDEX(选项!$I$2:$I$11,MATCH(E58,选项!$H$2:$H$11,0))),"")) | X58: =IF(OR(E58="",AND(LEFT(T58,4)<>"6601",LEFT(T58,4)<>"6401")),"",IFERROR(IF(INDEX(选项!$J$2:$J$11,MATCH(E58,选项!$H$2:$H$11,0))="","",INDEX(选项!$J$2:$J$11,MATCH(E58,选项!$H$2:$H$11,0))),""))
A59: 2026-07 | B59: 深圳星期零 | C59: 货拉拉 | D59: 成品调拨费用 | E59: 电商 | G59: 非月结 | H59: 李四 | I59: 1240 | J59: =IFERROR(INDEX(供应商列表!$F$4:$R$25,MATCH(C59,供应商列表!$A$4:$A$25,0),MATCH(D59,供应商列表!$F$3:$R$3,0)),"") | K59: =IFERROR(ROUND(I59/(1+J59),2),"") | L59: =IFERROR(I59-K59,"") | M59: =IFERROR(INDEX(供应商列表!$B$4:$B$25,MATCH(C59,供应商列表!$A$4:$A$25,0)),"") | N59: ="计提"&M59&(MID(A59,6,2)*1)&"月"&IFERROR(INDEX(供应商列表!$E$4:$E$25,MATCH(C59,供应商列表!$A$4:$A$25,0)),"线下")&IF(F59<>"",F59,IF(OR(E59="—",E59=""),"",E59))&IFERROR(INDEX('费用归属表（快照）'!$F$4:$F$16,MATCH(D59,'费用归属表（快照）'!$A$4:$A$16,0)),"") | Q59: =IF(P59="","",P59-I59) | T59: =IF(D59="","",IFERROR(INDEX('费用归属表（快照）'!$C$4:$C$16,MATCH(D59,'费用归属表（快照）'!$A$4:$A$16,0)),"")) | U59: =IF(D59="","",IF(AND(D59="销售出库费用",B59="深圳星期九"),"永续供应中心 0010401",IF(AND(D59="原料入库费用",E59="小料"),"茶饮小料部 0030902",IFERROR(INDEX('费用归属表（快照）'!$D$4:$D$16,MATCH(D59,'费用归属表（快照）'!$A$4:$A$16,0)),"")))) | V59: =IF(D59="","",IFERROR(INDEX('费用归属表（快照）'!$B$4:$B$16,MATCH(D59,'费用归属表（快照）'!$A$4:$A$16,0)),"")) | W59: =IF(OR(E59="",AND(LEFT(T59,4)<>"6601",LEFT(T59,4)<>"6401")),"",IFERROR(IF(INDEX(选项!$I$2:$I$11,MATCH(E59,选项!$H$2:$H$11,0))="","",INDEX(选项!$I$2:$I$11,MATCH(E59,选项!$H$2:$H$11,0))),"")) | X59: =IF(OR(E59="",AND(LEFT(T59,4)<>"6601",LEFT(T59,4)<>"6401")),"",IFERROR(IF(INDEX(选项!$J$2:$J$11,MATCH(E59,选项!$H$2:$H$11,0))="","",INDEX(选项!$J$2:$J$11,MATCH(E59,选项!$H$2:$H$11,0))),""))
A60: 合计 | I60: =SUM(I4:I59) | K60: =SUM(K4:K59) | L60: =SUM(L4:L59) | P60: =SUM(P4:P59)

Sheet 做账去向表
A1: 做账去向表(本月费用准备做到哪个科目/哪个业务线/哪个部门——全公式自动,数据源=计提明细表维度列) 账期 2026-07
A2: 行=账证实证维度组合(2026 序时账 1229 行反推,共 27 种);金额=明细表按 主体×科目×部门×费用项目×产品分类×产品项目 六键汇总;新组合(人工改维度产生)落不进清单时,底部核对格≠0 提醒。
A3: 付款主体 | B3: 借方科目 | C3: 部门 | D3: 费用项目 | E3: 产品分类 | F3: 产品项目 | G3: 业务线(参考) | H3: 未税 | I3: 税额 | J3: 含税 | K3: 笔数 | L3: 账证月份
A4: 深圳星期零 | B4: 6601 销售费用 | C4: 永续物流中心 0011401 | D4: 出库运费 FYXM008.002其他物流费用002 | E4: CPFL007 | G4: 植物肉 | H4: =SUMIFS(计提明细表!$K$4:$K$59,计提明细表!$B$4:$B$59,$A4,计提明细表!$T$4:$T$59,$B4,计提明细表!$U$4:$U$59,$C4,计提明细表!$V$4:$V$59,$D4,计提明细表!$W$4:$W$59,$E4&"",计提明细表!$X$4:$X$59,$F4&"") | I4: =SUMIFS(计提明细表!$L$4:$L$59,计提明细表!$B$4:$B$59,$A4,计提明细表!$T$4:$T$59,$B4,计提明细表!$U$4:$U$59,$C4,计提明细表!$V$4:$V$59,$D4,计提明细表!$W$4:$W$59,$E4&"",计提明细表!$X$4:$X$59,$F4&"") | J4: =SUMIFS(计提明细表!$I$4:$I$59,计提明细表!$B$4:$B$59,$A4,计提明细表!$T$4:$T$59,$B4,计提明细表!$U$4:$U$59,$C4,计提明细表!$V$4:$V$59,$D4,计提明细表!$W$4:$W$59,$E4&"",计提明细表!$X$4:$X$59,$F4&"") | K4: =COUNTIFS(计提明细表!$B$4:$B$59,$A4,计提明细表!$T$4:$T$59,$B4,计提明细表!$U$4:$U$59,$C4,计提明细表!$V$4:$V$59,$D4,计提明细表!$W$4:$W$59,$E4&"",计提明细表!$X$4:$X$59,$F4&"") | L4: 1-6月
A5: 深圳星期零 | B5: 6601 销售费用 | C5: 永续物流中心 0011401 | D5: 出库运费 FYXM008.002其他物流费用002 | E5: CPFL010 | F5: CPXM017 | G5: 鲜食 | H5: =SUMIFS(计提明细表!$K$4:$K$59,计提明细表!$B$4:$B$59,$A5,计提明细表!$T$4:$T$59,$B5,计提明细表!$U$4:$U$59,$C5,计提明细表!$V$4:$V$59,$D5,计提明细表!$W$4:$W$59,$E5&"",计提明细表!$X$4:$X$59,$F5&"") | I5: =SUMIFS(计提明细表!$L$4:$L$59,计提明细表!$B$4:$B$59,$A5,计提明细表!$T$4:$T$59,$B5,计提明细表!$U$4:$U$59,$C5,计提明细表!$V$4:$V$59,$D5,计提明细表!$W$4:$W$59,$E5&"",计提明细表!$X$4:$X$59,$F5&"") | J5: =SUMIFS(计提明细表!$I$4:$I$59,计提明细表!$B$4:$B$59,$A5,计提明细表!$T$4:$T$59,$B5,计提明细表!$U$4:$U$59,$C5,计提明细表!$V$4:$V$59,$D5,计提明细表!$W$4:$W$59,$E5&"",计提明细表!$X$4:$X$59,$F5&"") | K5: =COUNTIFS(计提明细表!$B$4:$B$59,$A5,计提明细表!$T$4:$T$59,$B5,计提明细表!$U$4:$U$59,$C5,计提明细表!$V$4:$V$59,$D5,计提明细表!$W$4:$W$59,$E5&"",计提明细表!$X$4:$X$59,$F5&"") | L5: 1-6月
A6: 深圳星期零 | B6: 6601 销售费用 | C6: 永续物流中心 0011401 | D6: 出库运费 FYXM008.002其他物流费用002 | E6: CPFL011 | G6: 零售 | H6: =SUMIFS(计提明细表!$K$4:$K$59,计提明细表!$B$4:$B$59,$A6,计提明细表!$T$4:$T$59,$B6,计提明细表!$U$4:$U$59,$C6,计提明细表!$V$4:$V$59,$D6,计提明细表!$W$4:$W$59,$E6&"",计提明细表!$X$4:$X$59,$F6&"") | I6: =SUMIFS(计提明细表!$L$4:$L$59,计提明细表!$B$4:$B$59,$A6,计提明细表!$T$4:$T$59,$B6,计提明细表!$U$4:$U$59,$C6,计提明细表!$V$4:$V$59,$D6,计提明细表!$W$4:$W$59,$E6&"",计提明细表!$X$4:$X$59,$F6&"") | J6: =SUMIFS(计提明细表!$I$4:$I$59,计提明细表!$B$4:$B$59,$A6,计提明细表!$T$4:$T$59,$B6,计提明细表!$U$4:$U$59,$C6,计提明细表!$V$4:$V$59,$D6,计提明细表!$W$4:$W$59,$E6&"",计提明细表!$X$4:$X$59,$F6&"") | K6: =COUNTIFS(计提明细表!$B$4:$B$59,$A6,计提明细表!$T$4:$T$59,$B6,计提明细表!$U$4:$U$59,$C6,计提明细表!$V$4:$V$59,$D6,计提明细表!$W$4:$W$59,$E6&"",计提明细表!$X$4:$X$59,$F6&"") | L6: 1-6月
A7: 深圳星期零 | B7: 6601 销售费用 | C7: 永续物流中心 0011401 | D7: 出库运费 FYXM008.002其他物流费用002 | E7: CPFL011 | F7: CPXM017 | G7: 山姆零售 | H7: =SUMIFS(计提明细表!$K$4:$K$59,计提明细表!$B$4:$B$59,$A7,计提明细表!$T$4:$T$59,$B7,计提明细表!$U$4:$U$59,$C7,计提明细表!$V$4:$V$59,$D7,计提明细表!$W$4:$W$59,$E7&"",计提明细表!$X$4:$X$59,$F7&"") | I7: =SUMIFS(计提明细表!$L$4:$L$59,计提明细表!$B$4:$B$59,$A7,计提明细表!$T$4:$T$59,$B7,计提明细表!$U$4:$U$59,$C7,计提明细表!$V$4:$V$59,$D7,计提明细表!$W$4:$W$59,$E7&"",计提明细表!$X$4:$X$59,$F7&"") | J7: =SUMIFS(计提明细表!$I$4:$I$59,计提明细表!$B$4:$B$59,$A7,计提明细表!$T$4:$T$59,$B7,计提明细表!$U$4:$U$59,$C7,计提明细表!$V$4:$V$59,$D7,计提明细表!$W$4:$W$59,$E7&"",计提明细表!$X$4:$X$59,$F7&"") | K7: =COUNTIFS(计提明细表!$B$4:$B$59,$A7,计提明细表!$T$4:$T$59,$B7,计提明细表!$U$4:$U$59,$C7,计提明细表!$V$4:$V$59,$D7,计提明细表!$W$4:$W$59,$E7&"",计提明细表!$X$4:$X$59,$F7&"") | L7: 1-6月
A8: 深圳星期零 | B8: 6601 销售费用 | C8: 永续物流中心 0011401 | D8: 出库运费 FYXM008.002其他物流费用002 | E8: CPFL008 | G8: 豆蛋制品 | H8: =SUMIFS(计提明细表!$K$4:$K$59,计提明细表!$B$4:$B$59,$A8,计提明细表!$T$4:$T$59,$B8,计提明细表!$U$4:$U$59,$C8,计提明细表!$V$4:$V$59,$D8,计提明细表!$W$4:$W$59,$E8&"",计提明细表!$X$4:$X$59,$F8&"") | I8: =SUMIFS(计提明细表!$L$4:$L$59,计提明细表!$B$4:$B$59,$A8,计提明细表!$T$4:$T$59,$B8,计提明细表!$U$4:$U$59,$C8,计提明细表!$V$4:$V$59,$D8,计提明细表!$W$4:$W$59,$E8&"",计提明细表!$X$4:$X$59,$F8&"") | J8: =SUMIFS(计提明细表!$I$4:$I$59,计提明细表!$B$4:$B$59,$A8,计提明细表!$T$4:$T$59,$B8,计提明细表!$U$4:$U$59,$C8,计提明细表!$V$4:$V$59,$D8,计提明细表!$W$4:$W$59,$E8&"",计提明细表!$X$4:$X$59,$F8&"") | K8: =COUNTIFS(计提明细表!$B$4:$B$59,$A8,计提明细表!$T$4:$T$59,$B8,计提明细表!$U$4:$U$59,$C8,计提明细表!$V$4:$V$59,$D8,计提明细表!$W$4:$W$59,$E8&"",计提明细表!$X$4:$X$59,$F8&"") | L8: 1-6月
A9: 深圳星期零 | B9: 6601 销售费用 | C9: 永续物流中心 0011401 | D9: 出库运费 FYXM008.002其他物流费用002 | E9: CPFL009 | G9: 小料 | H9: =SUMIFS(计提明细表!$K$4:$K$59,计提明细表!$B$4:$B$59,$A9,计提明细表!$T$4:$T$59,$B9,计提明细表!$U$4:$U$59,$C9,计提明细表!$V$4:$V$59,$D9,计提明细表!$W$4:$W$59,$E9&"",计提明细表!$X$4:$X$59,$F9&"") | I9: =SUMIFS(计提明细表!$L$4:$L$59,计提明细表!$B$4:$B$59,$A9,计提明细表!$T$4:$T$59,$B9,计提明细表!$U$4:$U$59,$C9,计提明细表!$V$4:$V$59,$D9,计提明细表!$W$4:$W$59,$E9&"",计提明细表!$X$4:$X$59,$F9&"") | J9: =SUMIFS(计提明细表!$I$4:$I$59,计提明细表!$B$4:$B$59,$A9,计提明细表!$T$4:$T$59,$B9,计提明细表!$U$4:$U$59,$C9,计提明细表!$V$4:$V$59,$D9,计提明细表!$W$4:$W$59,$E9&"",计提明细表!$X$4:$X$59,$F9&"") | K9: =COUNTIFS(计提明细表!$B$4:$B$59,$A9,计提明细表!$T$4:$T$59,$B9,计提明细表!$U$4:$U$59,$C9,计提明细表!$V$4:$V$59,$D9,计提明细表!$W$4:$W$59,$E9&"",计提明细表!$X$4:$X$59,$F9&"") | L9: 1-6月
A10: 深圳星期零 | B10: 6601 销售费用 | C10: 永续物流中心 0011401 | D10: 出库运费 FYXM008.002其他物流费用002 | E10: CPFL002 | G10: 电商 | H10: =SUMIFS(计提明细表!$K$4:$K$59,计提明细表!$B$4:$B$59,$A10,计提明细表!$T$4:$T$59,$B10,计提明细表!$U$4:$U$59,$C10,计提明细表!$V$4:$V$59,$D10,计提明细表!$W$4:$W$59,$E10&"",计提明细表!$X$4:$X$59,$F10&"") | I10: =SUMIFS(计提明细表!$L$4:$L$59,计提明细表!$B$4:$B$59,$A10,计提明细表!$T$4:$T$59,$B10,计提明细表!$U$4:$U$59,$C10,计提明细表!$V$4:$V$59,$D10,计提明细表!$W$4:$W$59,$E10&"",计提明细表!$X$4:$X$59,$F10&"") | J10: =SUMIFS(计提明细表!$I$4:$I$59,计提明细表!$B$4:$B$59,$A10,计提明细表!$T$4:$T$59,$B10,计提明细表!$U$4:$U$59,$C10,计提明细表!$V$4:$V$59,$D10,计提明细表!$W$4:$W$59,$E10&"",计提明细表!$X$4:$X$59,$F10&"") | K10: =COUNTIFS(计提明细表!$B$4:$B$59,$A10,计提明细表!$T$4:$T$59,$B10,计提明细表!$U$4:$U$59,$C10,计提明细表!$V$4:$V$59,$D10,计提明细表!$W$4:$W$59,$E10&"",计提明细表!$X$4:$X$59,$F10&"") | L10: 1-6月
A11: 深圳星期零 | B11: 6601 销售费用 | C11: 永续物流中心 0011401 | D11: 出库运费 FYXM008.002其他物流费用002 | E11: CPFL013 | F11: CPXM022 | G11: kikiherb | H11: =SUMIFS(计提明细表!$K$4:$K$59,计提明细表!$B$4:$B$59,$A11,计提明细表!$T$4:$T$59,$B11,计提明细表!$U$4:$U$59,$C11,计提明细表!$V$4:$V$59,$D11,计提明细表!$W$4:$W$59,$E11&"",计提明细表!$X$4:$X$59,$F11&"") | I11: =SUMIFS(计提明细表!$L$4:$L$59,计提明细表!$B$4:$B$59,$A11,计提明细表!$T$4:$T$59,$B11,计提明细表!$U$4:$U$59,$C11,计提明细表!$V$4:$V$59,$D11,计提明细表!$W$4:$W$59,$E11&"",计提明细表!$X$4:$X$59,$F11&"") | J11: =SUMIFS(计提明细表!$I$4:$I$59,计提明细表!$B$4:$B$59,$A11,计提明细表!$T$4:$T$59,$B11,计提明细表!$U$4:$U$59,$C11,计提明细表!$V$4:$V$59,$D11,计提明细表!$W$4:$W$59,$E11&"",计提明细表!$X$4:$X$59,$F11&"") | K11: =COUNTIFS(计提明细表!$B$4:$B$59,$A11,计提明细表!$T$4:$T$59,$B11,计提明细表!$U$4:$U$59,$C11,计提明细表!$V$4:$V$59,$D11,计提明细表!$W$4:$W$59,$E11&"",计提明细表!$X$4:$X$59,$F11&"") | L11: 6月起
A12: 深圳星期零 | B12: 6601 销售费用 | C12: 永续物流中心 0011401 | D12: 货物仓储费 FYXM008.002其他物流费用001 | E12: CPFL010 | F12: CPXM017 | G12: 鲜食 | H12: =SUMIFS(计提明细表!$K$4:$K$59,计提明细表!$B$4:$B$59,$A12,计提明细表!$T$4:$T$59,$B12,计提明细表!$U$4:$U$59,$C12,计提明细表!$V$4:$V$59,$D12,计提明细表!$W$4:$W$59,$E12&"",计提明细表!$X$4:$X$59,$F12&"") | I12: =SUMIFS(计提明细表!$L$4:$L$59,计提明细表!$B$4:$B$59,$A12,计提明细表!$T$4:$T$59,$B12,计提明细表!$U$4:$U$59,$C12,计提明细表!$V$4:$V$59,$D12,计提明细表!$W$4:$W$59,$E12&"",计提明细表!$X$4:$X$59,$F12&"") | J12: =SUMIFS(计提明细表!$I$4:$I$59,计提明细表!$B$4:$B$59,$A12,计提明细表!$T$4:$T$59,$B12,计提明细表!$U$4:$U$59,$C12,计提明细表!$V$4:$V$59,$D12,计提明细表!$W$4:$W$59,$E12&"",计提明细表!$X$4:$X$59,$F12&"") | K12: =COUNTIFS(计提明细表!$B$4:$B$59,$A12,计提明细表!$T$4:$T$59,$B12,计提明细表!$U$4:$U$59,$C12,计提明细表!$V$4:$V$59,$D12,计提明细表!$W$4:$W$59,$E12&"",计提明细表!$X$4:$X$59,$F12&"") | L12: 3-4月
A13: 深圳星期零 | B13: 6601 销售费用 | C13: 永续物流中心 0011401 | D13: 货物仓储费 FYXM008.002其他物流费用001 | E13: CPFL011 | G13: 零售 | H13: =SUMIFS(计提明细表!$K$4:$K$59,计提明细表!$B$4:$B$59,$A13,计提明细表!$T$4:$T$59,$B13,计提明细表!$U$4:$U$59,$C13,计提明细表!$V$4:$V$59,$D13,计提明细表!$W$4:$W$59,$E13&"",计提明细表!$X$4:$X$59,$F13&"") | I13: =SUMIFS(计提明细表!$L$4:$L$59,计提明细表!$B$4:$B$59,$A13,计提明细表!$T$4:$T$59,$B13,计提明细表!$U$4:$U$59,$C13,计提明细表!$V$4:$V$59,$D13,计提明细表!$W$4:$W$59,$E13&"",计提明细表!$X$4:$X$59,$F13&"") | J13: =SUMIFS(计提明细表!$I$4:$I$59,计提明细表!$B$4:$B$59,$A13,计提明细表!$T$4:$T$59,$B13,计提明细表!$U$4:$U$59,$C13,计提明细表!$V$4:$V$59,$D13,计提明细表!$W$4:$W$59,$E13&"",计提明细表!$X$4:$X$59,$F13&"") | K13: =COUNTIFS(计提明细表!$B$4:$B$59,$A13,计提明细表!$T$4:$T$59,$B13,计提明细表!$U$4:$U$59,$C13,计提明细表!$V$4:$V$59,$D13,计提明细表!$W$4:$W$59,$E13&"",计提明细表!$X$4:$X$59,$F13&"") | L13: 1月
A14: 深圳星期零 | B14: 6604 研发费用 | C14: 永续研发中心 0010506 | D14: 研发外购 FYXM005.002研发费用001 | G14: — | H14: =SUMIFS(计提明细表!$K$4:$K$59,计提明细表!$B$4:$B$59,$A14,计提明细表!$T$4:$T$59,$B14,计提明细表!$U$4:$U$59,$C14,计提明细表!$V$4:$V$59,$D14,计提明细表!$W$4:$W$59,$E14&"",计提明细表!$X$4:$X$59,$F14&"") | I14: =SUMIFS(计提明细表!$L$4:$L$59,计提明细表!$B$4:$B$59,$A14,计提明细表!$T$4:$T$59,$B14,计提明细表!$U$4:$U$59,$C14,计提明细表!$V$4:$V$59,$D14,计提明细表!$W$4:$W$59,$E14&"",计提明细表!$X$4:$X$59,$F14&"") | J14: =SUMIFS(计提明细表!$I$4:$I$59,计提明细表!$B$4:$B$59,$A14,计提明细表!$T$4:$T$59,$B14,计提明细表!$U$4:$U$59,$C14,计提明细表!$V$4:$V$59,$D14,计提明细表!$W$4:$W$59,$E14&"",计提明细表!$X$4:$X$59,$F14&"") | K14: =COUNTIFS(计提明细表!$B$4:$B$59,$A14,计提明细表!$T$4:$T$59,$B14,计提明细表!$U$4:$U$59,$C14,计提明细表!$V$4:$V$59,$D14,计提明细表!$W$4:$W$59,$E14&"",计提明细表!$X$4:$X$59,$F14&"") | L14: 2-6月
A15: 深圳星期零 | B15: 6604 研发费用 | C15: 永续研发中心 0010506 | D15: 搬运费 FYXM005.003其他业务活动005 | G15: —(设备) | H15: =SUMIFS(计提明细表!$K$4:$K$59,计提明细表!$B$4:$B$59,$A15,计提明细表!$T$4:$T$59,$B15,计提明细表!$U$4:$U$59,$C15,计提明细表!$V$4:$V$59,$D15,计提明细表!$W$4:$W$59,$E15&"",计提明细表!$X$4:$X$59,$F15&"") | I15: =SUMIFS(计提明细表!$L$4:$L$59,计提明细表!$B$4:$B$59,$A15,计提明细表!$T$4:$T$59,$B15,计提明细表!$U$4:$U$59,$C15,计提明细表!$V$4:$V$59,$D15,计提明细表!$W$4:$W$59,$E15&"",计提明细表!$X$4:$X$59,$F15&"") | J15: =SUMIFS(计提明细表!$I$4:$I$59,计提明细表!$B$4:$B$59,$A15,计提明细表!$T$4:$T$59,$B15,计提明细表!$U$4:$U$59,$C15,计提明细表!$V$4:$V$59,$D15,计提明细表!$W$4:$W$59,$E15&"",计提明细表!$X$4:$X$59,$F15&"") | K15: =COUNTIFS(计提明细表!$B$4:$B$59,$A15,计提明细表!$T$4:$T$59,$B15,计提明细表!$U$4:$U$59,$C15,计提明细表!$V$4:$V$59,$D15,计提明细表!$W$4:$W$59,$E15&"",计提明细表!$X$4:$X$59,$F15&"") | L15: 4,7月
A16: 深圳星期九 | B16: 6601 销售费用 | C16: 永续供应中心 0010401 | D16: 出库运费 FYXM008.002其他物流费用002 | E16: CPFL009 | G16: 小料 | H16: =SUMIFS(计提明细表!$K$4:$K$59,计提明细表!$B$4:$B$59,$A16,计提明细表!$T$4:$T$59,$B16,计提明细表!$U$4:$U$59,$C16,计提明细表!$V$4:$V$59,$D16,计提明细表!$W$4:$W$59,$E16&"",计提明细表!$X$4:$X$59,$F16&"") | I16: =SUMIFS(计提明细表!$L$4:$L$59,计提明细表!$B$4:$B$59,$A16,计提明细表!$T$4:$T$59,$B16,计提明细表!$U$4:$U$59,$C16,计提明细表!$V$4:$V$59,$D16,计提明细表!$W$4:$W$59,$E16&"",计提明细表!$X$4:$X$59,$F16&"") | J16: =SUMIFS(计提明细表!$I$4:$I$59,计提明细表!$B$4:$B$59,$A16,计提明细表!$T$4:$T$59,$B16,计提明细表!$U$4:$U$59,$C16,计提明细表!$V$4:$V$59,$D16,计提明细表!$W$4:$W$59,$E16&"",计提明细表!$X$4:$X$59,$F16&"") | K16: =COUNTIFS(计提明细表!$B$4:$B$59,$A16,计提明细表!$T$4:$T$59,$B16,计提明细表!$U$4:$U$59,$C16,计提明细表!$V$4:$V$59,$D16,计提明细表!$W$4:$W$59,$E16&"",计提明细表!$X$4:$X$59,$F16&"") | L16: 1-6月
A17: 孝感星期九 | B17: 5101 制造费用 | C17: 茶饮小料部 0030902 | D17: 入库运费 FYXM002.002运费成本002 | G17: —(小料入库) | H17: =SUMIFS(计提明细表!$K$4:$K$59,计提明细表!$B$4:$B$59,$A17,计提明细表!$T$4:$T$59,$B17,计提明细表!$U$4:$U$59,$C17,计提明细表!$V$4:$V$59,$D17,计提明细表!$W$4:$W$59,$E17&"",计提明细表!$X$4:$X$59,$F17&"") | I17: =SUMIFS(计提明细表!$L$4:$L$59,计提明细表!$B$4:$B$59,$A17,计提明细表!$T$4:$T$59,$B17,计提明细表!$U$4:$U$59,$C17,计提明细表!$V$4:$V$59,$D17,计提明细表!$W$4:$W$59,$E17&"",计提明细表!$X$4:$X$59,$F17&"") | J17: =SUMIFS(计提明细表!$I$4:$I$59,计提明细表!$B$4:$B$59,$A17,计提明细表!$T$4:$T$59,$B17,计提明细表!$U$4:$U$59,$C17,计提明细表!$V$4:$V$59,$D17,计提明细表!$W$4:$W$59,$E17&"",计提明细表!$X$4:$X$59,$F17&"") | K17: =COUNTIFS(计提明细表!$B$4:$B$59,$A17,计提明细表!$T$4:$T$59,$B17,计提明细表!$U$4:$U$59,$C17,计提明细表!$V$4:$V$59,$D17,计提明细表!$W$4:$W$59,$E17&"",计提明细表!$X$4:$X$59,$F17&"") | L17: 1-7月
A18: 孝感星期九 | B18: 5101 制造费用 | C18: 仓储物流部 0030301 | D18: 入库运费 FYXM002.002运费成本002 | G18: —(工厂入库) | H18: =SUMIFS(计提明细表!$K$4:$K$59,计提明细表!$B$4:$B$59,$A18,计提明细表!$T$4:$T$59,$B18,计提明细表!$U$4:$U$59,$C18,计提明细表!$V$4:$V$59,$D18,计提明细表!$W$4:$W$59,$E18&"",计提明细表!$X$4:$X$59,$F18&"") | I18: =SUMIFS(计提明细表!$L$4:$L$59,计提明细表!$B$4:$B$59,$A18,计提明细表!$T$4:$T$59,$B18,计提明细表!$U$4:$U$59,$C18,计提明细表!$V$4:$V$59,$D18,计提明细表!$W$4:$W$59,$E18&"",计提明细表!$X$4:$X$59,$F18&"") | J18: =SUMIFS(计提明细表!$I$4:$I$59,计提明细表!$B$4:$B$59,$A18,计提明细表!$T$4:$T$59,$B18,计提明细表!$U$4:$U$59,$C18,计提明细表!$V$4:$V$59,$D18,计提明细表!$W$4:$W$59,$E18&"",计提明细表!$X$4:$X$59,$F18&"") | K18: =COUNTIFS(计提明细表!$B$4:$B$59,$A18,计提明细表!$T$4:$T$59,$B18,计提明细表!$U$4:$U$59,$C18,计提明细表!$V$4:$V$59,$D18,计提明细表!$W$4:$W$59,$E18&"",计提明细表!$X$4:$X$59,$F18&"") | L18: 1-6月
A19: 孝感星期九 | B19: 5101 制造费用 | C19: 仓储物流部 0030301 | D19: 搬运费 FYXM005.003其他业务活动005 | G19: —(设备) | H19: =SUMIFS(计提明细表!$K$4:$K$59,计提明细表!$B$4:$B$59,$A19,计提明细表!$T$4:$T$59,$B19,计提明细表!$U$4:$U$59,$C19,计提明细表!$V$4:$V$59,$D19,计提明细表!$W$4:$W$59,$E19&"",计提明细表!$X$4:$X$59,$F19&"") | I19: =SUMIFS(计提明细表!$L$4:$L$59,计提明细表!$B$4:$B$59,$A19,计提明细表!$T$4:$T$59,$B19,计提明细表!$U$4:$U$59,$C19,计提明细表!$V$4:$V$59,$D19,计提明细表!$W$4:$W$59,$E19&"",计提明细表!$X$4:$X$59,$F19&"") | J19: =SUMIFS(计提明细表!$I$4:$I$59,计提明细表!$B$4:$B$59,$A19,计提明细表!$T$4:$T$59,$B19,计提明细表!$U$4:$U$59,$C19,计提明细表!$V$4:$V$59,$D19,计提明细表!$W$4:$W$59,$E19&"",计提明细表!$X$4:$X$59,$F19&"") | K19: =COUNTIFS(计提明细表!$B$4:$B$59,$A19,计提明细表!$T$4:$T$59,$B19,计提明细表!$U$4:$U$59,$C19,计提明细表!$V$4:$V$59,$D19,计提明细表!$W$4:$W$59,$E19&"",计提明细表!$X$4:$X$59,$F19&"") | L19: 5月
A20: 孝感星期九 | B20: 6401 主营业务成本 | C20: 仓储物流部 0030301 | D20: 入库运费 FYXM002.002运费成本002 | E20: CPFL010 | F20: CPXM017 | G20: 鲜食 | H20: =SUMIFS(计提明细表!$K$4:$K$59,计提明细表!$B$4:$B$59,$A20,计提明细表!$T$4:$T$59,$B20,计提明细表!$U$4:$U$59,$C20,计提明细表!$V$4:$V$59,$D20,计提明细表!$W$4:$W$59,$E20&"",计提明细表!$X$4:$X$59,$F20&"") | I20: =SUMIFS(计提明细表!$L$4:$L$59,计提明细表!$B$4:$B$59,$A20,计提明细表!$T$4:$T$59,$B20,计提明细表!$U$4:$U$59,$C20,计提明细表!$V$4:$V$59,$D20,计提明细表!$W$4:$W$59,$E20&"",计提明细表!$X$4:$X$59,$F20&"") | J20: =SUMIFS(计提明细表!$I$4:$I$59,计提明细表!$B$4:$B$59,$A20,计提明细表!$T$4:$T$59,$B20,计提明细表!$U$4:$U$59,$C20,计提明细表!$V$4:$V$59,$D20,计提明细表!$W$4:$W$59,$E20&"",计提明细表!$X$4:$X$59,$F20&"") | K20: =COUNTIFS(计提明细表!$B$4:$B$59,$A20,计提明细表!$T$4:$T$59,$B20,计提明细表!$U$4:$U$59,$C20,计提明细表!$V$4:$V$59,$D20,计提明细表!$W$4:$W$59,$E20&"",计提明细表!$X$4:$X$59,$F20&"") | L20: 1-6月
A21: 孝感星期九 | B21: 6401 主营业务成本 | C21: 仓储物流部 0030301 | D21: 入库运费 FYXM002.002运费成本002 | E21: CPFL007 | G21: 植物肉 | H21: =SUMIFS(计提明细表!$K$4:$K$59,计提明细表!$B$4:$B$59,$A21,计提明细表!$T$4:$T$59,$B21,计提明细表!$U$4:$U$59,$C21,计提明细表!$V$4:$V$59,$D21,计提明细表!$W$4:$W$59,$E21&"",计提明细表!$X$4:$X$59,$F21&"") | I21: =SUMIFS(计提明细表!$L$4:$L$59,计提明细表!$B$4:$B$59,$A21,计提明细表!$T$4:$T$59,$B21,计提明细表!$U$4:$U$59,$C21,计提明细表!$V$4:$V$59,$D21,计提明细表!$W$4:$W$59,$E21&"",计提明细表!$X$4:$X$59,$F21&"") | J21: =SUMIFS(计提明细表!$I$4:$I$59,计提明细表!$B$4:$B$59,$A21,计提明细表!$T$4:$T$59,$B21,计提明细表!$U$4:$U$59,$C21,计提明细表!$V$4:$V$59,$D21,计提明细表!$W$4:$W$59,$E21&"",计提明细表!$X$4:$X$59,$F21&"") | K21: =COUNTIFS(计提明细表!$B$4:$B$59,$A21,计提明细表!$T$4:$T$59,$B21,计提明细表!$U$4:$U$59,$C21,计提明细表!$V$4:$V$59,$D21,计提明细表!$W$4:$W$59,$E21&"",计提明细表!$X$4:$X$59,$F21&"") | L21: 2-6月
A22: 孝感星期九 | B22: 6401 主营业务成本 | C22: 仓储物流部 0030301 | D22: 入库运费 FYXM002.002运费成本002 | E22: CPFL011 | G22: 零售 | H22: =SUMIFS(计提明细表!$K$4:$K$59,计提明细表!$B$4:$B$59,$A22,计提明细表!$T$4:$T$59,$B22,计提明细表!$U$4:$U$59,$C22,计提明细表!$V$4:$V$59,$D22,计提明细表!$W$4:$W$59,$E22&"",计提明细表!$X$4:$X$59,$F22&"") | I22: =SUMIFS(计提明细表!$L$4:$L$59,计提明细表!$B$4:$B$59,$A22,计提明细表!$T$4:$T$59,$B22,计提明细表!$U$4:$U$59,$C22,计提明细表!$V$4:$V$59,$D22,计提明细表!$W$4:$W$59,$E22&"",计提明细表!$X$4:$X$59,$F22&"") | J22: =SUMIFS(计提明细表!$I$4:$I$59,计提明细表!$B$4:$B$59,$A22,计提明细表!$T$4:$T$59,$B22,计提明细表!$U$4:$U$59,$C22,计提明细表!$V$4:$V$59,$D22,计提明细表!$W$4:$W$59,$E22&"",计提明细表!$X$4:$X$59,$F22&"") | K22: =COUNTIFS(计提明细表!$B$4:$B$59,$A22,计提明细表!$T$4:$T$59,$B22,计提明细表!$U$4:$U$59,$C22,计提明细表!$V$4:$V$59,$D22,计提明细表!$W$4:$W$59,$E22&"",计提明细表!$X$4:$X$59,$F22&"") | L22: 1,5月
A23: 孝感星期九 | B23: 6401 主营业务成本 | C23: 仓储物流部 0030301 | D23: 入库运费 FYXM002.002运费成本002 | E23: CPFL011 | F23: CPXM017 | G23: 山姆零售 | H23: =SUMIFS(计提明细表!$K$4:$K$59,计提明细表!$B$4:$B$59,$A23,计提明细表!$T$4:$T$59,$B23,计提明细表!$U$4:$U$59,$C23,计提明细表!$V$4:$V$59,$D23,计提明细表!$W$4:$W$59,$E23&"",计提明细表!$X$4:$X$59,$F23&"") | I23: =SUMIFS(计提明细表!$L$4:$L$59,计提明细表!$B$4:$B$59,$A23,计提明细表!$T$4:$T$59,$B23,计提明细表!$U$4:$U$59,$C23,计提明细表!$V$4:$V$59,$D23,计提明细表!$W$4:$W$59,$E23&"",计提明细表!$X$4:$X$59,$F23&"") | J23: =SUMIFS(计提明细表!$I$4:$I$59,计提明细表!$B$4:$B$59,$A23,计提明细表!$T$4:$T$59,$B23,计提明细表!$U$4:$U$59,$C23,计提明细表!$V$4:$V$59,$D23,计提明细表!$W$4:$W$59,$E23&"",计提明细表!$X$4:$X$59,$F23&"") | K23: =COUNTIFS(计提明细表!$B$4:$B$59,$A23,计提明细表!$T$4:$T$59,$B23,计提明细表!$U$4:$U$59,$C23,计提明细表!$V$4:$V$59,$D23,计提明细表!$W$4:$W$59,$E23&"",计提明细表!$X$4:$X$59,$F23&"") | L23: 5月
A24: 孝感星期九 | B24: 6601 销售费用 | C24: 仓储物流部 0030301 | D24: 货物仓储费 FYXM008.002其他物流费用001 | E24: CPFL009 | G24: 小料(线下外仓) | H24: =SUMIFS(计提明细表!$K$4:$K$59,计提明细表!$B$4:$B$59,$A24,计提明细表!$T$4:$T$59,$B24,计提明细表!$U$4:$U$59,$C24,计提明细表!$V$4:$V$59,$D24,计提明细表!$W$4:$W$59,$E24&"",计提明细表!$X$4:$X$59,$F24&"") | I24: =SUMIFS(计提明细表!$L$4:$L$59,计提明细表!$B$4:$B$59,$A24,计提明细表!$T$4:$T$59,$B24,计提明细表!$U$4:$U$59,$C24,计提明细表!$V$4:$V$59,$D24,计提明细表!$W$4:$W$59,$E24&"",计提明细表!$X$4:$X$59,$F24&"") | J24: =SUMIFS(计提明细表!$I$4:$I$59,计提明细表!$B$4:$B$59,$A24,计提明细表!$T$4:$T$59,$B24,计提明细表!$U$4:$U$59,$C24,计提明细表!$V$4:$V$59,$D24,计提明细表!$W$4:$W$59,$E24&"",计提明细表!$X$4:$X$59,$F24&"") | K24: =COUNTIFS(计提明细表!$B$4:$B$59,$A24,计提明细表!$T$4:$T$59,$B24,计提明细表!$U$4:$U$59,$C24,计提明细表!$V$4:$V$59,$D24,计提明细表!$W$4:$W$59,$E24&"",计提明细表!$X$4:$X$59,$F24&"") | L24: 1-6月
A25: 孝感星期九 | B25: 6601 销售费用 | C25: 永续物流中心 0011401 | D25: 货物仓储费 FYXM008.002其他物流费用001 | E25: CPFL002 | G25: 电商(电商仓) | H25: =SUMIFS(计提明细表!$K$4:$K$59,计提明细表!$B$4:$B$59,$A25,计提明细表!$T$4:$T$59,$B25,计提明细表!$U$4:$U$59,$C25,计提明细表!$V$4:$V$59,$D25,计提明细表!$W$4:$W$59,$E25&"",计提明细表!$X$4:$X$59,$F25&"") | I25: =SUMIFS(计提明细表!$L$4:$L$59,计提明细表!$B$4:$B$59,$A25,计提明细表!$T$4:$T$59,$B25,计提明细表!$U$4:$U$59,$C25,计提明细表!$V$4:$V$59,$D25,计提明细表!$W$4:$W$59,$E25&"",计提明细表!$X$4:$X$59,$F25&"") | J25: =SUMIFS(计提明细表!$I$4:$I$59,计提明细表!$B$4:$B$59,$A25,计提明细表!$T$4:$T$59,$B25,计提明细表!$U$4:$U$59,$C25,计提明细表!$V$4:$V$59,$D25,计提明细表!$W$4:$W$59,$E25&"",计提明细表!$X$4:$X$59,$F25&"") | K25: =COUNTIFS(计提明细表!$B$4:$B$59,$A25,计提明细表!$T$4:$T$59,$B25,计提明细表!$U$4:$U$59,$C25,计提明细表!$V$4:$V$59,$D25,计提明细表!$W$4:$W$59,$E25&"",计提明细表!$X$4:$X$59,$F25&"") | L25: 1-6月
A26: 孝感星期九 | B26: 6601 销售费用 | C26: 永续物流中心 0011401 | D26: 货物仓储费 FYXM008.002其他物流费用001 | E26: CPFL013 | F26: CPXM022 | G26: kikiherb | H26: =SUMIFS(计提明细表!$K$4:$K$59,计提明细表!$B$4:$B$59,$A26,计提明细表!$T$4:$T$59,$B26,计提明细表!$U$4:$U$59,$C26,计提明细表!$V$4:$V$59,$D26,计提明细表!$W$4:$W$59,$E26&"",计提明细表!$X$4:$X$59,$F26&"") | I26: =SUMIFS(计提明细表!$L$4:$L$59,计提明细表!$B$4:$B$59,$A26,计提明细表!$T$4:$T$59,$B26,计提明细表!$U$4:$U$59,$C26,计提明细表!$V$4:$V$59,$D26,计提明细表!$W$4:$W$59,$E26&"",计提明细表!$X$4:$X$59,$F26&"") | J26: =SUMIFS(计提明细表!$I$4:$I$59,计提明细表!$B$4:$B$59,$A26,计提明细表!$T$4:$T$59,$B26,计提明细表!$U$4:$U$59,$C26,计提明细表!$V$4:$V$59,$D26,计提明细表!$W$4:$W$59,$E26&"",计提明细表!$X$4:$X$59,$F26&"") | K26: =COUNTIFS(计提明细表!$B$4:$B$59,$A26,计提明细表!$T$4:$T$59,$B26,计提明细表!$U$4:$U$59,$C26,计提明细表!$V$4:$V$59,$D26,计提明细表!$W$4:$W$59,$E26&"",计提明细表!$X$4:$X$59,$F26&"") | L26: 6月起
A27: 孝感星期九 | B27: 6601 销售费用 | C27: 永续物流中心 0011401 | D27: 货物仓储费 FYXM008.002其他物流费用001 | E27: CPFL010 | F27: CPXM017 | G27: 鲜食(线上) | H27: =SUMIFS(计提明细表!$K$4:$K$59,计提明细表!$B$4:$B$59,$A27,计提明细表!$T$4:$T$59,$B27,计提明细表!$U$4:$U$59,$C27,计提明细表!$V$4:$V$59,$D27,计提明细表!$W$4:$W$59,$E27&"",计提明细表!$X$4:$X$59,$F27&"") | I27: =SUMIFS(计提明细表!$L$4:$L$59,计提明细表!$B$4:$B$59,$A27,计提明细表!$T$4:$T$59,$B27,计提明细表!$U$4:$U$59,$C27,计提明细表!$V$4:$V$59,$D27,计提明细表!$W$4:$W$59,$E27&"",计提明细表!$X$4:$X$59,$F27&"") | J27: =SUMIFS(计提明细表!$I$4:$I$59,计提明细表!$B$4:$B$59,$A27,计提明细表!$T$4:$T$59,$B27,计提明细表!$U$4:$U$59,$C27,计提明细表!$V$4:$V$59,$D27,计提明细表!$W$4:$W$59,$E27&"",计提明细表!$X$4:$X$59,$F27&"") | K27: =COUNTIFS(计提明细表!$B$4:$B$59,$A27,计提明细表!$T$4:$T$59,$B27,计提明细表!$U$4:$U$59,$C27,计提明细表!$V$4:$V$59,$D27,计提明细表!$W$4:$W$59,$E27&"",计提明细表!$X$4:$X$59,$F27&"") | L27: 5月
A28: 孝感星期九 | B28: 6402 其他业务支出 | C28: 仓储物流部 0030301 | D28: 原辅料及包装物 FYXM002.004其他产品成本费用009 | G28: —(原料销售) | H28: =SUMIFS(计提明细表!$K$4:$K$59,计提明细表!$B$4:$B$59,$A28,计提明细表!$T$4:$T$59,$B28,计提明细表!$U$4:$U$59,$C28,计提明细表!$V$4:$V$59,$D28,计提明细表!$W$4:$W$59,$E28&"",计提明细表!$X$4:$X$59,$F28&"") | I28: =SUMIFS(计提明细表!$L$4:$L$59,计提明细表!$B$4:$B$59,$A28,计提明细表!$T$4:$T$59,$B28,计提明细表!$U$4:$U$59,$C28,计提明细表!$V$4:$V$59,$D28,计提明细表!$W$4:$W$59,$E28&"",计提明细表!$X$4:$X$59,$F28&"") | J28: =SUMIFS(计提明细表!$I$4:$I$59,计提明细表!$B$4:$B$59,$A28,计提明细表!$T$4:$T$59,$B28,计提明细表!$U$4:$U$59,$C28,计提明细表!$V$4:$V$59,$D28,计提明细表!$W$4:$W$59,$E28&"",计提明细表!$X$4:$X$59,$F28&"") | K28: =COUNTIFS(计提明细表!$B$4:$B$59,$A28,计提明细表!$T$4:$T$59,$B28,计提明细表!$U$4:$U$59,$C28,计提明细表!$V$4:$V$59,$D28,计提明细表!$W$4:$W$59,$E28&"",计提明细表!$X$4:$X$59,$F28&"") | L28: 1-4月
A29: 孝感星期九 | B29: 6604 研发费用 | C29: 永续研发中心 0010506 | D29: 研发外购 FYXM005.002研发费用001 | G29: —(研发中试) | H29: =SUMIFS(计提明细表!$K$4:$K$59,计提明细表!$B$4:$B$59,$A29,计提明细表!$T$4:$T$59,$B29,计提明细表!$U$4:$U$59,$C29,计提明细表!$V$4:$V$59,$D29,计提明细表!$W$4:$W$59,$E29&"",计提明细表!$X$4:$X$59,$F29&"") | I29: =SUMIFS(计提明细表!$L$4:$L$59,计提明细表!$B$4:$B$59,$A29,计提明细表!$T$4:$T$59,$B29,计提明细表!$U$4:$U$59,$C29,计提明细表!$V$4:$V$59,$D29,计提明细表!$W$4:$W$59,$E29&"",计提明细表!$X$4:$X$59,$F29&"") | J29: =SUMIFS(计提明细表!$I$4:$I$59,计提明细表!$B$4:$B$59,$A29,计提明细表!$T$4:$T$59,$B29,计提明细表!$U$4:$U$59,$C29,计提明细表!$V$4:$V$59,$D29,计提明细表!$W$4:$W$59,$E29&"",计提明细表!$X$4:$X$59,$F29&"") | K29: =COUNTIFS(计提明细表!$B$4:$B$59,$A29,计提明细表!$T$4:$T$59,$B29,计提明细表!$U$4:$U$59,$C29,计提明细表!$V$4:$V$59,$D29,计提明细表!$W$4:$W$59,$E29&"",计提明细表!$X$4:$X$59,$F29&"") | L29: 5,7月
A30: 孝感星期九 | B30: 6601 销售费用 | C30: 永续物流中心 0011401 | D30: 出库运费 FYXM008.002其他物流费用002 | E30: CPFL007 | G30: 植物肉(调拨) | H30: =SUMIFS(计提明细表!$K$4:$K$59,计提明细表!$B$4:$B$59,$A30,计提明细表!$T$4:$T$59,$B30,计提明细表!$U$4:$U$59,$C30,计提明细表!$V$4:$V$59,$D30,计提明细表!$W$4:$W$59,$E30&"",计提明细表!$X$4:$X$59,$F30&"") | I30: =SUMIFS(计提明细表!$L$4:$L$59,计提明细表!$B$4:$B$59,$A30,计提明细表!$T$4:$T$59,$B30,计提明细表!$U$4:$U$59,$C30,计提明细表!$V$4:$V$59,$D30,计提明细表!$W$4:$W$59,$E30&"",计提明细表!$X$4:$X$59,$F30&"") | J30: =SUMIFS(计提明细表!$I$4:$I$59,计提明细表!$B$4:$B$59,$A30,计提明细表!$T$4:$T$59,$B30,计提明细表!$U$4:$U$59,$C30,计提明细表!$V$4:$V$59,$D30,计提明细表!$W$4:$W$59,$E30&"",计提明细表!$X$4:$X$59,$F30&"") | K30: =COUNTIFS(计提明细表!$B$4:$B$59,$A30,计提明细表!$T$4:$T$59,$B30,计提明细表!$U$4:$U$59,$C30,计提明细表!$V$4:$V$59,$D30,计提明细表!$W$4:$W$59,$E30&"",计提明细表!$X$4:$X$59,$F30&"") | L30: 7月新增
A31: 🖐维度待定 | B31: (费用归属空/人工核对行,在明细表补齐后自动归位) | H31: =SUMIFS(计提明细表!$K$4:$K$59,计提明细表!$T$4:$T$59,"",计提明细表!$I$4:$I$59,"<>") | I31: =SUMIFS(计提明细表!$L$4:$L$59,计提明细表!$T$4:$T$59,"",计提明细表!$I$4:$I$59,"<>") | J31: =SUMIFS(计提明细表!$I$4:$I$59,计提明细表!$T$4:$T$59,"",计提明细表!$I$4:$I$59,"<>") | K31: =COUNTIFS(计提明细表!$T$4:$T$59,"",计提明细表!$I$4:$I$59,"<>")
A32: 合计 | H32: =SUM(H4:H31) | I32: =SUM(I4:I31) | J32: =SUM(J4:J31) | K32: =SUM(K4:K31)
A34: 核对:组合外金额(明细I60−上表合计)= | H34: =计提明细表!$I$60-J32 | I34: ← 应为0;≠0=明细表有维度组合不在上表——常见:①做账主体与账单付款主体不一致(如原料入库账证只记孝感簿)②人工改了维度③新业务。查明细表核对后把组合补一行。
A35: 注:5101/6604/6402 科目不挂产品分类/产品项目(账证维度配置);「其它」类费用财务定科目后,组合行由工具签发时自动补。

Sheet 供应商列表
A1: 供应商列表(物流商身份+渠道+13类费用归属税率矩阵)——工具按月签发快照,勿手改;税率单一事实源=工具税率维表
A2: 物流商简称 | B2: 物流商全称 | C2: 金蝶供应商编码 (工具回填) | D2: 供应商分组 (工具回填) | E2: 渠道 (摘要用) | F2: 税率(按13类费用归属·专票口径) | S2: 是否建档 | T2: 备注
F3: 销售出库费用 | G3: 成品入库费用 | H3: 原料入库费用 | I3: 成品仓储费用 | J3: 原料仓储费用 | K3: 成品调拨费用 | L3: 原料调拨费用 | M3: 出库装卸费用 | N3: 成品入库装卸费用 | O3: 原料入库装卸费用 | P3: 研发设备采购 | Q3: 设备调拨费用 | R3: 其它
A4: 顺丰冷运 | B4: 上海顺丰冷运供应链有限公司 | D4: 供应商009 | E4: 线下 | F4: 0.09 | G4: 0.09 | H4: 0.09 | I4: 0.09 | J4: 0.09 | K4: 0.09 | L4: 0.09 | M4: 0.09 | N4: 0.09 | O4: 0.09 | P4: 0.09 | Q4: 0.09 | R4: 0.09 | S4: ✓
A5: 顺丰速运 | B5: 深圳顺丰速运有限公司 | D5: 供应商009 | E5: 线下 | F5: 0.06 | G5: 0.06 | H5: 0.06 | I5: 0.06 | J5: 0.06 | K5: 0.06 | L5: 0.06 | M5: 0.06 | N5: 0.06 | O5: 0.06 | P5: 0.06 | Q5: 0.06 | R5: 0.06 | S5: ✓
A6: 跨越物流 | B6: 深圳市跨越冷运有限公司 | D6: 供应商009 | E6: 线下 | F6: 0.06 | G6: 0.06 | H6: 0.06 | I6: 0.06 | J6: 0.06 | K6: 0.06 | L6: 0.06 | M6: 0.06 | N6: 0.06 | O6: 0.06 | P6: 0.06 | Q6: 0.06 | R6: 0.06 | S6: ✓
A7: 易风达 | B7: 武汉易风达冷链物流有限公司 | D7: 供应商009 | E7: 线下 | F7: 0.09 | G7: 0.09 | H7: 0.09 | I7: 0.06 | J7: 0.06 | K7: 0.09 | L7: 0.09 | M7: 0.09 | N7: 0.09 | O7: 0.09 | P7: 0.09 | Q7: 0.09 | R7: 0.09 | S7: ✓
A8: 朴朴 | B8: 朴朴 | D8: 供应商009 | E8: 线下 | F8: 0.09 | G8: 0.09 | H8: 0.09 | I8: 0.09 | J8: 0.09 | K8: 0.09 | L8: 0.09 | M8: 0.09 | N8: 0.09 | O8: 0.09 | P8: 0.09 | Q8: 0.09 | R8: 0.09 | S8: ✓
A9: 诚煜物流 | B9: 武汉诚煜冷藏物流有限公司 | D9: 供应商009 | E9: 线下 | F9: 0.09 | G9: 0.09 | H9: 0.09 | I9: 0.09 | J9: 0.09 | K9: 0.09 | L9: 0.09 | M9: 0.09 | N9: 0.09 | O9: 0.09 | P9: 0.09 | Q9: 0.09 | R9: 0.09 | S9: ✓
A10: 金刚物流 | B10: 大连金刚冷藏运输有限公司 | D10: 供应商009 | E10: 线下 | F10: 0.09 | G10: 0.09 | H10: 0.09 | I10: 0.09 | J10: 0.09 | K10: 0.09 | L10: 0.09 | M10: 0.09 | N10: 0.09 | O10: 0.09 | P10: 0.09 | Q10: 0.09 | R10: 0.09 | S10: ✓
A11: 链盟 | B11: 东莞市链盟供应链有限公司 | D11: 供应商009 | E11: 线下 | F11: 0.09 | G11: 0.09 | H11: 0.09 | I11: 0.09 | J11: 0.09 | K11: 0.09 | L11: 0.09 | M11: 0.09 | N11: 0.09 | O11: 0.09 | P11: 0.09 | Q11: 0.09 | R11: 0.09 | S11: ✓
A12: 路凯（13%） | B12: 路凯包装设备租赁（上海）有限公司 | D12: 供应商009 | E12: 线下 | F12: 0.13 | G12: 0.13 | H12: 0.13 | I12: 0.13 | J12: 0.13 | K12: 0.13 | L12: 0.13 | M12: 0.13 | N12: 0.13 | O12: 0.13 | P12: 0.13 | Q12: 0.13 | R12: 0.13 | S12: ✓
A13: 中通快运 | B13: 孝感市顺捷物流有限公司 | D13: 供应商009 | E13: 线下 | F13: 0.06 | G13: 0.06 | H13: 0.06 | I13: 0.06 | J13: 0.06 | K13: 0.06 | L13: 0.06 | M13: 0.06 | N13: 0.06 | O13: 0.06 | P13: 0.06 | Q13: 0.06 | R13: 0.06 | S13: ✓
A14: 极鲜达 | B14: 湖北极鲜达供应链责任公司 | D14: 供应商009 | E14: 线下 | F14: 0.09 | G14: 0.09 | H14: 0.09 | I14: 0.06 | J14: 0.06 | K14: 0.09 | L14: 0.09 | M14: 0.09 | N14: 0.09 | O14: 0.09 | P14: 0.09 | Q14: 0.09 | R14: 0.09 | S14: ✓
A15: 丰源 | B15: 湖北丰源物流供应链管理有限公司 | D15: 供应商009 | E15: 线下 | F15: 0.09 | G15: 0.09 | H15: 0.09 | I15: 0.09 | J15: 0.09 | K15: 0.09 | L15: 0.09 | M15: 0.09 | N15: 0.09 | O15: 0.09 | P15: 0.09 | Q15: 0.09 | R15: 0.09 | S15: ✓
... A25: 货拉拉 | B25: 货拉拉 | D25: 供应商009 | E25: 线下 | F25: 0.09 | G25: 0.09 | H25: 0.09 | I25: 0.09 | J25: 0.09 | K25: 0.09 | L25: 0.09 | M25: 0.09 | N25: 0.09 | O25: 0.09 | P25: 0.09 | Q25: 0.09 | R25: 0.09 | S25: ✓
A27: 说明:
A28: · 一行一物流商,简称是全表唯一查找键——同名两法人(如顺丰速运/大润发)须拆成不同简称。
A29: · 13 列税率=该商各费用归属的专票税率;橙格=与默认档(销售出库列)不同,如易风达/极鲜达仓储 6%。
A30: · 本表由财务工具按月签发(数据源=工具税率维表+供应商档案),物流部发现缺商/税率不对→联系财务改工具,下月快照自动更新。

Sheet 物流商费用汇总表
A1: 物流商费用汇总表(全公式自动 · 数据源=计提明细表) 账期 2026-07
A2: 物流商简称 | B2: 含税合计 | C2: 深圳星期零 | F2: 孝感星期九 | I2: 深圳星期九 | L2: 状态推进(手填/工具回填)
C3: 9% | D3: 6% | E3: 13% | F3: 9% | G3: 6% | H3: 13% | I3: 9% | J3: 6% | K3: 13% | L3: 已计提 | M3: 对账定稿 | N3: 已开票 | O3: 已请款 | P3: 已付款
A4: 顺丰冷运 | B4: =SUMIFS(计提明细表!$I$4:$I$59,计提明细表!$C$4:$C$59,A4) | C4: =SUMIFS(计提明细表!$I$4:$I$59,计提明细表!$C$4:$C$59,$A4,计提明细表!$B$4:$B$59,"深圳星期零",计提明细表!$J$4:$J$59,0.09) | D4: =SUMIFS(计提明细表!$I$4:$I$59,计提明细表!$C$4:$C$59,$A4,计提明细表!$B$4:$B$59,"深圳星期零",计提明细表!$J$4:$J$59,0.06) | E4: =SUMIFS(计提明细表!$I$4:$I$59,计提明细表!$C$4:$C$59,$A4,计提明细表!$B$4:$B$59,"深圳星期零",计提明细表!$J$4:$J$59,0.13) | F4: =SUMIFS(计提明细表!$I$4:$I$59,计提明细表!$C$4:$C$59,$A4,计提明细表!$B$4:$B$59,"孝感星期九",计提明细表!$J$4:$J$59,0.09) | G4: =SUMIFS(计提明细表!$I$4:$I$59,计提明细表!$C$4:$C$59,$A4,计提明细表!$B$4:$B$59,"孝感星期九",计提明细表!$J$4:$J$59,0.06) | H4: =SUMIFS(计提明细表!$I$4:$I$59,计提明细表!$C$4:$C$59,$A4,计提明细表!$B$4:$B$59,"孝感星期九",计提明细表!$J$4:$J$59,0.13) | I4: =SUMIFS(计提明细表!$I$4:$I$59,计提明细表!$C$4:$C$59,$A4,计提明细表!$B$4:$B$59,"深圳星期九",计提明细表!$J$4:$J$59,0.09) | J4: =SUMIFS(计提明细表!$I$4:$I$59,计提明细表!$C$4:$C$59,$A4,计提明细表!$B$4:$B$59,"深圳星期九",计提明细表!$J$4:$J$59,0.06) | K4: =SUMIFS(计提明细表!$I$4:$I$59,计提明细表!$C$4:$C$59,$A4,计提明细表!$B$4:$B$59,"深圳星期九",计提明细表!$J$4:$J$59,0.13)
A5: 顺丰速运 | B5: =SUMIFS(计提明细表!$I$4:$I$59,计提明细表!$C$4:$C$59,A5) | C5: =SUMIFS(计提明细表!$I$4:$I$59,计提明细表!$C$4:$C$59,$A5,计提明细表!$B$4:$B$59,"深圳星期零",计提明细表!$J$4:$J$59,0.09) | D5: =SUMIFS(计提明细表!$I$4:$I$59,计提明细表!$C$4:$C$59,$A5,计提明细表!$B$4:$B$59,"深圳星期零",计提明细表!$J$4:$J$59,0.06) | E5: =SUMIFS(计提明细表!$I$4:$I$59,计提明细表!$C$4:$C$59,$A5,计提明细表!$B$4:$B$59,"深圳星期零",计提明细表!$J$4:$J$59,0.13) | F5: =SUMIFS(计提明细表!$I$4:$I$59,计提明细表!$C$4:$C$59,$A5,计提明细表!$B$4:$B$59,"孝感星期九",计提明细表!$J$4:$J$59,0.09) | G5: =SUMIFS(计提明细表!$I$4:$I$59,计提明细表!$C$4:$C$59,$A5,计提明细表!$B$4:$B$59,"孝感星期九",计提明细表!$J$4:$J$59,0.06) | H5: =SUMIFS(计提明细表!$I$4:$I$59,计提明细表!$C$4:$C$59,$A5,计提明细表!$B$4:$B$59,"孝感星期九",计提明细表!$J$4:$J$59,0.13) | I5: =SUMIFS(计提明细表!$I$4:$I$59,计提明细表!$C$4:$C$59,$A5,计提明细表!$B$4:$B$59,"深圳星期九",计提明细表!$J$4:$J$59,0.09) | J5: =SUMIFS(计提明细表!$I$4:$I$59,计提明细表!$C$4:$C$59,$A5,计提明细表!$B$4:$B$59,"深圳星期九",计提明细表!$J$4:$J$59,0.06) | K5: =SUMIFS(计提明细表!$I$4:$I$59,计提明细表!$C$4:$C$59,$A5,计提明细表!$B$4:$B$59,"深圳星期九",计提明细表!$J$4:$J$59,0.13)
A6: 跨越物流 | B6: =SUMIFS(计提明细表!$I$4:$I$59,计提明细表!$C$4:$C$59,A6) | C6: =SUMIFS(计提明细表!$I$4:$I$59,计提明细表!$C$4:$C$59,$A6,计提明细表!$B$4:$B$59,"深圳星期零",计提明细表!$J$4:$J$59,0.09) | D6: =SUMIFS(计提明细表!$I$4:$I$59,计提明细表!$C$4:$C$59,$A6,计提明细表!$B$4:$B$59,"深圳星期零",计提明细表!$J$4:$J$59,0.06) | E6: =SUMIFS(计提明细表!$I$4:$I$59,计提明细表!$C$4:$C$59,$A6,计提明细表!$B$4:$B$59,"深圳星期零",计提明细表!$J$4:$J$59,0.13) | F6: =SUMIFS(计提明细表!$I$4:$I$59,计提明细表!$C$4:$C$59,$A6,计提明细表!$B$4:$B$59,"孝感星期九",计提明细表!$J$4:$J$59,0.09) | G6: =SUMIFS(计提明细表!$I$4:$I$59,计提明细表!$C$4:$C$59,$A6,计提明细表!$B$4:$B$59,"孝感星期九",计提明细表!$J$4:$J$59,0.06) | H6: =SUMIFS(计提明细表!$I$4:$I$59,计提明细表!$C$4:$C$59,$A6,计提明细表!$B$4:$B$59,"孝感星期九",计提明细表!$J$4:$J$59,0.13) | I6: =SUMIFS(计提明细表!$I$4:$I$59,计提明细表!$C$4:$C$59,$A6,计提明细表!$B$4:$B$59,"深圳星期九",计提明细表!$J$4:$J$59,0.09) | J6: =SUMIFS(计提明细表!$I$4:$I$59,计提明细表!$C$4:$C$59,$A6,计提明细表!$B$4:$B$59,"深圳星期九",计提明细表!$J$4:$J$59,0.06) | K6: =SUMIFS(计提明细表!$I$4:$I$59,计提明细表!$C$4:$C$59,$A6,计提明细表!$B$4:$B$59,"深圳星期九",计提明细表!$J$4:$J$59,0.13)
A7: 易风达 | B7: =SUMIFS(计提明细表!$I$4:$I$59,计提明细表!$C$4:$C$59,A7) | C7: =SUMIFS(计提明细表!$I$4:$I$59,计提明细表!$C$4:$C$59,$A7,计提明细表!$B$4:$B$59,"深圳星期零",计提明细表!$J$4:$J$59,0.09) | D7: =SUMIFS(计提明细表!$I$4:$I$59,计提明细表!$C$4:$C$59,$A7,计提明细表!$B$4:$B$59,"深圳星期零",计提明细表!$J$4:$J$59,0.06) | E7: =SUMIFS(计提明细表!$I$4:$I$59,计提明细表!$C$4:$C$59,$A7,计提明细表!$B$4:$B$59,"深圳星期零",计提明细表!$J$4:$J$59,0.13) | F7: =SUMIFS(计提明细表!$I$4:$I$59,计提明细表!$C$4:$C$59,$A7,计提明细表!$B$4:$B$59,"孝感星期九",计提明细表!$J$4:$J$59,0.09) | G7: =SUMIFS(计提明细表!$I$4:$I$59,计提明细表!$C$4:$C$59,$A7,计提明细表!$B$4:$B$59,"孝感星期九",计提明细表!$J$4:$J$59,0.06) | H7: =SUMIFS(计提明细表!$I$4:$I$59,计提明细表!$C$4:$C$59,$A7,计提明细表!$B$4:$B$59,"孝感星期九",计提明细表!$J$4:$J$59,0.13) | I7: =SUMIFS(计提明细表!$I$4:$I$59,计提明细表!$C$4:$C$59,$A7,计提明细表!$B$4:$B$59,"深圳星期九",计提明细表!$J$4:$J$59,0.09) | J7: =SUMIFS(计提明细表!$I$4:$I$59,计提明细表!$C$4:$C$59,$A7,计提明细表!$B$4:$B$59,"深圳星期九",计提明细表!$J$4:$J$59,0.06) | K7: =SUMIFS(计提明细表!$I$4:$I$59,计提明细表!$C$4:$C$59,$A7,计提明细表!$B$4:$B$59,"深圳星期九",计提明细表!$J$4:$J$59,0.13)
A8: 朴朴 | B8: =SUMIFS(计提明细表!$I$4:$I$59,计提明细表!$C$4:$C$59,A8) | C8: =SUMIFS(计提明细表!$I$4:$I$59,计提明细表!$C$4:$C$59,$A8,计提明细表!$B$4:$B$59,"深圳星期零",计提明细表!$J$4:$J$59,0.09) | D8: =SUMIFS(计提明细表!$I$4:$I$59,计提明细表!$C$4:$C$59,$A8,计提明细表!$B$4:$B$59,"深圳星期零",计提明细表!$J$4:$J$59,0.06) | E8: =SUMIFS(计提明细表!$I$4:$I$59,计提明细表!$C$4:$C$59,$A8,计提明细表!$B$4:$B$59,"深圳星期零",计提明细表!$J$4:$J$59,0.13) | F8: =SUMIFS(计提明细表!$I$4:$I$59,计提明细表!$C$4:$C$59,$A8,计提明细表!$B$4:$B$59,"孝感星期九",计提明细表!$J$4:$J$59,0.09) | G8: =SUMIFS(计提明细表!$I$4:$I$59,计提明细表!$C$4:$C$59,$A8,计提明细表!$B$4:$B$59,"孝感星期九",计提明细表!$J$4:$J$59,0.06) | H8: =SUMIFS(计提明细表!$I$4:$I$59,计提明细表!$C$4:$C$59,$A8,计提明细表!$B$4:$B$59,"孝感星期九",计提明细表!$J$4:$J$59,0.13) | I8: =SUMIFS(计提明细表!$I$4:$I$59,计提明细表!$C$4:$C$59,$A8,计提明细表!$B$4:$B$59,"深圳星期九",计提明细表!$J$4:$J$59,0.09) | J8: =SUMIFS(计提明细表!$I$4:$I$59,计提明细表!$C$4:$C$59,$A8,计提明细表!$B$4:$B$59,"深圳星期九",计提明细表!$J$4:$J$59,0.06) | K8: =SUMIFS(计提明细表!$I$4:$I$59,计提明细表!$C$4:$C$59,$A8,计提明细表!$B$4:$B$59,"深圳星期九",计提明细表!$J$4:$J$59,0.13)
A9: 诚煜物流 | B9: =SUMIFS(计提明细表!$I$4:$I$59,计提明细表!$C$4:$C$59,A9) | C9: =SUMIFS(计提明细表!$I$4:$I$59,计提明细表!$C$4:$C$59,$A9,计提明细表!$B$4:$B$59,"深圳星期零",计提明细表!$J$4:$J$59,0.09) | D9: =SUMIFS(计提明细表!$I$4:$I$59,计提明细表!$C$4:$C$59,$A9,计提明细表!$B$4:$B$59,"深圳星期零",计提明细表!$J$4:$J$59,0.06) | E9: =SUMIFS(计提明细表!$I$4:$I$59,计提明细表!$C$4:$C$59,$A9,计提明细表!$B$4:$B$59,"深圳星期零",计提明细表!$J$4:$J$59,0.13) | F9: =SUMIFS(计提明细表!$I$4:$I$59,计提明细表!$C$4:$C$59,$A9,计提明细表!$B$4:$B$59,"孝感星期九",计提明细表!$J$4:$J$59,0.09) | G9: =SUMIFS(计提明细表!$I$4:$I$59,计提明细表!$C$4:$C$59,$A9,计提明细表!$B$4:$B$59,"孝感星期九",计提明细表!$J$4:$J$59,0.06) | H9: =SUMIFS(计提明细表!$I$4:$I$59,计提明细表!$C$4:$C$59,$A9,计提明细表!$B$4:$B$59,"孝感星期九",计提明细表!$J$4:$J$59,0.13) | I9: =SUMIFS(计提明细表!$I$4:$I$59,计提明细表!$C$4:$C$59,$A9,计提明细表!$B$4:$B$59,"深圳星期九",计提明细表!$J$4:$J$59,0.09) | J9: =SUMIFS(计提明细表!$I$4:$I$59,计提明细表!$C$4:$C$59,$A9,计提明细表!$B$4:$B$59,"深圳星期九",计提明细表!$J$4:$J$59,0.06) | K9: =SUMIFS(计提明细表!$I$4:$I$59,计提明细表!$C$4:$C$59,$A9,计提明细表!$B$4:$B$59,"深圳星期九",计提明细表!$J$4:$J$59,0.13)
A10: 金刚物流 | B10: =SUMIFS(计提明细表!$I$4:$I$59,计提明细表!$C$4:$C$59,A10) | C10: =SUMIFS(计提明细表!$I$4:$I$59,计提明细表!$C$4:$C$59,$A10,计提明细表!$B$4:$B$59,"深圳星期零",计提明细表!$J$4:$J$59,0.09) | D10: =SUMIFS(计提明细表!$I$4:$I$59,计提明细表!$C$4:$C$59,$A10,计提明细表!$B$4:$B$59,"深圳星期零",计提明细表!$J$4:$J$59,0.06) | E10: =SUMIFS(计提明细表!$I$4:$I$59,计提明细表!$C$4:$C$59,$A10,计提明细表!$B$4:$B$59,"深圳星期零",计提明细表!$J$4:$J$59,0.13) | F10: =SUMIFS(计提明细表!$I$4:$I$59,计提明细表!$C$4:$C$59,$A10,计提明细表!$B$4:$B$59,"孝感星期九",计提明细表!$J$4:$J$59,0.09) | G10: =SUMIFS(计提明细表!$I$4:$I$59,计提明细表!$C$4:$C$59,$A10,计提明细表!$B$4:$B$59,"孝感星期九",计提明细表!$J$4:$J$59,0.06) | H10: =SUMIFS(计提明细表!$I$4:$I$59,计提明细表!$C$4:$C$59,$A10,计提明细表!$B$4:$B$59,"孝感星期九",计提明细表!$J$4:$J$59,0.13) | I10: =SUMIFS(计提明细表!$I$4:$I$59,计提明细表!$C$4:$C$59,$A10,计提明细表!$B$4:$B$59,"深圳星期九",计提明细表!$J$4:$J$59,0.09) | J10: =SUMIFS(计提明细表!$I$4:$I$59,计提明细表!$C$4:$C$59,$A10,计提明细表!$B$4:$B$59,"深圳星期九",计提明细表!$J$4:$J$59,0.06) | K10: =SUMIFS(计提明细表!$I$4:$I$59,计提明细表!$C$4:$C$59,$A10,计提明细表!$B$4:$B$59,"深圳星期九",计提明细表!$J$4:$J$59,0.13)
A11: 链盟 | B11: =SUMIFS(计提明细表!$I$4:$I$59,计提明细表!$C$4:$C$59,A11) | C11: =SUMIFS(计提明细表!$I$4:$I$59,计提明细表!$C$4:$C$59,$A11,计提明细表!$B$4:$B$59,"深圳星期零",计提明细表!$J$4:$J$59,0.09) | D11: =SUMIFS(计提明细表!$I$4:$I$59,计提明细表!$C$4:$C$59,$A11,计提明细表!$B$4:$B$59,"深圳星期零",计提明细表!$J$4:$J$59,0.06) | E11: =SUMIFS(计提明细表!$I$4:$I$59,计提明细表!$C$4:$C$59,$A11,计提明细表!$B$4:$B$59,"深圳星期零",计提明细表!$J$4:$J$59,0.13) | F11: =SUMIFS(计提明细表!$I$4:$I$59,计提明细表!$C$4:$C$59,$A11,计提明细表!$B$4:$B$59,"孝感星期九",计提明细表!$J$4:$J$59,0.09) | G11: =SUMIFS(计提明细表!$I$4:$I$59,计提明细表!$C$4:$C$59,$A11,计提明细表!$B$4:$B$59,"孝感星期九",计提明细表!$J$4:$J$59,0.06) | H11: =SUMIFS(计提明细表!$I$4:$I$59,计提明细表!$C$4:$C$59,$A11,计提明细表!$B$4:$B$59,"孝感星期九",计提明细表!$J$4:$J$59,0.13) | I11: =SUMIFS(计提明细表!$I$4:$I$59,计提明细表!$C$4:$C$59,$A11,计提明细表!$B$4:$B$59,"深圳星期九",计提明细表!$J$4:$J$59,0.09) | J11: =SUMIFS(计提明细表!$I$4:$I$59,计提明细表!$C$4:$C$59,$A11,计提明细表!$B$4:$B$59,"深圳星期九",计提明细表!$J$4:$J$59,0.06) | K11: =SUMIFS(计提明细表!$I$4:$I$59,计提明细表!$C$4:$C$59,$A11,计提明细表!$B$4:$B$59,"深圳星期九",计提明细表!$J$4:$J$59,0.13)
A12: 路凯（13%） | B12: =SUMIFS(计提明细表!$I$4:$I$59,计提明细表!$C$4:$C$59,A12) | C12: =SUMIFS(计提明细表!$I$4:$I$59,计提明细表!$C$4:$C$59,$A12,计提明细表!$B$4:$B$59,"深圳星期零",计提明细表!$J$4:$J$59,0.09) | D12: =SUMIFS(计提明细表!$I$4:$I$59,计提明细表!$C$4:$C$59,$A12,计提明细表!$B$4:$B$59,"深圳星期零",计提明细表!$J$4:$J$59,0.06) | E12: =SUMIFS(计提明细表!$I$4:$I$59,计提明细表!$C$4:$C$59,$A12,计提明细表!$B$4:$B$59,"深圳星期零",计提明细表!$J$4:$J$59,0.13) | F12: =SUMIFS(计提明细表!$I$4:$I$59,计提明细表!$C$4:$C$59,$A12,计提明细表!$B$4:$B$59,"孝感星期九",计提明细表!$J$4:$J$59,0.09) | G12: =SUMIFS(计提明细表!$I$4:$I$59,计提明细表!$C$4:$C$59,$A12,计提明细表!$B$4:$B$59,"孝感星期九",计提明细表!$J$4:$J$59,0.06) | H12: =SUMIFS(计提明细表!$I$4:$I$59,计提明细表!$C$4:$C$59,$A12,计提明细表!$B$4:$B$59,"孝感星期九",计提明细表!$J$4:$J$59,0.13) | I12: =SUMIFS(计提明细表!$I$4:$I$59,计提明细表!$C$4:$C$59,$A12,计提明细表!$B$4:$B$59,"深圳星期九",计提明细表!$J$4:$J$59,0.09) | J12: =SUMIFS(计提明细表!$I$4:$I$59,计提明细表!$C$4:$C$59,$A12,计提明细表!$B$4:$B$59,"深圳星期九",计提明细表!$J$4:$J$59,0.06) | K12: =SUMIFS(计提明细表!$I$4:$I$59,计提明细表!$C$4:$C$59,$A12,计提明细表!$B$4:$B$59,"深圳星期九",计提明细表!$J$4:$J$59,0.13)
A13: 中通快运 | B13: =SUMIFS(计提明细表!$I$4:$I$59,计提明细表!$C$4:$C$59,A13) | C13: =SUMIFS(计提明细表!$I$4:$I$59,计提明细表!$C$4:$C$59,$A13,计提明细表!$B$4:$B$59,"深圳星期零",计提明细表!$J$4:$J$59,0.09) | D13: =SUMIFS(计提明细表!$I$4:$I$59,计提明细表!$C$4:$C$59,$A13,计提明细表!$B$4:$B$59,"深圳星期零",计提明细表!$J$4:$J$59,0.06) | E13: =SUMIFS(计提明细表!$I$4:$I$59,计提明细表!$C$4:$C$59,$A13,计提明细表!$B$4:$B$59,"深圳星期零",计提明细表!$J$4:$J$59,0.13) | F13: =SUMIFS(计提明细表!$I$4:$I$59,计提明细表!$C$4:$C$59,$A13,计提明细表!$B$4:$B$59,"孝感星期九",计提明细表!$J$4:$J$59,0.09) | G13: =SUMIFS(计提明细表!$I$4:$I$59,计提明细表!$C$4:$C$59,$A13,计提明细表!$B$4:$B$59,"孝感星期九",计提明细表!$J$4:$J$59,0.06) | H13: =SUMIFS(计提明细表!$I$4:$I$59,计提明细表!$C$4:$C$59,$A13,计提明细表!$B$4:$B$59,"孝感星期九",计提明细表!$J$4:$J$59,0.13) | I13: =SUMIFS(计提明细表!$I$4:$I$59,计提明细表!$C$4:$C$59,$A13,计提明细表!$B$4:$B$59,"深圳星期九",计提明细表!$J$4:$J$59,0.09) | J13: =SUMIFS(计提明细表!$I$4:$I$59,计提明细表!$C$4:$C$59,$A13,计提明细表!$B$4:$B$59,"深圳星期九",计提明细表!$J$4:$J$59,0.06) | K13: =SUMIFS(计提明细表!$I$4:$I$59,计提明细表!$C$4:$C$59,$A13,计提明细表!$B$4:$B$59,"深圳星期九",计提明细表!$J$4:$J$59,0.13)
A14: 极鲜达 | B14: =SUMIFS(计提明细表!$I$4:$I$59,计提明细表!$C$4:$C$59,A14) | C14: =SUMIFS(计提明细表!$I$4:$I$59,计提明细表!$C$4:$C$59,$A14,计提明细表!$B$4:$B$59,"深圳星期零",计提明细表!$J$4:$J$59,0.09) | D14: =SUMIFS(计提明细表!$I$4:$I$59,计提明细表!$C$4:$C$59,$A14,计提明细表!$B$4:$B$59,"深圳星期零",计提明细表!$J$4:$J$59,0.06) | E14: =SUMIFS(计提明细表!$I$4:$I$59,计提明细表!$C$4:$C$59,$A14,计提明细表!$B$4:$B$59,"深圳星期零",计提明细表!$J$4:$J$59,0.13) | F14: =SUMIFS(计提明细表!$I$4:$I$59,计提明细表!$C$4:$C$59,$A14,计提明细表!$B$4:$B$59,"孝感星期九",计提明细表!$J$4:$J$59,0.09) | G14: =SUMIFS(计提明细表!$I$4:$I$59,计提明细表!$C$4:$C$59,$A14,计提明细表!$B$4:$B$59,"孝感星期九",计提明细表!$J$4:$J$59,0.06) | H14: =SUMIFS(计提明细表!$I$4:$I$59,计提明细表!$C$4:$C$59,$A14,计提明细表!$B$4:$B$59,"孝感星期九",计提明细表!$J$4:$J$59,0.13) | I14: =SUMIFS(计提明细表!$I$4:$I$59,计提明细表!$C$4:$C$59,$A14,计提明细表!$B$4:$B$59,"深圳星期九",计提明细表!$J$4:$J$59,0.09) | J14: =SUMIFS(计提明细表!$I$4:$I$59,计提明细表!$C$4:$C$59,$A14,计提明细表!$B$4:$B$59,"深圳星期九",计提明细表!$J$4:$J$59,0.06) | K14: =SUMIFS(计提明细表!$I$4:$I$59,计提明细表!$C$4:$C$59,$A14,计提明细表!$B$4:$B$59,"深圳星期九",计提明细表!$J$4:$J$59,0.13)
A15: 丰源 | B15: =SUMIFS(计提明细表!$I$4:$I$59,计提明细表!$C$4:$C$59,A15) | C15: =SUMIFS(计提明细表!$I$4:$I$59,计提明细表!$C$4:$C$59,$A15,计提明细表!$B$4:$B$59,"深圳星期零",计提明细表!$J$4:$J$59,0.09) | D15: =SUMIFS(计提明细表!$I$4:$I$59,计提明细表!$C$4:$C$59,$A15,计提明细表!$B$4:$B$59,"深圳星期零",计提明细表!$J$4:$J$59,0.06) | E15: =SUMIFS(计提明细表!$I$4:$I$59,计提明细表!$C$4:$C$59,$A15,计提明细表!$B$4:$B$59,"深圳星期零",计提明细表!$J$4:$J$59,0.13) | F15: =SUMIFS(计提明细表!$I$4:$I$59,计提明细表!$C$4:$C$59,$A15,计提明细表!$B$4:$B$59,"孝感星期九",计提明细表!$J$4:$J$59,0.09) | G15: =SUMIFS(计提明细表!$I$4:$I$59,计提明细表!$C$4:$C$59,$A15,计提明细表!$B$4:$B$59,"孝感星期九",计提明细表!$J$4:$J$59,0.06) | H15: =SUMIFS(计提明细表!$I$4:$I$59,计提明细表!$C$4:$C$59,$A15,计提明细表!$B$4:$B$59,"孝感星期九",计提明细表!$J$4:$J$59,0.13) | I15: =SUMIFS(计提明细表!$I$4:$I$59,计提明细表!$C$4:$C$59,$A15,计提明细表!$B$4:$B$59,"深圳星期九",计提明细表!$J$4:$J$59,0.09) | J15: =SUMIFS(计提明细表!$I$4:$I$59,计提明细表!$C$4:$C$59,$A15,计提明细表!$B$4:$B$59,"深圳星期九",计提明细表!$J$4:$J$59,0.06) | K15: =SUMIFS(计提明细表!$I$4:$I$59,计提明细表!$C$4:$C$59,$A15,计提明细表!$B$4:$B$59,"深圳星期九",计提明细表!$J$4:$J$59,0.13)
... A25: 货拉拉 | B25: =SUMIFS(计提明细表!$I$4:$I$59,计提明细表!$C$4:$C$59,A25) | C25: =SUMIFS(计提明细表!$I$4:$I$59,计提明细表!$C$4:$C$59,$A25,计提明细表!$B$4:$B$59,"深圳星期零",计提明细表!$J$4:$J$59,0.09) | D25: =SUMIFS(计提明细表!$I$4:$I$59,计提明细表!$C$4:$C$59,$A25,计提明细表!$B$4:$B$59,"深圳星期零",计提明细表!$J$4:$J$59,0.06) | E25: =SUMIFS(计提明细表!$I$4:$I$59,计提明细表!$C$4:$C$59,$A25,计提明细表!$B$4:$B$59,"深圳星期零",计提明细表!$J$4:$J$59,0.13) | F25: =SUMIFS(计提明细表!$I$4:$I$59,计提明细表!$C$4:$C$59,$A25,计提明细表!$B$4:$B$59,"孝感星期九",计提明细表!$J$4:$J$59,0.09) | G25: =SUMIFS(计提明细表!$I$4:$I$59,计提明细表!$C$4:$C$59,$A25,计提明细表!$B$4:$B$59,"孝感星期九",计提明细表!$J$4:$J$59,0.06) | H25: =SUMIFS(计提明细表!$I$4:$I$59,计提明细表!$C$4:$C$59,$A25,计提明细表!$B$4:$B$59,"孝感星期九",计提明细表!$J$4:$J$59,0.13) | I25: =SUMIFS(计提明细表!$I$4:$I$59,计提明细表!$C$4:$C$59,$A25,计提明细表!$B$4:$B$59,"深圳星期九",计提明细表!$J$4:$J$59,0.09) | J25: =SUMIFS(计提明细表!$I$4:$I$59,计提明细表!$C$4:$C$59,$A25,计提明细表!$B$4:$B$59,"深圳星期九",计提明细表!$J$4:$J$59,0.06) | K25: =SUMIFS(计提明细表!$I$4:$I$59,计提明细表!$C$4:$C$59,$A25,计提明细表!$B$4:$B$59,"深圳星期九",计提明细表!$J$4:$J$59,0.13)
A26: 合计 | B26: =SUM(B4:B25) | C26: =SUM(C4:C25) | D26: =SUM(D4:D25) | E26: =SUM(E4:E25) | F26: =SUM(F4:F25) | G26: =SUM(G4:G25) | H26: =SUM(H4:H25) | I26: =SUM(I4:I25) | ... K26: =SUM(K4:K25)
A28: 核对:含税合计列总计应=计提明细表 I60 合计;差异非0说明明细表有汇总表未覆盖的物流商(简称不在③清单)。
A29: =B26-计提明细表!$I$60 | B29: ←此格应为 0

Sheet 费用归属表（快照）
A1: 费用归属表(快照)——13类费用归属→费用项目/科目/部门/摘要用语。工具映射维表签发,财务改口径请改工具页面
A2: 主规则(默认行,一类一行,科目唯一)
A3: 费用归属 | B3: 费用项目 | C3: 借方科目 | D3: 默认部门 | E3: 贷方科目 | F3: 摘要用语 | G3: 典型场景
A4: 销售出库费用 | B4: 出库运费 FYXM008.002其他物流费用002 | C4: 6601 销售费用 | D4: 永续物流中心 0011401 | E4: 2241.02 其他应付款—供应商往来 | F4: 出库运费 | G4: 各线销售发货(装卸费未单列时含在内)
A5: 成品入库费用 | B5: 入库运费 FYXM002.002运费成本002 | C5: 6401 主营业务成本 | D5: 仓储物流部 0030301 | E5: 2241.02 其他应付款—供应商往来 | F5: 成品入库运费 | G5: 代工厂成品回仓、电商仓成品入仓
A6: 原料入库费用 | B6: 入库运费 FYXM002.002运费成本002 | C6: 5101 制造费用 | D6: 仓储物流部 0030301 | E6: 2241.02 其他应付款—供应商往来 | F6: 原料入库运费 | G6: 孝感工厂采购入库到付、小料原料入库(小料例外→茶饮小料部,公式/映射自动)
A7: 成品仓储费用 | B7: 货物仓储费 FYXM008.002其他物流费用001 | C7: 6601 销售费用 | D7: 永续物流中心 0011401 | E7: 2241.02 其他应付款—供应商往来 | F7: 成品仓储费 | G7: 小料/电商外仓、鲜食山姆仓
A8: 原料仓储费用 | B8: 货物仓储费 FYXM008.002其他物流费用001 | C8: 5101 制造费用 | D8: 仓储物流部 0030301 | E8: 2241.02 其他应付款—供应商往来 | F8: 原料仓储费 | G8: 木薯外仓仓储
A9: 成品调拨费用 | B9: 出库运费 FYXM008.002其他物流费用002 | C9: 6601 销售费用 | D9: 永续物流中心 0011401 | E9: 2241.02 其他应付款—供应商往来 | F9: 调拨运费 | G9: 成品仓间调拨、电商调拨
A10: 原料调拨费用 | B10: 入库运费 FYXM002.002运费成本002 | C10: 5101 制造费用 | D10: 仓储物流部 0030301 | E10: 2241.02 其他应付款—供应商往来 | F10: 调拨运费 | G10: 原料转仓
A11: 出库装卸费用 | B11: 出库运费 FYXM008.002其他物流费用002 | C11: 6601 销售费用 | D11: 永续物流中心 0011401 | E11: 2241.02 其他应付款—供应商往来 | F11: 装卸费 | G11: 天鹰:发货装车(账单单列才拆)
A12: 成品入库装卸费用 | B12: 入库运费 FYXM002.002运费成本002 | C12: 6401 主营业务成本 | D12: 仓储物流部 0030301 | E12: 2241.02 其他应付款—供应商往来 | F12: 装卸费 | G12: 天鹰:外仓成品调回卸货
A13: 原料入库装卸费用 | B13: 入库运费 FYXM002.002运费成本002 | C13: 5101 制造费用 | D13: 仓储物流部 0030301 | E13: 2241.02 其他应付款—供应商往来 | F13: 装卸费 | G13: 天鹰:原料卸货
A14: 研发设备采购 | B14: 研发外购 FYXM005.002研发费用001 | C14: 6604 研发费用 | D14: 永续研发中心 0010506 | E14: 2241.02 其他应付款—供应商往来 | F14: 研发运费 | G14: 研发外购、研发中试
... A16: 其它 | B16: ⚠待财务定 | C16: 🖐逐笔人工定(录入时财务选) | D16: 🖐逐笔人工定(按需求) | E16: 2241.02 其他应付款—供应商往来 | F16: 费用 | G16: 捐赠/报废、原料销售运费等兜底
A18: 例外行(三级取数:费用归属×主体 / 费用归属×业务线 覆盖默认行)
A19: 费用归属 | B19: 例外条件 | C19: 覆盖项 | D19: 覆盖值 | E19: 来源
A20: 销售出库费用 | B20: 主体=深圳星期九 | C20: 部门 | D20: 永续供应中心 0010401 | E20: A期序时账实证
A21: 原料入库费用 | B21: 小料(业务线=小料) | C21: 部门 | D21: 茶饮小料部 0030902(非小料=仓储物流部) | E21: 业务方批注 2026-08-05 确认
A24: 计提凭证三行结构(固定·一行一张凭证·真凭证实证)
A25: 借/贷 | B25: 科目 | C25: 金额 | D25: 核算维度
A26: 借 | B26: 费用科目(按费用归属,见主规则) | C26: 未税额 | D26: 部门+费用项目+产品分类(业务线)[+TO C]
A27: 借 | B27: 2221.01.07 应交税费—暂估进项税 | C27: 税额 | D27: 供应商
A28: 贷 | B28: 2241.02 其他应付款—供应商往来 | C28: 含税额 | D28: 供应商+供应商分组009(物流运输服务)
A30: 说明(维度实证=2026 序时账 1229 行物流计提凭证、30 种借方维度组合,2026-08-05 只读回查):
A31: · 产品维度按业务线挂:鲜食/山姆零售→CPXM017(账证:鲜食入库行也挂);kikiherb→CPFL013+CPXM022(6月顺鸽已入账,独立业务线);产品项目不止 TO C 一个值。
A32: · 仓储费部门按仓分(账证):孝感线下外仓(易风达等)→仓储物流部+挂孝感星期九簿;电商仓(比翼/顺鸽)/深零外仓→永续物流中心。明细表部门列可直接改。
A33: · 原料销售运费实拼(账证,丰源1-4月):6402 其他业务支出 + FYXM002.004其他产品成本费用009原辅料及包装物 + 仓储物流部——「其它」类的实证归宿之一(D-7)。
A34: · 🖐人工核对类=设备调拨/其它:科目部门不走自动映射,财务在明细表维度列或工具活表逐笔定(账证参考:设备转移深零→6604研发+搬运费/孝感→5101+搬运费)。
A35: · 判定速查(业务方批注):销售出库/仓储→有业务线维度即齐;原料入库(5101)→部门分小料(茶饮小料部)/非小料(仓储物流部);成品入库(6401)→维度按业务线区分。
A36: · ⚠成品6401/原料5101 口径、「其它」类科目——待财务终核(重构方案 D-4/D-7)。
A37: · 本表为工具「映射维表」页面的只读快照;改口径→财务在工具改,当月签发模板即生效。

Sheet 选项
A1: 付款主体 | B1: 业务线 | C1: 费用归属 | E1: 结算类型 | G1: 状态 | H1: 业务线 | I1: 产品分类编码 | J1: 产品项目编码
A2: 深圳星期零 | B2: 植物肉 | C2: 销售出库费用 | E2: 月结 | G2: 未开始 | H2: 植物肉 | I2: CPFL007
A3: 孝感星期九 | B3: 鲜食 | C3: 成品入库费用 | E3: 非月结 | G3: 已计提 | H3: 鲜食 | I3: CPFL010 | J3: CPXM017
A4: 深圳星期九 | B4: 零售 | C4: 原料入库费用 | G4: 对账定稿 | H4: 零售 | I4: CPFL011
B5: 小料 | C5: 成品仓储费用 | G5: 已开票 | H5: 小料 | I5: CPFL009
B6: 豆蛋制品 | C6: 原料仓储费用 | G6: 已请款 | H6: 豆蛋制品 | I6: CPFL008
B7: 电商 | C7: 成品调拨费用 | G7: 已付款 | H7: 电商 | I7: CPFL002
B8: 山姆零售 | C8: 原料调拨费用 | H8: 山姆零售 | I8: CPFL011 | J8: CPXM017
B9: kikiherb | C9: 出库装卸费用 | H9: kikiherb | I9: CPFL013 | J9: CPXM022
B10: 海外 | C10: 成品入库装卸费用 | H10: 海外
B11: — | C11: 原料入库装卸费用 | H11: —
C12: 研发设备采购
C13: 设备调拨费用
C14: 其它
